Workbook

Sheet Formosa
A1: Fornecedores | C1: =50000 -> 50000
A3: Rivoli | C3: 7872 | D3: 2 rendas
A4: Suvita | C4: 8866 | D4: 20% leasing
A5: Gastro | C5: 10205 | D5: Bancadas
A6: Sara | C6: 2700 | D6: Projeto
A7: Sklum | C7: 869 | D7: Mesas
A8: Aexperial | C8: 2937.73 | D8: Carapinas
A9: Decorestudio | C9: 526 | D9: Luminoso - 40% do valor total
A10: Protame | C10: 1878.38 | D10: POS Formosa
A11: Cutlab | C11: 1166.5 | D11: Vinil Recortado 583,25 + 583,25

Sheet BD_Movimentos
A1: Data | B1: Tipo | C1: Empresa | D1: Nome Comercial | E1: Fatura | F1: Valor Real | G1: Data Vencimento | H1: Estado | I1: Centro Custo | J1: Agen confir | K1: Data Pagamento | L1: Valor Prev. | M1: Descrição
A2: 45756 | B2: Pagamento | C2: yh6 | E2: FT25/575 | F2: -67.22 | H2: Pago | I2: Matosinhos | K2: 45782 | L2: =F2 -> -67.22
A3: 45128 | B3: Pagamento | C3: A Prestigiosa | E3: 5159 | F3: -99.26 | H3: Pago | L3: =F3 -> -99.26 | M3: coco
A4: 45194 | B4: Pagamento | C4: A prestigiosa | E4: FT23/6803 | F4: -34.42 | H4: Pago | L4: =F4 -> -34.42 | M4: Coco
A5: 45196 | B5: Pagamento | C5: A prestigiosa | E5: FT 23/6864 | F5: -127.5 | H5: Pago | L5: =F5 -> -127.5 | M5: Leite de coco
A6: 45259 | B6: Pagamento | C6: A prestigiosa | E6: FT 23/8170 | F6: -111.51 | H6: Pago | L6: =F6 -> -111.51 | M6: Coco
A7: 45341 | B7: Pagamento | C7: A Prestigiosa | E7: FT 24/10609 | F7: -180.1 | H7: Pago | L7: =F7 -> -180.1 | M7: Coco
A8: 45796 | B8: Pagamento | C8: A prestigiosa | E8: FT25/9513 | F8: -311 | H8: Pago | I8: Matosinhos | K8: 45796
A9: 45514 | B9: Pagamento | C9: ADENE | E9: FT 24/418287 | F9: -166.05 | H9: Pago | I9: Baixa | L9: =F9 -> -166.05 | M9: Taxa certificado energético - PT50 0035 0447 0005576690067
A10: 45812 | B10: Recebimento | C10: Abóbada Verde | E10: FA 1A2501/83 | F10: 75 | H10: Pago | I10: B2B | K10: 45819 | L10: =F10 -> 75
A11: 45303 | B11: Pagamento | C11: Aexperial | F11: -2937.73 | H11: Pago | L11: =F11 -> -2937.73 | M11: Carapinas
A12: 45786 | B12: Pagamento | C12: Aexperial | E12: PF 25/311 | F12: -1562.44 | H12: Pago | I12: Matosinhos | K12: 45789 | M12: Carapinas
A13: 45303 | B13: Pagamento | C13: Ageas | E13: 74548945 | F13: -15.23 | H13: Pago | L13: =F13 -> -15.23 | M13: Entidade: 23445 REF: 574889165 Valor: 15,23 /(até ao final do mês)
A14: 45784 | B14: Pagamento | C14: AGEAS | F14: -1590.79 | G14: 45787 | H14: Pago | I14: Matosinhos | K14: 45786 | L14: =F14 -> -1590.79 | M14: Apólice seguro A.Trabalho 20776 | 973 638 193
B15: Pagamento | C15: Aluguer garagem | F15: -400 | H15: Pago | I15: Matosinhos | K15: 45912 | M15: Renda Setembro e Outubro 25
A16: 45939 | B16: Pagamento | C16: AF System | E16: Orc25/185 | F16: -13000 | H16: Suspenso | I16: Produção | M16: Transf de sinal de 1500€ a 14/10/2025
A17: 45853 | B17: Pagamento | C17: Aluguer garagem | F17: -400 | H17: Pago | I17: Matosinhos | M17: Renda Julho e Agosto 25
A18: 45748 | B18: Pagamento | C18: Aluguer garagem | F18: -600 | H18: Pago | I18: Matosinhos | M18: Renda Abril, Maio, Junho 25
B19: Pagamento | C19: Aluguer garagem | F19: -400 | G19: 45962 | H19: Pago | I19: Matosinhos | K19: 45972 | M19: Renda Novembro e Dezembro 25
B20: Pagamento | C20: Aluguer garagem | F20: -400 | G20: 46023 | H20: Pago | I20: Matosinhos | K20: 46038 | L20: Renda Novembro e Dezembro 25 | M20: Renda Jan e Fev 2026
B21: Pagamento | C21: Aluguer garagem | F21: -400 | G21: 46082 | H21: Pago | I21: Matosinhos | K21: 46090 | L21: Renda Novembro e Dezembro 25 | M21: Renda Mar e Abr 2026
A22: 45566 | B22: Pagamento | C22: Ambiese | E22: FT 24/1735 | F22: -42.52 | H22: Pago | I22: Matosinhos | K22: 45454 | L22: =F22 -> -42.52 | M22: Detergentes
A23: 45587 | B23: Pagamento | C23: Ambiese | E23: FT 24/1860 | F23: -87.38 | H23: Pago | I23: Matosinhos | K23: 45454 | L23: =F23 -> -87.38 | M23: Detergentes
A24: 45595 | B24: Pagamento | C24: Ambiese | E24: FT 24/1916 | F24: -139.67 | H24: Pago | I24: Matosinhos | K24: 45454 | L24: =F24 -> -139.67 | M24: Detergentes
A25: 45601 | B25: Pagamento | C25: Ambiese | E25: FT24/1941 | F25: -152.34 | H25: Pago | I25: Matosinhos | K25: 45455 | L25: =F25 -> -152.34
A26: 45601 | B26: Pagamento | C26: Ambiese | E26: FT24/1948 | F26: -14.51 | H26: Pago | I26: Matosinhos | K26: 45455 | L26: =F26 -> -14.51
A27: 45608 | B27: Pagamento | C27: Ambiese | E27: FT24/1991 | F27: -21.27 | H27: Pago | I27: Matosinhos | K27: 45455 | L27: =F27 -> -21.27
A28: 45615 | B28: Pagamento | C28: Ambiese | E28: FT24/2034 | F28: -83.34 | G28: 45615 | H28: Pago | I28: Matosinhos | K28: 45455 | L28: =F28 -> -83.34
A29: 45622 | B29: Pagamento | C29: Ambiese | E29: FT24/2076 | F29: -33.1 | G29: 45622 | H29: Pago | I29: Matosinhos | K29: 45455 | L29: =F29 -> -33.1
A30: 45684 | B30: Pagamento | C30: Ambiese | E30: FT25/135 | F30: -114.43 | G30: 45684 | H30: Pago | I30: Matosinhos | K30: 45695 | L30: =F30 -> -114.43
A31: 45684 | B31: Pagamento | C31: Ambiese | E31: FT25/136 | F31: -21.84 | G31: 45684 | H31: Pago | I31: Matosinhos | K31: 45695 | L31: =F31 -> -21.84
A32: 45693 | B32: Pagamento | C32: Ambiese | E32: FT25/196 | F32: -61.27 | G32: 45693 | H32: Pago | I32: Matosinhos | K32: 45723 | L32: =F32 -> -61.27
A33: 45707 | B33: Pagamento | C33: Ambiese | E33: FT25/291 | F33: -52.85 | G33: 45735 | H33: Pago | I33: Matosinhos | K33: 45723 | L33: =F33 -> -52.85
A34: 45699 | B34: Pagamento | C34: Ambiese | E34: FT25/241 | F34: -21.99 | G34: 45727 | H34: Pago | I34: Matosinhos | K34: 45723 | L34: =F34 -> -21.99
A35: 45714 | B35: Pagamento | C35: Ambiese | E35: FT25/323 | F35: -92.79 | H35: Pago | I35: Matosinhos | K35: 45727 | L35: =F35 -> -92.79
A36: 45699 | B36: Pagamento | C36: Ambiese | E36: FT25/240 | F36: -33.17 | H36: Pago | I36: Bolhao | K36: 45751 | L36: =F36 -> -33.17
A37: 45713 | B37: Pagamento | C37: Ambiese | E37: FT25/322 | F37: -29.86 | H37: Pago | I37: Bolhão | K37: 45751 | L37: =F37 -> -29.86
A38: 45721 | B38: Pagamento | C38: Ambiese | E38: FT25/366 | F38: -106.49 | H38: Pago | I38: Matosinhos | K38: 45751 | L38: =F38 -> -106.49
A39: 45727 | B39: Pagamento | C39: Ambiese | E39: FT25/395 | F39: -33.17 | H39: Pago | I39: Bolhão | K39: 45751 | L39: =F39 -> -33.17
A40: 45727 | B40: Pagamento | C40: Ambiese | E40: FT25/394 | F40: -50.09 | H40: Pago | I40: Matosinhos | K40: 45751 | L40: =F40 -> -50.09
A41: 45734 | B41: Pagamento | C41: Ambiese | E41: FT25/438 | F41: -52.85 | H41: Pago | I41: Matosinhos | K41: 45751 | L41: =F41 -> -52.85
A42: 45741 | B42: Pagamento | C42: Ambiese | E42: FT25/480 | F42: -55.17 | G42: 45771 | H42: Pago | I42: Matosinhos | K42: 45771 | L42: =F42 -> -55.17
A43: 45741 | B43: Pagamento | C43: Ambiese | E43: FT25/479 | F43: -17.13 | G43: 45771 | H43: Pago | I43: Bolhao | K43: 45771 | L43: =F43 -> -17.13
A44: 374466 | B44: Pagamento | C44: Ambiese | E44: FT25/519 | F44: -111.35 | H44: Pago | I44: Matosinhos | K44: 45782 | L44: =F44 -> -111.35
A45: 45762 | B45: Pagamento | C45: Ambiese | E45: FT25/595 | F45: -38.03 | H45: Pago | I45: Bolhao | K45: 45782 | L45: =F45 -> -38.03 | M45: Pago em duplicado. Abti o valor na FT25/673
A46: 45762 | B46: Pagamento | C46: Ambiese | E46: FT25/594 | F46: -98.76 | H46: Pago | I46: Matosinhos | K46: 45782 | L46: =F46 -> -98.76
A47: 45762 | B47: Pagamento | C47: Ambiese | E47: FT25/595 | F47: -38.03 | H47: Pago | I47: Bolhão | K47: 45782
A48: 45770 | B48: Pagamento | C48: Ambiese | E48: FT25/632 | F48: -39.13 | H48: Pago | I48: Matosinhos | K48: 45782
A49: 45776 | B49: Pagamento | C49: Ambiese | E49: FT25/668 | F49: -175.39 | H49: Pago | I49: Matosinhos | K49: 45782
A50: 45782 | B50: Pagamento | C50: Ambiese | E50: FT25/700 | F50: -134.44 | G50: 45812 | H50: Pago | I50: Matosinhos | K50: 45803 | L50: =F50 -> -134.44
A51: 45776 | B51: Pagamento | C51: Ambiese | E51: FT25/673 | F51: =-(66.12-38.03) -> -28.09 | G51: 45812 | H51: Pago | I51: Bolhao | K51: 45803 | L51: =F51 -> -28.09 | M51: Abater 38,03 FT 595 paga em duplicado
A52: 45789 | B52: Pagamento | C52: Ambiese | E52: FT25/741 | F52: -79.08 | H52: Pago | I52: Bolhao | K52: 45803
A53: 45789 | B53: Pagamento | C53: Ambiese | E53: FT25/742 | F53: -106.49 | H53: Pago | I53: Matosinhos | K53: 45803
A54: 45629 | B54: Pagamento | C54: Ambiese | E54: FT24/2110 | F54: -49.66 | G54: =IF(OR(C54="Matosinhos",C54="Bolhão"),A54,A54+30) -> 45659 | H54: Pago | I54: Matosinhos | K54: 45901 | L54: =F54 -> -49.66
A55: 45635 | B55: Pagamento | C55: Ambiese | E55: FT24/2141 | F55: -104.57 | G55: =IF(OR(C55="Matosinhos",C55="Bolhão"),A55,A55+30) -> 45665 | H55: Pago | I55: Matosinhos | K55: 45901 | L55: =F55 -> -104.57
A56: 45643 | B56: Pagamento | C56: Ambiese | E56: FT24/2195 | F56: -81.51 | G56: =IF(OR(C56="Matosinhos",C56="Bolhão"),A56,A56+30) -> 45673 | H56: Pago | I56: Matosinhos | K56: 45901 | L56: =F56 -> -81.51
A57: 45656 | B57: Pagamento | C57: Ambiese | E57: FT24/2246 | F57: -139.7 | G57: =IF(OR(C57="Matosinhos",C57="Bolhão"),A57,A57+30) -> 45686 | H57: Pago | I57: Matosinhos | K57: 45901 | L57: =F57 -> -139.7
A58: 45103 | B58: Pagamento | C58: Ambiese | E58: 1213 | F58: -109.64 | H58: Pago | I58: Matosinhos | L58: =F58 -> -109.64 | M58: NC 12 - 30,44€
A59: 45119 | B59: Pagamento | C59: Ambiese | E59: 1351 | F59: -123.2 | H59: Pago | I59: Matosinhos | L59: =F59 -> -123.2 | M59: NC 13 - 10,15€
A60: 45133 | B60: Pagamento | C60: Ambiese | E60: 1439 | F60: -75.26 | H60: Pago | I60: Matosinhos | L60: =F60 -> -75.26
A61: 45161 | B61: Pagamento | C61: Ambiese | E61: FT 23/1579 | F61: -118.09 | H61: Pago | I61: Matosinhos | L61: =F61 -> -118.09 | M61: Detergentes
A62: 45173 | B62: Pagamento | C62: Ambiese | E62: FT 23/1643 | F62: -49.14 | H62: Pago | I62: Matosinhos | L62: =F62 -> -49.14 | M62: Detergentes
A63: 45183 | B63: Pagamento | C63: Ambiese | E63: FT 23/1731 | F63: -8.92 | H63: Pago | I63: Matosinhos | L63: =F63 -> -8.92 | M63: Detergentes
A64: 45188 | B64: Pagamento | C64: Ambiese | E64: FT 23/1763 | F64: -11.69 | H64: Pago | I64: Matosinhos | L64: =F64 -> -11.69 | M64: Detergentes
A65: 45203 | B65: Pagamento | C65: Ambiese | E65: FT 23/1866 | F65: -16.24 | H65: Pago | I65: Matosinhos | L65: =F65 -> -16.24 | M65: Detergentes
A66: 45217 | B66: Pagamento | C66: Ambiese | E66: FT 23/1950 | F66: -57.96 | H66: Pago | I66: Matosinhos | L66: =F66 -> -57.96 | M66: Detergentes
A67: 45236 | B67: Pagamento | C67: Ambiese | E67: FT 23/2068 | F67: -27.98 | H67: Pago | I67: Matosinhos | L67: =F67 -> -27.98 | M67: Detergentes
A68: 45244 | B68: Pagamento | C68: Ambiese | E68: FT 23/2122 | F68: -13.47 | H68: Pago | I68: Matosinhos | L68: =F68 -> -13.47 | M68: Detergentes - NC 20
A69: 45245 | B69: Pagamento | C69: Ambiese | E69: FT 23/2150 | F69: -4.55 | H69: Pago | I69: Matosinhos | L69: =F69 -> -4.55 | M69: Detergentes
A70: 45245 | B70: Pagamento | C70: Ambiese | E70: FT 23/2149 | F70: -40.25 | H70: Pago | I70: Matosinhos | L70: =F70 -> -40.25 | M70: Detergentes
A71: 45251 | B71: Pagamento | C71: Ambiese | E71: FT 23/2183 | F71: -49.35 | H71: Pago | I71: Matosinhos | L71: =F71 -> -49.35 | M71: Detergentes
A72: 45258 | B72: Pagamento | C72: Ambiese | E72: FT 23/2234 | F72: -33.39 | H72: Pago | I72: Matosinhos | L72: =F72 -> -33.39 | M72: Detergentes
... A93: 45404 | B93: Pagamento | C93: Ambiese | E93: FT 24/714 | F93: -74.76 | H93: Pago | I93: Matosinhos | L93: =F93 -> -74.76 | M93: Detergentes
A94: 45465 | B94: Recebimento | C94: Alexandre Batata | D94: Alex | E94: FT 1A2401/43 | F94: 200 | G94: =A94+30 -> 45495 | H94: Por pagar | I94: Eventos | L94: =F94 -> 200 | M94: 274500160
A95: 45901 | B95: Recebimento | C95: André branquinho | D95: André branquinho | E95: FA 1A2501/148 | F95: 340 | H95: Pago | I95: Eventos | K95: 45908
A96: 45818 | B96: Recebimento | C96: Antónia Almeida (Ferpinta) | D96: Ferpinta | E96: FA1A2501/89 | F96: 670 | H96: Pago | I96: B2B | K96: 45820 | L96: =F96 -> 670
A97: 45411 | B97: Pagamento | C97: Ambiese | E97: FT 24/757 | F97: -128.38 | H97: Pago | I97: Matosinhos | L97: =F97 -> -128.38 | M97: Detergentes
A98: 45419 | B98: Pagamento | C98: Ambiese | E98: FT 24/813 | F98: -77.71 | H98: Pago | I98: Matosinhos | J98: 45448 | L98: =F98 -> -77.71 | M98: Detergentes ( NC 12 / da FT 24/757)
A99: 45426 | B99: Pagamento | C99: Ambiese | E99: FT 24/856 | F99: -79.47 | H99: Pago | I99: Matosinhos | J99: 45448 | L99: =F99 -> -79.47 | M99: Detergentes
A100: 45432 | B100: Pagamento | C100: Ambiese | E100: FT 24/892 | F100: -64.96 | H100: Pago | I100: Matosinhos | J100: 45448 | L100: =F100 -> -64.96 | M100: Detergentes
A101: 45439 | B101: Pagamento | C101: Ambiese | E101: FT 24/936 | F101: -64.96 | H101: Pago | I101: Matosinhos | J101: 45448 | L101: =F101 -> -64.96 | M101: Detergentes
A102: 45448 | B102: Pagamento | C102: Ambiese | E102: FT 24/992 | F102: -119.14 | H102: Pago | L102: =F102 -> -119.14 | M102: Detergentes
A103: 45449 | B103: Pagamento | C103: Ambiese | E103: FT 24/241 | F103: -60.25 | H103: Pago | I103: Matosinhos | L103: =F103 -> -60.25 | M103: Papel
A104: 45456 | B104: Pagamento | C104: Ambiese | E104: FT 24/1035 | F104: -31.71 | H104: Pago | L104: =F104 -> -31.71 | M104: Detergentes
A105: 45456 | B105: Pagamento | C105: Ambiese | E105: FT 24/1026 | F105: -125.84 | H105: Pago | L105: =F105 -> -125.84 | M105: Detergentes
A106: 45461 | B106: Pagamento | C106: Ambiese | E106: FT 24/1065 | F106: -96.8 | H106: Pago | L106: =F106 -> -96.8 | M106: Detergentes
A107: 45468 | B107: Pagamento | C107: Ambiese | E107: FT 24/1098 | F107: -37.81 | H107: Pago | L107: =F107 -> -37.81 | M107: Detergentes
A108: 45475 | B108: Pagamento | C108: Ambiese | E108: FT 24/1160 | F108: -83.36 | H108: Pago | L108: =F108 -> -83.36 | M108: Detergentes
A109: 45481 | B109: Pagamento | C109: Ambiese | E109: FT 24/1208 | F109: -48.41 | H109: Pago | L109: =F109 -> -48.41 | M109: Detergentes
A110: 45489 | B110: Pagamento | C110: Ambiese | E110: FT 24/1258 | F110: -64.96 | H110: Pago | L110: =F110 -> -64.96 | M110: Detergentes
A111: 45496 | B111: Pagamento | C111: Ambiese | E111: FT 24/1309 | F111: -122.56 | H111: Pago | L111: =F111 -> -122.56 | M111: Detergentes
A112: 45498 | B112: Pagamento | C112: Ambiese | E112: FT 24/1326 | F112: -49.66 | H112: Pago | L112: =F112 -> -49.66 | M112: Detergentes
A113: 45503 | B113: Pagamento | C113: Ambiese | E113: FT 24/1344 | F113: -43.7 | H113: Pago | L113: =F113 -> -43.7 | M113: Detergentes
A114: 45505 | B114: Pagamento | C114: Ambiese | E114: FT 24/1369 | F114: -33.1 | H114: Pago | I114: Matosinhos | L114: =F114 -> -33.1 | M114: Papel
A115: 45510 | B115: Pagamento | C115: Ambiese | E115: FT 24/1405 | F115: -93.42 | H115: Pago | I115: Matosinhos | L115: =F115 -> -93.42 | M115: Detergentes
A116: 45511 | B116: Pagamento | C116: Ambiese | E116: FT 24/1420 | F116: -81.43 | H116: Pago | I116: Matosinhos | L116: =F116 -> -81.43 | M116: Papel
A117: 45516 | B117: Pagamento | C117: Ambiese | E117: FT 24/1438 | F117: -152.34 | H117: Pago | I117: Matosinhos | L117: =F117 -> -152.34 | M117: Papel
A118: 45517 | B118: Pagamento | C118: Ambiese | E118: FT 24/1456 | F118: -9.42 | H118: Pago | I118: Matosinhos | L118: =F118 -> -9.42 | M118: Detergentes
A119: 45524 | B119: Pagamento | C119: Ambiese | E119: FT 24/1474 | F119: -74.76 | H119: Pago | I119: Matosinhos | L119: =F119 -> -74.76 | M119: Detergente/papel
A120: 45530 | B120: Pagamento | C120: Ambiese | E120: FT 24/1505 | F120: -121.06 | H120: Pago | I120: Baixa | L120: =F120 -> -121.06 | M120: Toalheiros
...

Sheet Fundo de Caixa
A1: Valor | B1: Qt | C1: Total | I1: Valor | J1: Qt | K1: Total | M1: Fundo Maneio MAT | O1: 45656 | Q1: Fundo Maneio BOLH | S1: 45659
A2: 0.01 | B2: 277 | C2: =B2*A2 -> 2.77 | I2: 0.01 | K2: =J2*I2 -> 0 | M2: Valor | N2: Qt | O2: Total | Q2: Valor | R2: Qt | S2: Total
A3: 0.02 | B3: 62 | C3: =B3*A3 -> 1.24 | I3: 0.02 | K3: =J3*I3 -> 0 | M3: 0.01 | O3: =N3*M3 -> 0 | Q3: 0.01 | S3: =R3*Q3 -> 0
A4: 0.05 | B4: 4 | C4: =B4*A4 -> 0.2 | I4: 0.05 | K4: =J4*I4 -> 0 | M4: 0.02 | N4: 51 | O4: =N4*M4 -> 1.02 | Q4: 0.02 | S4: =R4*Q4 -> 0
A5: 0.1 | B5: 21 | C5: =B5*A5 -> 2.1 | I5: 0.1 | K5: =J5*I5 -> 0 | M5: 0.05 | O5: =N5*M5 -> 0 | Q5: 0.05 | S5: =R5*Q5 -> 0
A6: 0.2 | B6: 0 | C6: =B6*A6 -> 0 | E6: fundo n+1 | F6: =F8+35 -> 86.31 | I6: 0.2 | K6: =J6*I6 -> 0 | M6: 0.1 | N6: 56 | O6: =N6*M6 -> 5.6 | Q6: 0.1 | S6: =R6*Q6 -> 0
A7: 0.5 | B7: 2 | C7: =B7*A7 -> 1 | I7: 0.5 | K7: =J7*I7 -> 0 | M7: 0.2 | N7: 43 | O7: =N7*M7 -> 8.6 | Q7: 0.2 | S7: =R7*Q7 -> 0
A8: 1 | B8: 30 | C8: =B8*A8 -> 30 | E8: Moedas | F8: =SUM(C2:C9) -> 51.31 | I8: 1 | K8: =J8*I8 -> 0 | M8: 0.5 | N8: 1 | O8: =N8*M8 -> 0.5 | Q8: 0.5 | S8: =R8*Q8 -> 0
A9: 2 | B9: 7 | C9: =B9*A9 -> 14 | E9: Notas | F9: =SUM(C10:C16) -> 0 | I9: 2 | K9: =J9*I9 -> 0 | M9: 1 | N9: 2 | O9: =N9*M9 -> 2 | Q9: 1 | S9: =R9*Q9 -> 0
A10: 5 | B10: 0 | C10: =B10*A10 -> 0 | E10: Total | F10: =C17 -> 51.31 | I10: 5 | K10: =J10*I10 -> 0 | M10: 2 | N10: 1 | O10: =N10*M10 -> 2 | Q10: 2 | S10: =R10*Q10 -> 0
A11: 10 | B11: 0 | C11: =B11*A11 -> 0 | E11: fundo cx | F11: 72.75 | I11: 10 | J11: 21 | K11: =J11*I11 -> 210 | M11: 5 | N11: 5 | O11: =N11*M11 -> 25 | Q11: 5 | S11: =R11*Q11 -> 0
A12: 20 | B12: 0 | C12: =B12*A12 -> 0 | E12: Numerário | F12: =F10-F11 -> -21.44 | I12: 20 | J12: 28 | K12: =J12*I12 -> 560 | M12: 10 | N12: 9 | O12: =N12*M12 -> 90 | Q12: 10 | S12: =R12*Q12 -> 0
A13: 50 | B13: 0 | C13: =B13*A13 -> 0 | I13: 50 | J13: 2 | K13: =J13*I13 -> 100 | M13: 20 | N13: 2 | O13: =N13*M13 -> 40 | Q13: 20 | S13: =R13*Q13 -> 0
A14: 100 | B14: 0 | C14: =B14*A14 -> 0 | I14: 100 | K14: =J14*I14 -> 0 | M14: 50 | O14: =N14*M14 -> 0 | Q14: 50 | S14: =R14*Q14 -> 0
A15: 200 | B15: 0 | C15: =B15*A15 -> 0 | I15: 200 | K15: =J15*I15 -> 0 | M15: 100 | O15: =N15*M15 -> 0 | Q15: 100 | S15: =R15*Q15 -> 0
A16: 500 | B16: 0 | C16: =B16*A16 -> 0 | E16: =355-35 -> 320 | I16: 500 | K16: =J16*I16 -> 0 | M16: 200 | O16: =N16*M16 -> 0 | Q16: 200 | S16: =R16*Q16 -> 0
C17: =SUM(C2:C16) -> 51.31 | K17: =SUM(K2:K16) -> 870 | M17: 500 | O17: =N17*M17 -> 0 | Q17: 500 | S17: =R17*Q17 -> 0
O18: =SUM(O3:O17) -> 174.72 | S18: =SUM(S3:S17) -> 0
S19: 38.21

Sheet Depositos Matosinhos
A1: Dia | B1: Deposito | C1: Num | E1: Pagamentos | F1: Comentario
A2: 44813 | B2: 4575
A3: 44814 | C3: =Setembro!N11 -> 504.8
A4: 44815 | C4: =Setembro!N12 -> 575.93 | D4: 566.33 | F4: O total do multibanco tinha um valor inferior ao registado de 9,60€, compensou no numerário
A5: 44816 | C5: =Setembro!N13 -> 0
A6: 44817 | C6: =Setembro!N14 -> 70.1 | E6: =105.66+68.14+200.88+66 -> 440.68 | F6: Makro (FT023560/033862/027982) / Frutas ( FT 1222)
A7: 44818 | C7: =Setembro!N15 -> 197.82 | E7: 160 | F7: MagoFri (FT 25037/26835/27085) - recibo 5620
A8: 44819 | C8: =Setembro!N16 -> 165.84 | E8: 420 | F8: Progelcone (FT40220215591) - recibo 416940
A9: 44820 | C9: =Setembro!N17 -> 314 | D9: 310
A10: 44821 | C10: =Setembro!N18 -> 543.9
A11: 44822 | C11: =Setembro!N19 -> 593.8
A12: 44823 | C12: =Setembro!N20 -> 0
A13: 44824 | C13: =Setembro!N21 -> 314.96
A14: 44825 | C14: =Setembro!N22 -> 182.68 | E14: =210.9+135.79+259.99 -> 606.68 | F14: Frutas(FT1296)/Makro(ft015314)/Fnac(FT 65850)
A15: 44826 | C15: =Setembro!N23 -> 250.58 | E15: 16.97 | F15: Progelcone (FT40220217257)-recibo416945
A16: 44827 | C16: =Setembro!N24 -> 193.3 | D16: 195 | E16: 40 | F16: lavazzA
A17: 44828 | C17: =Setembro!N25 -> 338.55 | D17: 335
A18: 44829 | C18: =Setembro!N26 -> 371.69 | D18: 360 | F18: Houve um uber pelo menos que não foi registado como uber
A19: 44830 | C19: =Setembro!N27 -> 0
A20: 44831 | C20: =Setembro!N28 -> 99.5
A21: 44832 | C21: =Setembro!N29 -> 72.1 | E21: =87.91+76.24 -> 164.15 | F21: Frutas(FT1336)/Makro (FT015344)
A22: 44833 | C22: =Setembro!N30 -> 96.48 | E22: 345 | F22: Progelcone(FT40220218850)-recibo418634
A23: 44834 | C23: =Setembro!N31 -> 80.4 | E23: 40 | F23: lavazzA
A25: 44835 | C25: =Outubro!N2 -> 479.9
A26: 44836 | C26: =Outubro!N3 -> 315.65
A27: 44837 | C27: =Outubro!N4 -> 0
A28: 44838 | C28: =Outubro!N5 -> 246.05
A29: 44839 | C29: =Outubro!N6 -> 608.44
A30: 44840 | B30: 4480 | C30: =Outubro!N7 -> 94.1
A31: 44841 | C31: =Outubro!N8 -> 149.98
A32: 44842 | C32: =Outubro!N9 -> 245.06
A33: 44843 | C33: =Outubro!N10 -> 193.6 | D33: 195
A34: 44844 | C34: =Outubro!N11 -> 0
A35: 44845 | C35: =Outubro!N12 -> 132.64
A36: 44846 | C36: =Outubro!N13 -> 112.6
A37: 44847 | C37: =Outubro!N14 -> 113.36 | E37: =247+ 8 -> 255 | F37: Progelcone (FT40220220986/FT40220220992)- Recibo 418646 / Pingo Doce
A38: 44848 | C38: =Outubro!N15 -> 102.94
A39: 44849 | C39: =Outubro!N16 -> 236.24
A40: 44850 | C40: =Outubro!N17 -> 205.32 | E40: =49+81.28+61.25+135.46+28.67 -> 355.66 | F40: Tiger/Makro/Homa/Makro/28,67
A41: 44851 | C41: =Outubro!N18 -> 0
A42: 44852 | C42: =Outubro!N19 -> 42.8
A43: 44853 | C43: =Outubro!N20 -> 46.4 | E43: 225 | F43: Magofri (FT 28411/29433) - recibo 6379
A44: 44854 | C44: =Outubro!N21 -> 65.3
A45: 44855 | C45: =Outubro!N22 -> 115.76 | E45: =23+81.6+48+68.14+47.95 -> 268.69 | F45: Makro/Pontos de açucar
A46: 44856 | C46: =Outubro!N23 -> 69.4
A47: 44857 | C47: =Outubro!N24 -> 167.4
A48: 44858 | C48: =Outubro!N25 -> 0
A49: 44859 | C49: =Outubro!N26 -> 70.3
A50: 44860 | C50: =Outubro!N27 -> 57.38
A51: 44861 | C51: =Outubro!N28 -> 41.28
A52: 44862 | C52: =Outubro!N29 -> 78.1 | E52: 60 | F52: Lavazza (FR 652/3156)
A53: 44863 | C53: =Outubro!N30 -> 123.5
A54: 44864 | C54: =Outubro!N31 -> 418.44
A55: 44865 | C55: =Outubro!N32 -> 0
A57: 44866 | C57: =Novembro!N2 -> 148.9 | E57: =212.85+48.71+102.32 -> 363.88 | F57: Magofri (FT 31197) - recibo 6653 / Makro (FT015838/028629)
A58: 44867 | C58: =Novembro!N3 -> 113.74
A59: 44868 | C59: =Novembro!N4 -> 43.7
A60: 44869 | C60: =Novembro!N5 -> 65.1 | E60: =137.19 -> 137.19 | F60: Lavazza(FR 652/3176)
A61: 44870 | C61: =Novembro!N6 -> 328.22 | E61: =47.98+3.65 -> 51.63 | F61: Makro( FT 39420/39421)
A62: 44871 | C62: =Novembro!N7 -> 147.9
A63: 44872 | C63: =Novembro!N8 -> 0
A64: 44873 | C64: =Novembro!N9 -> 28.5
A65: 44874 | C65: =Novembro!N10 -> 48.9 | E65: =56.98+54.21 + 3.73 -> 114.92 | F65: RP(612603)/Makro( FT 29413)/pingo doce
A66: 44875 | B66: 1785 | C66: =Novembro!N11 -> 128.62 | E66: 98.59 | F66: Makro ( FT 036248)
A67: 44876 | C67: =Novembro!N12 -> 90.09 | E67: 38.66 | F67: Lavazza( FR 652/3206)
A68: 44877 | C68: =Novembro!N13 -> 343.92
A69: 44878 | C69: =Novembro!N14 -> 129.5
A70: 44879 | C70: =Novembro!N15 -> 0 | E70: =37.96+202.75 -> 240.71 | F70: Homa( FR -161/23771)/ Progelcone( FT 40220228750 - recibo - 418791)
A71: 44880 | C71: =Novembro!N16 -> 19.7
A72: 44881 | C72: =Novembro!N17 -> 0
A73: 44882 | C73: =Novembro!N18 -> 62.2 | E73: =194.05+0.5 -> 194.55 | F73: Makro(FT 042571)/ Pingo doce
A74: 44883 | C74: =Novembro!N19 -> 53.4
A75: 44884 | C75: =Novembro!N20 -> 54.5 | E75: =11.7 -> 11.7 | F75: Pingo doce
A76: 44885 | C76: =Novembro!N21 -> 90.14
A77: 44886 | C77: =Novembro!N22 -> 0
A78: 44887 | C78: =Novembro!N23 -> 7.6
A79: 44888 | C79: =Novembro!N24 -> 64.5 | E79: =76.95 -> 76.95 | F79: Magofri (FT 33938)
A80: 44889 | C80: =Novembro!N25 -> 49.5
A81: 44890 | C81: =Novembro!N26 -> 76.6
A82: 44891 | C82: =Novembro!N27 -> 175.2
A83: 44892 | C83: =Novembro!N28 -> 79.7
A84: 44893 | C84: =Novembro!N29 -> 0 | E84: =6.14 -> 6.14 | F84: Pingo doce
A85: 44894 | C85: =Novembro!N30 -> 0
A86: 44895 | C86: =Dezembro!N16 -> 9.6
A88: 44896 | C88: =Dezembro!N2 -> 0
A89: 44897 | C89: =Dezembro!N3 -> 0
A90: 44898 | C90: =Dezembro!N4 -> 0
A91: 44899 | C91: =Dezembro!N5 -> 0
A92: 44900 | C92: =Dezembro!N6 -> 0
A93: 44901 | C93: =Dezembro!N7 -> 0
A94: 44902 | C94: =Dezembro!N8 -> 0
A95: 44903 | C95: =Dezembro!N9 -> 0
A96: 44904 | C96: =Dezembro!N10 -> 0
A97: 44905 | C97: =Dezembro!N11 -> 0
A98: 44906 | C98: =Dezembro!N12 -> 0
A99: 44907 | C99: =Dezembro!N13 -> 0
A100: 44908 | C100: =Dezembro!N14 -> 45.7 | E100: =1.64+6.89 -> 8.53 | F100: Pingo doce
A101: 44909 | C101: =Dezembro!N15 -> 16.4
A102: 44910 | B102: 810 | C102: =Dezembro!N16 -> 9.6 | E102: 103.84 | F102: Progelcone (FT40220235277) - recibo 418939
A103: 44911 | C103: =Dezembro!N17 -> 128.58 | E103: =26.6 -> 26.6 | F103: Confeipan
...

Sheet Maio
B1: FECHO DO DIA | C1: SALT PAY | D1: SANTANDER | E1: GASTOS C/RECIBO | F1: GASTOS S/RECIBO | G1: GLOVO | H1: UBER EATS | I1: VOLUP | J1: BOLT | K1: NUMERARIO | L1: TOTAL | M1: DEPOSITO | N1: EXTRA | O1: FUNDO CAIXA
A2: 44682 | L2: =C2+D2+E2+F2+G2+H2+I2+J2+K2 -> 0 | M2: =K2-N2 -> 0 | N2: =L2-B2-F2 -> 0
A3: 44683 | L3: =C3+D3+E3+F3+G3+H3+I3+J3+K3 -> 0 | M3: =K3-N3 -> 0 | N3: =L3-B3-F3 -> 0
A4: 44684 | L4: =C4+D4+E4+F4+G4+H4+I4+J4+K4 -> 0 | M4: =K4-N4 -> 0 | N4: =L4-B4-F4 -> 0
A5: 44685 | L5: =C5+D5+E5+F5+G5+H5+I5+J5+K5 -> 0 | M5: =K5-N5 -> 0 | N5: =L5-B5-F5 -> 0
A6: 44686 | L6: =C6+D6+E6+F6+G6+H6+I6+J6+K6 -> 0 | M6: =K6-N6 -> 0 | N6: =L6-B6-F6 -> 0
A7: 44687 | L7: =C7+D7+E7+F7+G7+H7+I7+J7+K7 -> 0 | M7: =K7-N7 -> 0 | N7: =L7-B7-F7 -> 0
A8: 44688 | B8: 251 | C8: 113.16 | D8: 54.35 | K8: 95 | L8: =C8+D8+E8+F8+G8+H8+I8+J8+K8 -> 262.51 | M8: 0 | N8: =L8-B8-F8 -> 11.51 | O8: 80
A9: 44689 | B9: 1073.7 | C9: 659.3 | D9: 56.5 | K9: 360 | L9: =C9+D9+E9+F9+G9+H9+I9+J9+K9 -> 1075.8 | M9: =K9-N9 -> 357.9 | N9: =L9-B9-F9 -> 2.1 | O9: 77.21
A10: 44690 | B10: 200.9 | C10: 126.21 | D10: 0 | K10: 75 | L10: =C10+D10+E10+F10+G10+H10+I10+J10+K10 -> 201.21 | M10: =K10-N10 -> 74.69 | N10: =L10-B10-F10 -> 0.31 | O10: 83.11
A11: 44691 | B11: 203.8 | C11: 112.9 | D11: 0 | K11: 95 | L11: =C11+D11+E11+F11+G11+H11+I11+J11+K11 -> 207.9 | M11: =K11-N11 -> 90.9 | N11: =L11-B11-F11 -> 4.1 | O11: 80
A12: 44692 | B12: 311.5 | C12: 228.4 | D12: 8.7 | K12: 95 | L12: =C12+D12+E12+F12+G12+H12+I12+J12+K12 -> 332.1 | M12: =K12-N12 -> 74.4 | N12: =L12-B12-F12 -> 20.6 | O12: 80
A13: 44693 | B13: 237.7 | C13: 145.9 | D13: 37.5 | E13: 0 | F13: 0 | G13: 0 | H13: 0 | I13: 0 | J13: 0 | K13: 60 | L13: =C13+D13+E13+F13+G13+H13+I13+J13+K13 -> 243.4 | M13: =K13-N13 -> 54.3 | N13: =L13-B13-F13 -> 5.7 | O13: 86
A14: 44694 | B14: 562.22 | C14: 346.12 | D14: 18.1 | E14: 0 | F14: 0 | G14: 0 | H14: 0 | I14: 0 | J14: 0 | K14: 210 | L14: =C14+D14+E14+F14+G14+H14+I14+J14+K14 -> 574.22 | M14: =K14-N14 -> 198 | N14: =L14-B14-F14 -> 12 | O14: 89.21
A15: 44695 | B15: 1108.8 | C15: 538.6 | D15: 63.8 | E15: =2.5+5.99 -> 8.49 | F15: 0 | G15: 0 | H15: 0 | I15: 0 | J15: 0 | K15: 510 | L15: =C15+D15+E15+F15+G15+H15+I15+J15+K15 -> 1120.89 | M15: =K15-N15 -> 497.91 | N15: =L15-B15-F15 -> 12.09 | O15: 89.61
A16: 44696 | B16: 501.66 | C16: 161.3 | D16: 104.3 | E16: 36.3 | F16: 0 | G16: 0 | H16: 0 | I16: 0 | J16: 0 | K16: 200 | L16: =C16+D16+E16+F16+G16+H16+I16+J16+K16 -> 501.9 | M16: =K16-N16 -> 199.76 | N16: =L16-B16-F16 -> 0.24 | O16: 89.5
A17: 44697 | B17: 115.3 | C17: 49.8 | D17: 8.6 | E17: 5.45 | F17: 0 | G17: 0 | H17: 0 | I17: 0 | J17: 0 | K17: 55 | L17: =C17+D17+E17+F17+G17+H17+I17+J17+K17 -> 118.85 | M17: =K17-N17 -> 51.45 | N17: =L17-B17-F17 -> 3.55
A18: 44698 | B18: 135.8 | C18: 66.9 | D18: 18.8 | E18: 0 | F18: 0 | G18: 0 | H18: 0 | I18: 0 | J18: 0 | K18: 55 | L18: =C18+D18+E18+F18+G18+H18+I18+J18+K18 -> 140.7 | M18: =K18-N18 -> 50.1 | N18: =L18-B18-F18 -> 4.9 | O18: 81.04
A19: 44699 | B19: 300.74 | C19: 124.14 | D19: 36.2 | E19: 0 | F19: 0 | G19: 0 | H19: 0 | I19: 0 | J19: 0 | K19: 145 | L19: =C19+D19+E19+F19+G19+H19+I19+J19+K19 -> 305.34 | M19: =K19-N19 -> 140.4 | N19: =L19-B19-F19 -> 4.6 | O19: 76.8
A20: 44700 | B20: 441.3 | C20: 260.9 | D20: 35 | E20: 2.79 | F20: 0 | G20: 0 | H20: 0 | I20: 0 | J20: 0 | K20: 150 | L20: =C20+D20+E20+F20+G20+H20+I20+J20+K20 -> 448.69 | M20: =K20-N20 -> 142.61 | N20: =L20-B20-F20 -> 7.39 | O20: 80
A21: 44701 | B21: 1355.51 | C21: 659.1 | D21: 219.8 | E21: =1.16+6.72 -> 7.88 | F21: 15 | G21: 0 | H21: 0 | I21: 0 | J21: 0 | K21: 470 | L21: =C21+D21+E21+F21+G21+H21+I21+J21+K21 -> 1371.78 | M21: =K21-N21 -> 468.73 | N21: =L21-B21-F21 -> 1.27 | O21: 88.15
A22: 44702 | B22: 902.1 | C22: 469.72 | D22: 114.4 | E22: =32.85+7.01+70.11 -> 109.97 | F22: 0 | G22: 0 | H22: 0 | I22: 0 | J22: 0 | K22: 210 | L22: =C22+D22+E22+F22+G22+H22+I22+J22+K22 -> 904.09 | M22: =K22-N22 -> 208.01 | N22: =L22-B22-F22 -> 1.99 | O22: 78.85
A23: 44703 | B23: 1219.7 | C23: 613 | D23: 185.1 | E23: =2.53+2.93 -> 5.46 | F23: 0 | G23: 0 | H23: 0 | I23: 0 | J23: 0 | K23: 450 | L23: =C23+D23+E23+F23+G23+H23+I23+J23+K23 -> 1253.56 | M23: =K23-N23 -> 416.14 | N23: =L23-B23-F23 -> 33.86 | O23: 76.97
A24: 44704 | B24: 220.6 | C24: 126.6 | D24: 15.2 | E24: 0 | F24: 0 | G24: 0 | H24: 0 | I24: 0 | J24: 0 | K24: 80 | L24: =C24+D24+E24+F24+G24+H24+I24+J24+K24 -> 221.8 | M24: =K24-N24 -> 78.8 | N24: =L24-B24-F24 -> 1.2 | O24: 71.37
A25: 44705 | B25: 300.22 | C25: 187.72 | D25: 21.2 | E25: 4.59 | F25: 0 | G25: 0 | H25: 0 | I25: 0 | J25: 0 | K25: 90 | L25: =C25+D25+E25+F25+G25+H25+I25+J25+K25 -> 303.51 | M25: =K25-N25 -> 86.71 | N25: =L25-B25-F25 -> 3.29 | O25: 64.27
A26: 44706 | B26: 404.7 | C26: 277.2 | D26: 0 | E26: 0 | F26: 0 | G26: 0 | H26: 0 | I26: 0 | J26: 0 | K26: 130 | L26: =C26+D26+E26+F26+G26+H26+I26+J26+K26 -> 407.2 | M26: =K26-N26 -> 127.5 | N26: =L26-B26-F26 -> 2.5 | O26: 70.75
A27: 44707 | B27: 720.6 | C27: 417.18 | D27: 36.5 | E27: =8+2.7 -> 10.7 | F27: 0 | G27: 0 | H27: 0 | I27: 0 | J27: 0 | K27: 260 | L27: =C27+D27+E27+F27+G27+H27+I27+J27+K27 -> 724.38 | M27: =K27-N27 -> 256.22 | N27: =L27-B27-F27 -> 3.78 | O27: 79.87
A28: 44708 | B28: 1466.48 | C28: 814.18 | D28: 182.4 | E28: 0 | F28: 0 | G28: 0 | H28: 0 | I28: 0 | J28: 0 | K28: 470 | L28: =C28+D28+E28+F28+G28+H28+I28+J28+K28 -> 1466.58 | M28: =K28-N28 -> 469.9 | N28: =L28-B28-F28 -> 0.1 | O28: =P28+25 -> 60.04 | P28: 35.04
A29: 44709 | B29: 1635.56 | C29: 1059.2 | D29: 66.9 | E29: 0 | F29: 0 | G29: 0 | H29: 0 | I29: 0 | J29: 0 | K29: 510 | L29: =C29+D29+E29+F29+G29+H29+I29+J29+K29 -> 1636.1 | M29: =K29-N29 -> 509.46 | N29: =L29-B29-F29 -> 0.54 | O29: 71.04
A30: 44710 | B30: 1100.48 | C30: 673.6 | D30: 67.8 | E30: 0 | F30: 0 | G30: 0 | H30: 0 | I30: 0 | J30: 0 | K30: 360 | L30: =C30+D30+E30+F30+G30+H30+I30+J30+K30 -> 1101.4 | M30: =K30-N30 -> 359.08 | N30: =L30-B30-F30 -> 0.92 | O30: 85
A31: 44711 | L31: =C31+D31+E31+F31+G31+H31+I31+J31+K31 -> 0 | M31: =K31-N31 -> 0 | N31: =L31-B31-F31 -> 0
A32: 44712 | B32: 357.55 | C32: 287.95 | D32: 17.9 | H32: 18.9 | K32: 40 | L32: =C32+D32+E32+F32+G32+H32+I32+J32+K32 -> 364.75 | M32: =K32-N32 -> 32.8 | N32: =L32-B32-F32 -> 7.2 | O32: 77.8
A33: =SUM(Junho!B33) -> 0 | L33: =SUM(L2:L32) -> 15288.66 | M33: =SUM(M2:M32) -> 4945.77 | N33: =SUM(N2:N32) -> 145.74

Sheet Junho
B1: FECHO DO DIA | C1: SALT PAY | D1: SANTANDER | E1: GASTOS C/RECIBO | F1: GASTOS S/RECIBO | G1: GLOVO | H1: UBER EATS | I1: VOLUP | J1: BOLT | K1: NUMERARIO | L1: TOTAL | M1: DEPOSITO | N1: EXTRA | O1: FUNDO CAIXA
A2: 44713 | B2: 696.62 | C2: 453.08 | D2: 82.5 | E2: 0 | F2: 0 | G2: 0 | H2: 0 | I2: 0 | J2: 0 | K2: 170 | L2: =C2+D2+E2+F2+G2+H2+I2+J2+K2 -> 705.58 | M2: =K2-N2 -> 161.04 | N2: =L2-B2-F2 -> 8.96 | O2: 83.55
A3: 44714 | B3: 546.7 | C3: 343.1 | D3: 43.5 | E3: 0 | F3: 0 | G3: 0 | H3: 0 | I3: 0 | J3: 0 | K3: 165 | L3: =C3+D3+E3+F3+G3+H3+I3+J3+K3 -> 551.6 | M3: =K3-N3 -> 160.1 | N3: =L3-B3-F3 -> 4.9 | O3: 86.59
A4: 44715 | B4: 755.7 | C4: 342.1 | D4: 132.38 | E4: 0 | F4: 0 | G4: 37.8 | H4: 47.8 | I4: 0 | J4: 0 | K4: 235 | L4: =C4+D4+E4+F4+G4+H4+I4+J4+K4 -> 795.08 | M4: =K4-N4 -> 195.62 | N4: =L4-B4-F4 -> 39.38 | O4: 0
A5: 44716 | B5: 1609.99 | C5: 929.61 | D5: 200.1 | E5: =1.72+56.35 -> 58.07 | F5: 0 | G5: 0 | H5: 0 | I5: 0 | J5: 0 | K5: 430 | L5: =C5+D5+E5+F5+G5+H5+I5+J5+K5 -> 1617.78 | M5: =K5-N5 -> 422.21 | N5: =L5-B5-F5 -> 7.79 | O5: 83.76
A6: 44717 | B6: 1349.52 | C6: 844.46 | D6: 104 | E6: 0 | F6: 0 | G6: 0 | H6: 0 | I6: 0 | J6: 0 | K6: 410 | L6: =C6+D6+E6+F6+G6+H6+I6+J6+K6 -> 1358.46 | M6: =K6-N6 -> 401.06 | N6: =L6-B6-F6 -> 8.94 | O6: 84.06
A7: 44718 | B7: 0 | C7: 0 | D7: 0 | E7: 0 | F7: 0 | G7: 0 | H7: 0 | I7: 0 | J7: 0 | K7: 0 | L7: =C7+D7+E7+F7+G7+H7+I7+J7+K7 -> 0 | M7: =K7-N7 -> 0 | N7: =L7-B7-F7 -> 0 | O7: 0
A8: 44719 | B8: 403.9 | C8: 201.7 | D8: 49 | E8: 9.6 | F8: 0 | G8: 0 | H8: 0 | I8: 0 | J8: 0 | K8: 145 | L8: =C8+D8+E8+F8+G8+H8+I8+J8+K8 -> 405.3 | M8: =K8-N8 -> 143.6 | N8: =L8-B8-F8 -> 1.4 | O8: 83.7
A9: 44720 | B9: 310.2 | C9: 270 | D9: 3.8 | E9: 0 | F9: 0 | G9: 0 | H9: 0 | I9: 0 | J9: 0 | K9: 40 | L9: =C9+D9+E9+F9+G9+H9+I9+J9+K9 -> 313.8 | M9: =K9-N9 -> 36.4 | N9: =L9-B9-F9 -> 3.6 | O9: 80.2
A10: 44721 | B10: 481.64 | C10: 313.44 | D10: 14.4 | E10: 0 | F10: 0 | G10: 0 | H10: 0 | I10: 0 | J10: 0 | K10: 155 | L10: =C10+D10+E10+F10+G10+H10+I10+J10+K10 -> 482.84 | M10: =K10-N10 -> 153.8 | N10: =L10-B10-F10 -> 1.2 | O10: 84.2
A11: 44722 | B11: 1388.99 | C11: 866.91 | D11: 87.5 | E11: 0 | F11: 0 | G11: 0 | H11: 0 | I11: 0 | J11: 0 | K11: 445 | L11: =C11+D11+E11+F11+G11+H11+I11+J11+K11 -> 1399.41 | M11: =K11-N11 -> 434.58 | N11: =L11-B11-F11 -> 10.42 | O11: 83.73
A12: 44723 | B12: 1438.15 | C12: 852.85 | D12: 101.5 | E12: 0 | F12: 0 | G12: 0 | H12: 0 | I12: 0 | J12: 0 | K12: 510 | L12: =C12+D12+E12+F12+G12+H12+I12+J12+K12 -> 1464.35 | M12: =K12-N12 -> 483.8 | N12: =L12-B12-F12 -> 26.2 | O12: 86.72
A13: 44724 | B13: 1268.28 | C13: 791.08 | D13: 92.8 | E13: 17.79 | F13: 0 | G13: 0 | H13: 18.9 | I13: 0 | J13: 0 | K13: 350 | L13: =C13+D13+E13+F13+G13+H13+I13+J13+K13 -> 1270.57 | M13: =K13-N13 -> 347.71 | N13: =L13-B13-F13 -> 2.29 | O13: 78.02
A14: 44725 | B14: 0 | C14: 0 | D14: 0 | E14: 0 | F14: 0 | G14: 0 | H14: 0 | I14: 0 | J14: 0 | K14: 0 | L14: 0 | M14: 0 | N14: 0 | O14: 0
A15: 44726 | B15: 405.24 | C15: 204.4 | D15: 23.8 | E15: 0 | F15: 0 | G15: 0 | H15: 0 | I15: 0 | J15: 0 | K15: 180 | L15: =C15+D15+E15+F15+G15+H15+I15+J15+K15 -> 408.2 | M15: =K15-N15 -> 177.04 | N15: =L15-B15-F15 -> 2.96 | O15: 82.09
A16: 44727 | B16: 161.4 | C16: 92.2 | D16: 3.8 | E16: 0 | F16: 0 | G16: 0 | H16: 0 | I16: 0 | J16: 0 | K16: 65 | L16: =C16+D16+E16+F16+G16+H16+I16+J16+K16 -> 161 | M16: =K16-N16 -> 65.4 | N16: =L16-B16-F16 -> -0.4 | O16: 83.04
A17: 44728 | B17: 729.5 | C17: 393 | D17: 59.9 | E17: 0 | F17: 0 | G17: 0 | H17: 0 | I17: 0 | J17: 0 | K17: 315 | L17: =C17+D17+E17+F17+G17+H17+I17+J17+K17 -> 767.9 | M17: =K17-N17 -> 276.6 | N17: =L17-B17-F17 -> 38.4 | O17: 80.14
A18: 44729 | B18: 937.4 | C18: 521.3 | D18: 83.4 | E18: 11.22 | F18: 0 | G18: 0 | H18: 0 | I18: 0 | J18: 0 | K18: 340 | L18: =C18+D18+E18+F18+G18+H18+I18+J18+K18 -> 955.92 | M18: =K18-N18 -> 321.48 | N18: =L18-B18-F18 -> 18.52 | O18: 82.58
A19: 44730 | B19: 1100.6 | C19: 608.6 | D19: 97.3 | E19: 0 | F19: 0 | G19: 0 | H19: 0 | I19: 0 | J19: 0 | K19: 415 | L19: =C19+D19+E19+F19+G19+H19+I19+J19+K19 -> 1120.9 | M19: =K19-N19 -> 394.7 | N19: =L19-B19-F19 -> 20.3 | O19: 81.6
A20: 44731 | B20: 1117.16 | C20: 689.38 | D20: 63.5 | E20: 1 | F20: 0 | G20: 0 | H20: 0 | I20: 0 | J20: 0 | K20: 365 | L20: =C20+D20+E20+F20+G20+H20+I20+J20+K20 -> 1118.88 | M20: =K20-N20 -> 363.28 | N20: =L20-B20-F20 -> 1.72 | O20: 84.51
A21: 44732 | B21: 0 | C21: 0 | D21: 0 | E21: 0 | F21: 0 | G21: 0 | H21: 0 | I21: 0 | J21: 0 | K21: 0 | L21: =C21+D21+E21+F21+G21+H21+I21+J21+K21 -> 0 | M21: =K21-N21 -> 0 | N21: =L21-B21-F21 -> 0 | O21: 0
A22: 44733 | B22: 212.4 | C22: 106.8 | D22: 11.1 | E22: 0 | F22: 0 | G22: 18.9 | H22: 0 | I22: 0 | J22: 0 | K22: 75 | L22: =C22+D22+E22+F22+G22+H22+I22+J22+K22 -> 211.8 | M22: =K22-N22 -> 75.6 | N22: =L22-B22-F22 -> -0.6 | O22: 84.58
A23: 44734 | B23: 500.1 | C23: 278.8 | D23: 37.4 | E23: 0 | F23: 0 | G23: 0 | H23: 0 | I23: 0 | J23: 0 | K23: 185 | L23: =C23+D23+E23+F23+G23+H23+I23+J23+K23 -> 501.2 | M23: =K23-N23 -> 183.9 | N23: =L23-B23-F23 -> 1.1 | O23: 79.85
A24: 44735 | B24: 354.48 | C24: 165.18 | D24: 0 | E24: 0 | F24: 0 | G24: 0 | H24: 0 | I24: 0 | J24: 0 | K24: 190 | L24: =C24+D24+E24+F24+G24+H24+I24+J24+K24 -> 355.18 | M24: =K24-N24 -> 189.3 | N24: =L24-B24-F24 -> 0.7 | O24: 81.95
A25: 44736 | B25: 934.38 | C25: 505.28 | D25: 123.9 | E25: 0 | F25: 0 | G25: 0 | H25: 19.9 | I25: 0 | J25: 0 | K25: 305 | L25: =C25+D25+E25+F25+G25+H25+I25+J25+K25 -> 954.08 | M25: =K25-N25 -> 285.3 | N25: =L25-B25-F25 -> 19.7 | O25: 82.2
A26: 44737 | B26: 1514.32 | C26: 848.64 | D26: 119.48 | E26: 0 | F26: 0 | G26: 0 | H26: 36.9 | I26: 0 | J26: 0 | K26: 500 | L26: =C26+D26+E26+F26+G26+H26+I26+J26+K26 -> 1505.02 | M26: =K26-N26 -> 509.3 | N26: =L26-B26-F26 -> -9.3 | O26: 86.18
... A28: 44739 | B28: 0 | C28: 0 | D28: 0 | E28: 0 | F28: 0 | G28: 0 | H28: 0 | I28: 0 | J28: 0 | K28: 0 | L28: =C28+D28+E28+F28+G28+H28+I28+J28+K28 -> 0 | M28: =K28-N28 -> 0 | N28: =L28-B28-F28 -> 0 | O28: 0
A29: 44740 | B29: 576.8 | C29: 319.1 | D29: 40.2 | E29: 0 | F29: 0 | G29: 0 | H29: 0 | I29: 0 | J29: 0 | K29: 220 | L29: =C29+D29+E29+F29+G29+H29+I29+J29+K29 -> 579.3 | M29: =K29-N29 -> 217.5 | N29: =L29-B29-F29 -> 2.5 | O29: 81.32 | P29: 35.04
A30: 44741 | B30: 525.8 | C30: 269.2 | D30: 52.3 | E30: 0 | F30: 0 | G30: 0 | H30: 0 | I30: 0 | J30: 0 | K30: 205 | L30: =C30+D30+E30+F30+G30+H30+I30+J30+K30 -> 526.5 | M30: =K30-N30 -> 204.3 | N30: =L30-B30-F30 -> 0.7 | O30: 80.27
A31: 44742 | B31: 542.14 | C31: 334.94 | D31: 33.1 | E31: 0 | F31: 0 | G31: 0 | H31: 0 | I31: 0 | J31: 0 | K31: 175 | L31: =C31+D31+E31+F31+G31+H31+I31+J31+K31 -> 543.04 | M31: =K31-N31 -> 174.1 | N31: =L31-B31-F31 -> 0.9 | O31: 80.68
L32: =C32+D32+E32+F32+G32+H32+I32+J32+K32 -> 0 | M32: =K32-N32 -> 0 | N32: =L32-B32-F32 -> 0 | O32: 0
B33: 0 | C33: 0 | D33: 0 | H33: 0 | K33: 0 | L33: =C33+D33+E33+F33+G33+H33+I33+J33+K33 -> 0 | M33: =K33-N33 -> 0 | N33: =L33-B33-F33 -> 0 | O33: 0
A34: TOTAL | L34: =SUM(L2:L33) -> 21314.05 | M34: =L34-N34 -> 21098.42 | N34: =SUM(N2:N33) -> 215.63 | Q34: =L34/26 -> 819.77115 | R34: /dia

Sheet Julho
B1: FECHO DO DIA | C1: SALT PAY | D1: SANTANDER | E1: GASTOS C/RECIBO | F1: GASTOS S/RECIBO | G1: GLOVO | H1: UBER EATS | I1: VOLUP | J1: BOLT | K1: Transf. Bancária | L1: NUMERARIO | M1: TOTAL | N1: DEPOSITO | O1: EXTRA | P1: FUNDO CAIXA
A2: 44743 | B2: 763.46 | C2: 459.56 | D2: 38.4 | E2: 0 | F2: 0 | G2: 0 | H2: 0 | I2: 0 | J2: 0 | L2: 265 | M2: =C2+D2+E2+F2+G2+H2+I2+J2+L2 -> 762.96 | N2: =L2-O2 -> 265.5 | O2: =M2-B2-F2 -> -0.5 | P2: 80.27
A3: 44744 | B3: 1076.44 | C3: 613.64 | D3: 116.3 | E3: 0.99 | F3: 0 | G3: 0 | H3: 0 | I3: 0 | J3: 0 | L3: 335 | M3: =C3+D3+E3+F3+G3+H3+I3+J3+L3 -> 1065.93 | N3: =L3-O3 -> 345.51 | O3: =M3-B3-F3 -> -10.51 | P3: 81.42
A4: 44745 | B4: 1300.2 | C4: 829.44 | D4: 58.84 | E4: 11.98 | F4: 0 | G4: 0 | H4: 0 | I4: 0 | J4: 0 | L4: 400 | M4: =C4+D4+E4+F4+G4+H4+I4+J4+L4 -> 1300.26 | N4: =L4-O4 -> 399.94 | O4: =M4-B4-F4 -> 0.06 | P4: 71.35
A5: 44746 | B5: 0 | C5: 0 | D5: 0 | E5: 0 | F5: 0 | G5: 0 | H5: 0 | I5: 0 | J5: 0 | L5: 0 | M5: 0 | N5: 0 | O5: 0
A6: 44747 | B6: 605 | C6: 398 | D6: 13.6 | E6: 0 | F6: 0 | G6: 36.9 | H6: 0 | I6: 0 | J6: 0 | L6: 160 | M6: =C6+D6+E6+F6+G6+H6+I6+J6+L6 -> 608.5 | N6: =L6-O6 -> 156.5 | O6: =M6-B6-F6 -> 3.5 | P6: 70.76
A7: 44748 | B7: 1013.2 | C7: 591.2 | D7: 45.7 | E7: 0 | F7: 0 | G7: 0 | H7: 0 | I7: 0 | J7: 0 | L7: 380 | M7: =C7+D7+E7+F7+G7+H7+I7+J7+L7 -> 1016.9 | N7: =L7-O7 -> 376.3 | O7: =M7-B7-F7 -> 3.7 | P7: 71.1
A8: 44749 | B8: 1400.45 | C8: 839.86 | D8: 108.4 | E8: 0 | F8: 0 | G8: 0 | H8: 0 | I8: 0 | J8: 0 | L8: 450 | M8: =C8+D8+E8+F8+G8+H8+I8+J8+L8 -> 1398.26 | N8: =L8-O8 -> 452.19 | O8: =M8-B8-F8 -> -2.19 | P8: 74
A9: 44750 | B9: 1682.19 | C9: 1023.19 | D9: 101.2 | E9: 0 | F9: 0 | G9: 0 | H9: 37.8 | I9: 0 | J9: 0 | L9: 525 | M9: =C9+D9+E9+F9+G9+H9+I9+J9+L9 -> 1687.19 | N9: =L9-O9 -> 520 | O9: =M9-B9-F9 -> 5 | P9: 74.69
A10: 44751 | B10: 1836.79 | C10: 1185.39 | D10: 165 | E10: 0 | F10: 0 | G10: 0 | H10: 0 | I10: 0 | J10: 0 | L10: 500 | M10: =C10+D10+E10+F10+G10+H10+I10+J10+L10 -> 1850.39 | N10: =L10-O10 -> 486.4 | O10: =M10-B10-F10 -> 13.6 | P10: 74
A11: 44752 | B11: 1206.1 | C11: 781.32 | D11: 67.4 | E11: 7.21 | F11: 0 | G11: 0 | H11: 0 | I11: 0 | J11: 0 | L11: 350 | M11: =C11+D11+E11+F11+G11+H11+I11+J11+L11 -> 1205.93 | N11: =L11-O11 -> 350.17 | O11: =M11-B11-F11 -> -0.17 | P11: 90.61
A12: 44753 | B12: 0 | E12: 0 | F12: 0 | G12: 0 | H12: 0 | I12: 0 | J12: 0 | L12: 0 | M12: =C12+D12+E12+F12+G12+H12+I12+J12+L12 -> 0 | N12: =L12-O12 -> 0 | O12: =M12-B12-F12 -> 0
A13: 44754 | B13: 1537.05 | C13: 835.85 | D13: 182.7 | E13: 0 | F13: 0 | G13: 0 | H13: 0 | I13: 0 | J13: 0 | L13: 525 | M13: =C13+D13+E13+F13+G13+H13+I13+J13+L13 -> 1543.55 | N13: =L13-O13 -> 518.5 | O13: =M13-B13-F13 -> 6.5 | P13: 90.04
A14: 44755 | B14: 1401.38 | C14: 655.44 | D14: 119.6 | E14: 0 | F14: 0 | G14: 0 | H14: 0 | I14: 0 | J14: 0 | L14: 625 | M14: =C14+D14+E14+F14+G14+H14+I14+J14+L14 -> 1400.04 | N14: =L14-O14 -> 626.34 | O14: =M14-B14-F14 -> -1.34 | P14: 83.45
A15: 44756 | B15: 1380.94 | C15: 769.54 | D15: 53.6 | E15: 0 | F15: 0 | G15: 0 | H15: 0 | I15: 0 | J15: 0 | K15: 156.8 | L15: 400 | M15: =C15+D15+E15+F15+G15+H15+I15+J15+L15+K15 -> 1379.94 | N15: =L15-O15 -> 401 | O15: =M15-B15-F15 -> -1 | P15: 78.81
A16: 44757 | B16: 1250.85 | C16: 719.25 | D16: 48.8 | E16: 0 | F16: 0 | G16: 0 | H16: 0 | I16: 0 | J16: 0 | L16: 495 | M16: =C16+D16+E16+F16+G16+H16+I16+J16+L16 -> 1263.05 | N16: =L16-O16 -> 482.8 | O16: =M16-B16-F16 -> 12.2 | P16: 80.2
A17: 44758 | B17: 1834.2 | C17: 939.16 | D17: 161 | E17: 12 | F17: 0 | G17: 0 | H17: 103.5 | I17: 0 | J17: 0 | L17: 618.34 | M17: =C17+D17+E17+F17+G17+H17+I17+J17+L17 -> 1834 | N17: =L17-O17 -> 618.54 | O17: =M17-B17-F17 -> -0.2 | P17: =46.67+45 -> 91.67
A18: 44759 | B18: 1630 | C18: 987.35 | D18: 108.5 | E18: 0 | F18: 0 | G18: 0 | H18: 19.9 | I18: 0 | J18: 0 | L18: 520 | M18: =C18+D18+E18+F18+G18+H18+I18+J18+L18 -> 1635.75 | N18: =L18-O18 -> 514.25 | O18: =M18-B18-F18 -> 5.75 | P18: 85.29
A19: 44760 | B19: 0 | C19: 0 | D19: 0 | E19: 0 | F19: 0 | G19: 0 | H19: 0 | I19: 0 | J19: 0 | L19: 0 | M19: 0 | N19: 0 | O19: =M19-B19-F19 -> 0
A20: 44761 | B20: 957.54 | C20: 602.3 | D20: 57.04 | E20: 0 | F20: 0 | G20: 0 | H20: 0 | I20: 0 | J20: 0 | L20: 300 | M20: =C20+D20+E20+F20+G20+H20+I20+J20+L20 -> 959.34 | N20: =L20-O20 -> 298.2 | O20: =M20-B20-F20 -> 1.8 | P20: 83.35
A21: 44762 | B21: 963.38 | C21: 531.18 | D21: 43.5 | E21: 0 | F21: 0 | G21: 0 | H21: 0 | I21: 0 | J21: 0 | L21: 385 | M21: =C21+D21+E21+F21+G21+H21+I21+J21+L21 -> 959.68 | N21: =L21-O21 -> 388.7 | O21: =M21-B21-F21 -> -3.7 | P21: 74
A22: 44763 | B22: 1070.5 | C22: 582.95 | D22: 104 | E22: 0 | F22: 0 | G22: 0 | H22: 0 | I22: 0 | J22: 0 | L22: 385 | M22: =C22+D22+E22+F22+G22+H22+I22+J22+L22 -> 1071.95 | N22: =L22-O22 -> 383.55 | O22: =M22-B22-F22 -> 1.45 | P22: 72.69
A23: 44764 | B23: 1180.88 | C23: =793.78-D23 -> 723.98 | D23: 69.8 | E23: 0 | F23: 0 | G23: 0 | H23: 37.8 | I23: 0 | J23: 0 | L23: 350 | M23: =C23+D23+E23+F23+G23+H23+I23+J23+L23 -> 1181.58 | N23: =L23-O23 -> 349.3 | O23: =M23-B23-F23 -> 0.7 | P23: 75.52
A24: 44765 | B24: 1611 | C24: 881.9 | D24: 79.5 | E24: 0 | F24: 0 | G24: 0 | H24: 18.9 | I24: 0 | J24: 0 | L24: 630 | M24: =C24+D24+E24+F24+G24+H24+I24+J24+L24 -> 1610.3 | N24: =L24-O24 -> 630.7 | O24: =M24-B24-F24 -> -0.7 | P24: 73.6
A25: 44766 | B25: 1291.56 | C25: 727.34 | D25: 112.3 | E25: 0 | F25: 0 | G25: 0 | H25: 0 | I25: 0 | J25: 0 | L25: 460 | M25: =C25+D25+E25+F25+G25+H25+I25+J25+L25 -> 1299.64 | N25: =L25-O25 -> 451.92 | O25: =M25-B25-F25 -> 8.08 | P25: 74.25
A26: 44767 | B26: 0 | C26: 0 | D26: 0 | E26: 0 | F26: 0 | G26: 0 | H26: 0 | I26: 0 | J26: 0 | L26: 0 | M26: =C26+D26+E26+F26+G26+H26+I26+J26+L26 -> 0 | N26: =L26-O26 -> 0 | O26: =M26-B26-F26 -> 0
A27: 44768 | B27: 1194.13 | C27: 621.84 | D27: 41.2 | E27: 0 | F27: 0 | G27: 0 | H27: 0 | I27: 0 | J27: 0 | K27: 195.99 | L27: 335 | M27: =C27+D27+E27+F27+G27+H27+I27+J27+L27+K27 -> 1194.03 | N27: =L27-O27 -> 335.1 | O27: =M27-B27-F27 -> -0.1 | P27: 76.23
A28: 44769 | B28: 905.52 | C28: 533.72 | D28: 54.8 | E28: 0 | F28: 0 | G28: 0 | H28: 18.9 | I28: 0 | J28: 0 | L28: 300 | M28: =C28+D28+E28+F28+G28+H28+I28+J28+L28 -> 907.42 | N28: =L28-O28 -> 298.1 | O28: =M28-B28-F28 -> 1.9 | P28: 70.75
A29: 44770 | B29: 679.9 | C29: 333.8 | D29: 67.7 | E29: 0 | F29: 0 | G29: 0 | H29: 0 | I29: 0 | J29: 0 | L29: 275 | M29: =C29+D29+E29+F29+G29+H29+I29+J29+L29 -> 676.5 | N29: =L29-O29 -> 278.4 | O29: =M29-B29-F29 -> -3.4 | P29: 70.33 | Q29: 35.04
A30: 44771 | B30: 1340.5 | C30: 843.16 | D30: 160.4 | E30: 0 | F30: 0 | G30: 0 | H30: 0 | I30: 0 | J30: 0 | L30: 350 | M30: =C30+D30+E30+F30+G30+H30+I30+J30+L30 -> 1353.56 | N30: =L30-O30 -> 336.94 | O30: =M30-B30-F30 -> 13.06 | P30: 75.88
A31: 44772 | B31: 1723.62 | C31: 938.72 | D31: 112.9 | E31: 0 | F31: 0 | G31: 0 | H31: 46.8 | I31: 0 | J31: 0 | L31: 625 | M31: =C31+D31+E31+F31+G31+H31+I31+J31+L31 -> 1723.42 | N31: =L31-O31 -> 625.2 | O31: =M31-B31-F31 -> -0.2 | P31: 76.2
A32: 44773 | B32: 1543.92 | C32: 1026.16 | D32: 73 | E32: 0 | F32: 0 | G32: 0 | H32: 0 | I32: 0 | J32: 0 | L32: 440 | M32: =C32+D32+E32+F32+G32+H32+I32+J32+L32 -> 1539.16 | N32: =L32-O32 -> 444.76 | O32: =M32-B32-F32 -> -4.76 | P32: 79.46
B33: 0 | C33: 0 | D33: 0 | E33: 0 | F33: 0 | G33: 0 | H33: 0 | I33: 0 | J33: 0 | L33: 0 | M33: =C33+D33+E33+F33+G33+H33+I33+J33+L33 -> 0 | N33: =L33-O33 -> 0 | O33: =M33-B33-F33 -> 0
A34: TOTAL | M34: =SUM(M2:M33) -> 34429.23 | N34: =M34-O34 -> 34380.7 | O34: =SUM(O2:O33) -> 48.53 | R34: =M34/26 -> 1324.2012 | S34: /dia

Sheet Agosto
B1: FECHO DO DIA | C1: SALT PAY | D1: SANTANDER | E1: GASTOS C/RECIBO | F1: GASTOS S/RECIBO | G1: GLOVO | H1: UBER EATS | I1: VOLUP | J1: BOLT | K1: Transf. Bancária | L1: NUMERARIO | M1: TOTAL | N1: DEPOSITO | O1: EXTRA | P1: FUNDO CAIXA
A2: 44774 | M2: =C2+D2+E2+F2+G2+H2+I2+J2+L2 -> 0 | N2: =L2-O2 -> 0 | O2: =M2-B2-F2 -> 0 | P2: 79.46
A3: 44775 | B3: 755.54 | C3: 430.74 | D3: 11.4 | E3: 0 | F3: 0 | G3: 0 | H3: 0 | I3: 0 | J3: 0 | K3: 0 | L3: 310 | M3: =C3+D3+E3+F3+G3+H3+I3+J3+L3 -> 752.14 | N3: =L3-O3 -> 313.4 | O3: =M3-B3-F3 -> -3.4 | P3: 82.93 | Q3: 33 euro quilos melhor
A4: 44776 | B4: 1087 | C4: 642.52 | D4: 43.2 | L4: 400 | M4: =C4+D4+E4+F4+G4+H4+I4+J4+L4+K4 -> 1085.72 | N4: =L4-O4 -> 401.28 | O4: =M4-B4-F4 -> -1.28 | P4: 71.35
A5: 44777 | B5: 965.21 | C5: 532.86 | D5: 35.8 | L5: 398.72 | M5: =C5+D5+E5+F5+G5+H5+I5+J5+L5+K5 -> 967.38 | N5: =L5-O5 -> 396.55 | O5: =M5-B5-F5 -> 2.17 | P5: =26.65+50 -> 76.65
A6: 44778 | B6: 871.88 | C6: 347.28 | D6: 89 | G6: 18.9 | H6: 37.8 | L6: 440 | M6: =C6+D6+E6+F6+G6+H6+I6+J6+L6+K6 -> 932.98 | N6: =L6-O6 -> 378.9 | O6: =M6-B6-F6 -> 61.1 | P6: 75.71
A7: 44779 | B7: 1079.92 | C7: 660.52 | D7: 39.2 | L7: 382.22 | M7: =C7+D7+E7+F7+G7+H7+I7+J7+L7+K7 -> 1081.94 | N7: =L7-O7 -> 380.2 | O7: =M7-B7-F7 -> 2.02 | P7: =50+37.93 -> 87.93 | Q7: 29.37
A8: 44780 | B8: 1011.56 | C8: 649.16 | D8: 51.5 | L8: 310 | M8: =C8+D8+E8+F8+G8+H8+I8+J8+L8+K8 -> 1010.66 | N8: =L8-O8 -> 310.9 | O8: =M8-B8-F8 -> -0.9 | P8: 86.63
A9: 44781 | B9: 0 | C9: 0 | D9: 0 | E9: 0 | F9: 0 | G9: 0 | H9: 0 | I9: 0 | J9: 0 | K9: 0 | L9: 0 | M9: 0 | N9: 0 | O9: 0
A10: 44782 | B10: 957.66 | C10: 567.56 | D10: 19 | H10: 56.7 | L10: 315 | M10: =C10+D10+E10+F10+G10+H10+I10+J10+L10+K10 -> 958.26 | N10: =L10-O10 -> 314.4 | O10: =M10-B10-F10 -> 0.6 | P10: 86.12
A11: 44783 | B11: 1146.49 | C11: 732.99 | D11: 73.4 | L11: 340 | M11: =C11+D11+E11+F11+G11+H11+I11+J11+L11+K11 -> 1146.39 | N11: =L11-O11 -> 340.1 | O11: =M11-B11-F11 -> -0.1 | P11: 89.22
A12: 44784 | B12: 1002.65 | C12: 434.58 | D12: 61.7 | L12: 510 | M12: =C12+D12+E12+F12+G12+H12+I12+J12+L12+K12 -> 1006.28 | N12: =L12-O12 -> 506.37 | O12: =M12-B12-F12 -> 3.63 | P12: 87.52 | Q12: 27,83 euro/quilos ok | S12: o resultado muda de acordo com a pastelaria produzida e não vendida
A13: 44785 | B13: 1366.1 | C13: 757.22 | D13: 92.1 | H13: 18.9 | L13: 520 | M13: =C13+D13+E13+F13+G13+H13+I13+J13+L13+K13 -> 1388.22 | N13: =L13-O13 -> 497.88 | O13: =M13-B13-F13 -> 22.12
A14: 44786 | B14: 1404.78 | C14: 796.28 | D14: 74.9 | L14: 530 | M14: =C14+D14+E14+F14+G14+H14+I14+J14+L14+K14 -> 1401.18 | N14: =L14-O14 -> 533.6 | O14: =M14-B14-F14 -> -3.6 | P14: 100.72
A15: 44787 | B15: 1300.92 | C15: 724.74 | D15: 63.9 | L15: 515 | M15: =C15+D15+E15+F15+G15+H15+I15+J15+L15+K15 -> 1303.64 | N15: =L15-O15 -> 512.28 | O15: =M15-B15-F15 -> 2.72 | P15: 98.62
A16: 44788 | B16: 1253.9 | C16: 635.2 | D16: 78.6 | L16: 540 | M16: =C16+D16+E16+F16+G16+H16+I16+J16+L16+K16 -> 1253.8 | N16: =L16-O16 -> 540.1 | O16: =M16-B16-F16 -> -0.1 | P16: 98.87
A17: 44789 | B17: 0 | C17: 0 | D17: 0 | L17: 0 | M17: =C17+D17+E17+F17+G17+H17+I17+J17+L17+K17 -> 0 | N17: =L17-O17 -> 0 | O17: =M17-B17-F17 -> 0
A18: 44790 | B18: 762.34 | C18: 402.98 | D18: 52.4 | L18: 310 | M18: =C18+D18+E18+F18+G18+H18+I18+J18+L18+K18 -> 765.38 | N18: =L18-O18 -> 306.96 | O18: =M18-B18-F18 -> 3.04 | P18: 84.77
A19: 44791 | B19: 1119.84 | C19: 652.36 | D19: 38.4 | L19: 450 | M19: =C19+D19+E19+F19+G19+H19+I19+J19+L19+K19 -> 1140.76 | N19: =L19-O19 -> 429.08 | O19: =M19-B19-F19 -> 20.92 | P19: 83.57
A20: 44792 | B20: 1517.72 | C20: 799.28 | D20: 117.1 | H20: 27.9 | L20: 574.71 | M20: =C20+D20+E20+F20+G20+H20+I20+J20+L20+K20 -> 1518.99 | N20: =L20-O20 -> 573.44 | O20: =M20-B20-F20 -> 1.27 | P20: 78.28
A21: 44793 | B21: 1400.8 | C21: 850.2 | D21: 71.02 | J21: 27.9 | L21: 452.89 | M21: =C21+D21+E21+F21+G21+H21+I21+J21+L21+K21 -> 1402.01 | N21: =L21-O21 -> 451.68 | O21: =M21-B21-F21 -> 1.21 | P21: 71.17
A22: 44794 | B22: 1142.68 | C22: 649.3 | D22: 43.3 | L22: 440 | M22: =C22+D22+E22+F22+G22+H22+I22+J22+L22+K22 -> 1132.6 | N22: =L22-O22 -> 450.08 | O22: =M22-B22-F22 -> -10.08 | P22: 78.62
A23: 44795 | B23: 0 | C23: 0 | D23: 0 | L23: 0 | M23: 0 | N23: 0 | O23: 0 | P23: 0
A24: 44796 | B24: 1035.55 | C24: 613.25 | D24: 36.8 | L24: 430 | M24: =C24+D24+E24+F24+G24+H24+I24+J24+L24+K24 -> 1080.05 | N24: =L24-O24 -> 385.5 | O24: =M24-B24-F24 -> 44.5 | P24: 84.41
A25: 44797 | B25: 576.06 | C25: 317.64 | D25: 24.4 | L25: 240 | M25: =C25+D25+E25+F25+G25+H25+I25+J25+L25+K25 -> 582.04 | N25: =L25-O25 -> 234.02 | O25: =M25-B25-F25 -> 5.98 | P25: 81.32
A26: 44798 | B26: 887.72 | C26: 486.8 | D26: 11.4 | L26: 390 | M26: =C26+D26+E26+F26+G26+H26+I26+J26+L26+K26 -> 888.2 | N26: =L26-O26 -> 389.52 | O26: =M26-B26-F26 -> 0.48 | P26: 83.32
A27: 44799 | B27: 1189.92 | C27: 685.08 | D27: 91.64 | L27: 410 | M27: =C27+D27+E27+F27+G27+H27+I27+J27+L27+K27 -> 1186.72 | N27: =L27-O27 -> 413.2 | O27: =M27-B27-F27 -> -3.2 | P27: 86.72
A28: 44800 | B28: 1482.84 | C28: 877.86 | D28: 141 | L28: 465 | M28: =C28+D28+E28+F28+G28+H28+I28+J28+L28+K28 -> 1483.86 | N28: =L28-O28 -> 463.98 | O28: =M28-B28-F28 -> 1.02 | P28: 85.92
A29: 44801 | B29: 1360.2 | C29: 693.1 | D29: 139.2 | H29: 55.8 | L29: 470 | M29: =C29+D29+E29+F29+G29+H29+I29+J29+L29+K29 -> 1358.1 | N29: =L29-O29 -> 472.1 | O29: =M29-B29-F29 -> -2.1 | P29: 84.22 | Q29: 35.04
A30: 44802 | B30: 0 | C30: 0 | D30: 0 | L30: 0 | M30: 0 | N30: 0 | O30: =M30-B30-F30 -> 0 | P30: 0
A31: 44803 | B31: 811.5 | C31: 427.14 | D31: 66 | L31: 320 | M31: =C31+D31+E31+F31+G31+H31+I31+J31+L31+K31 -> 813.14 | N31: =L31-O31 -> 318.36 | O31: =M31-B31-F31 -> 1.64 | P31: 82.82
A32: 44804 | B32: 1055.66 | C32: 573.21 | D32: 57.46 | H32: 18.9 | L32: 405 | M32: =C32+D32+E32+F32+G32+H32+I32+J32+L32+K32 -> 1054.57 | N32: =L32-O32 -> 406.09 | O32: =M32-B32-F32 -> -1.09 | P32: 80.57
M33: =C33+D33+E33+F33+G33+H33+I33+J33+L33+K33 -> 0 | N33: =L33-O33 -> 0 | O33: =M33-B33-F33 -> 0
A34: TOTAL | M34: =SUM(M2:M33) -> 28695.01 | N34: =M34-O34 -> 28546.44 | O34: =SUM(O2:O33) -> 148.57 | R34: =M34/26 -> 1103.6542 | S34: /dia
N36: =SUM(N26:N33) -> 2463.25
N37: 2158

Sheet Setembro
B1: FECHO DO DIA | C1: SALT PAY | D1: SANTANDER | E1: GASTOS C/RECIBO | F1: GASTOS S/RECIBO | G1: GLOVO | H1: UBER EATS | I1: VOLUP | J1: BOLT | K1: Transf. Bancária | L1: NUMERARIO | M1: TOTAL | N1: DEPOSITO | O1: EXTRA | P1: FUNDO CAIXA | R1: Num cert
A2: 44805 | B2: 800.88 | C2: 455.78 | D2: 109.3 | H2: 18.9 | L2: 220 | M2: =C2+D2+E2+F2+G2+H2+I2+J2+L2 -> 803.98 | N2: =L2-O2 -> 216.9 | O2: =M2-B2-F2 -> 3.1 | P2: 82.57
A3: 44806 | B3: 1035.27 | C3: 554.47 | D3: 102.6 | L3: 380 | M3: =C3+D3+E3+F3+G3+H3+I3+J3+L3 -> 1037.07 | N3: =L3-O3 -> 378.2 | O3: =M3-B3-F3 -> 1.8 | P3: 82.07
A4: 44807 | B4: 1138.1 | C4: 785.76 | D4: 58.36 | L4: 275 | M4: =C4+D4+E4+F4+G4+H4+I4+J4+L4+K4 -> 1119.12 | N4: =L4-O4 -> 293.98 | O4: =M4-B4-F4 -> -18.98 | P4: 83.07
A5: 44808 | B5: 1004.64 | C5: 601.44 | D5: 65.5 | H5: 37.8 | L5: 320.04 | M5: =C5+D5+E5+F5+G5+H5+I5+J5+L5+K5 -> 1024.78 | N5: =L5-O5 -> 299.9 | O5: =M5-B5-F5 -> 20.14 | P5: 83.11
A6: 44809 | B6: 0 | C6: 0 | D6: 0 | E6: 0 | F6: 0 | G6: 0 | H6: 0 | I6: 0 | J6: 0 | K6: 0 | L6: 0 | M6: 0 | N6: 0 | O6: =M6-B6-F6 -> 0
A7: 44810 | B7: 727.22 | C7: 410.74 | D7: 94.26 | L7: 225 | M7: =C7+D7+E7+F7+G7+H7+I7+J7+L7+K7 -> 730 | N7: =L7-O7 -> 222.22 | O7: =M7-B7-F7 -> 2.78 | P7: 80.66
A8: 44811 | B8: 528.63 | C8: 260.78 | D8: 24.9 | H8: 18.9 | L8: 225 | M8: =C8+D8+E8+F8+G8+H8+I8+J8+L8+K8 -> 529.58 | N8: =L8-O8 -> 224.05 | O8: =M8-B8-F8 -> 0.95 | P8: 80.61
A9: 44812 | B9: 625.4 | C9: 345.94 | D9: 47.46 | H9: 27.9 | L9: 205 | M9: =C9+D9+E9+F9+G9+H9+I9+J9+L9+K9 -> 626.3 | N9: =L9-O9 -> 204.1 | O9: =M9-B9-F9 -> 0.9 | P9: 80.21
A10: 44813 | B10: 856.66 | C10: 483.64 | D10: 53.7 | L10: 320.49 | M10: =C10+D10+E10+F10+G10+H10+I10+J10+L10+K10 -> 857.83 | N10: =L10-O10 -> 319.32 | O10: =M10-B10-F10 -> 1.17
A11: 44814 | B11: 1386.78 | C11: 787.48 | D11: 94.5 | L11: 545 | M11: =C11+D11+E11+F11+G11+H11+I11+J11+L11+K11 -> 1426.98 | N11: =L11-O11 -> 504.8 | O11: =M11-B11-F11 -> 40.2 | P11: 84.1
A12: 44815 | B12: 1632.97 | C12: 967.74 | D12: 89.3 | L12: 611.65 | M12: =C12+D12+E12+F12+G12+H12+I12+J12+L12+K12 -> 1668.69 | N12: =L12-O12 -> 575.93 | O12: =M12-B12-F12 -> 35.72 | P12: 85.75
A13: 44816 | B13: 0 | C13: 0 | D13: 0 | E13: 0 | F13: 0 | G13: 0 | H13: 0 | I13: 0 | J13: 0 | K13: 0 | L13: 0 | M13: 0 | N13: 0 | O13: 0 | P13: 0
A14: 44817 | B14: 304.47 | C14: 211.57 | D14: 22.8 | L14: 75 | M14: =C14+D14+E14+F14+G14+H14+I14+J14+L14+K14 -> 309.37 | N14: =L14-O14 -> 70.1 | O14: =M14-B14-F14 -> 4.9 | P14: 83.05
A15: 44818 | B15: 400.17 | C15: 182.15 | D15: 20.2 | L15: 200 | M15: =C15+D15+E15+F15+G15+H15+I15+J15+L15+K15 -> 402.35 | N15: =L15-O15 -> 197.82 | O15: =M15-B15-F15 -> 2.18 | P15: 83.94
A16: 44819 | B16: 886.85 | C16: 152.51 | D16: 24.5 | K16: 544 | L16: 165 | M16: =C16+D16+E16+F16+G16+H16+I16+J16+L16+K16 -> 886.01 | N16: =L16-O16 -> 165.84 | O16: =M16-B16-F16 -> -0.84 | P16: 83.26
A17: 44820 | B17: 967.99 | C17: 613.75 | D17: 40.24 | L17: 315.3 | M17: =C17+D17+E17+F17+G17+H17+I17+J17+L17+K17 -> 969.29 | N17: =L17-O17 -> 314 | O17: =M17-B17-F17 -> 1.3 | P17: 78.56
A18: 44821 | B18: 1444.28 | C18: 811.98 | D18: 88.4 | L18: 545 | M18: =C18+D18+E18+F18+G18+H18+I18+J18+L18+K18 -> 1445.38 | N18: =L18-O18 -> 543.9 | O18: =M18-B18-F18 -> 1.1 | P18: 80.96
A19: 44822 | B19: 1811.36 | C19: 1080.9 | D19: 136.66 | L19: 590 | M19: =C19+D19+E19+F19+G19+H19+I19+J19+L19+K19 -> 1807.56 | N19: =L19-O19 -> 593.8 | O19: =M19-B19-F19 -> -3.8 | P19: 73.66
A20: 44823 | B20: 0 | C20: 0 | D20: 0 | E20: 0 | L20: 0 | M20: 0 | N20: =L20-O20 -> 0 | O20: =M20-B20-F20 -> 0
A21: 44824 | B21: 663.66 | C21: 313.3 | D21: 35.4 | L21: 315 | M21: =C21+D21+E21+F21+G21+H21+I21+J21+L21+K21 -> 663.7 | N21: =L21-O21 -> 314.96 | O21: =M21-B21-F21 -> 0.04 | P21: 73.64
A22: 44825 | B22: 604.84 | C22: 359.46 | D22: 43.8 | H22: 18.9 | L22: 185 | M22: =C22+D22+E22+F22+G22+H22+I22+J22+L22+K22 -> 607.16 | N22: =L22-O22 -> 182.68 | O22: =M22-B22-F22 -> 2.32 | P22: 73.29
A23: 44826 | B23: 634.63 | C23: 337.75 | D23: 46.3 | L23: 250 | M23: =C23+D23+E23+F23+G23+H23+I23+J23+L23+K23 -> 634.05 | N23: =L23-O23 -> 250.58 | O23: =M23-B23-F23 -> -0.58 | P23: 72.04
A24: 44827 | B24: 847.18 | C24: 594.48 | D24: 59.4 | L24: 204.36 | M24: =C24+D24+E24+F24+G24+H24+I24+J24+L24+K24 -> 858.24 | N24: =L24-O24 -> 193.3 | O24: =M24-B24-F24 -> 11.06 | P24: 71.04
A25: 44828 | B25: 1289.6 | C25: 840.1 | D25: 107.1 | E25: 3.85 | L25: =329.83+15 -> 344.83 | M25: =C25+D25+E25+F25+G25+H25+I25+J25+L25+K25 -> 1295.88 | N25: =L25-O25 -> 338.55 | O25: =M25-B25-F25 -> 6.28 | P25: 80.87
A26: 44829 | B26: 1208.78 | C26: 599.66 | D26: 170.63 | H26: =29+18.9 -> 47.9 | J26: 18.9 | L26: 410.79 | M26: =C26+D26+E26+F26+G26+H26+I26+J26+L26+K26 -> 1247.88 | N26: =L26-O26 -> 371.69 | O26: =M26-B26-F26 -> 39.1 | P26: 76.66
A27: 44830 | B27: 0 | C27: 0 | D27: 0 | L27: 0 | M27: 0 | N27: =L27-O27 -> 0 | O27: =M27-B27-F27 -> 0 | P27: 0
A28: 44831 | B28: 443.48 | C28: 279.5 | D28: 64.48 | L28: 100 | M28: =C28+D28+E28+F28+G28+H28+I28+J28+L28+K28 -> 443.98 | N28: =L28-O28 -> 99.5 | O28: =M28-B28-F28 -> 0.5 | P28: 76.16
A29: 44832 | B29: 300.5 | C29: 202.4 | D29: 26 | L29: 70 | M29: =C29+D29+E29+F29+G29+H29+I29+J29+L29+K29 -> 298.4 | N29: =L29-O29 -> 72.1 | O29: =M29-B29-F29 -> -2.1 | P29: 75.36
A30: 44833 | B30: 201.06 | C30: 64.58 | D30: 40 | L30: 100 | M30: =C30+D30+E30+F30+G30+H30+I30+J30+L30+K30 -> 204.58 | N30: =L30-O30 -> 96.48 | O30: =M30-B30-F30 -> 3.52 | P30: 75.36
A31: 44834 | B31: 420 | C31: 279.5 | D31: 41.2 | H31: 18.9 | L31: 80 | M31: =C31+D31+E31+F31+G31+H31+I31+J31+L31+K31 -> 419.6 | N31: =L31-O31 -> 80.4 | O31: =M31-B31-F31 -> -0.4 | P31: 74.77
M32: =C32+D32+E32+F32+G32+H32+I32+J32+L32+K32 -> 0 | N32: =L32-O32 -> 0 | O32: =M32-B32-F32 -> 0
M33: =C33+D33+E33+F33+G33+H33+I33+J33+L33+K33 -> 0 | N33: =L33-O33 -> 0 | O33: =M33-B33-F33 -> 0
A34: TOTAL | M34: =SUM(M2:M33) -> 22317.76 | N34: =M34-O34 -> 22165.4 | O34: =SUM(O2:O33) -> 152.36

Sheet Novembro
B1: FECHO DO DIA | C1: SALT PAY | D1: SANTANDER | E1: GASTOS C/RECIBO | F1: GASTOS S/RECIBO | G1: GLOVO | H1: UBER EATS | I1: VOLUP | J1: BOLT | K1: Transf. Bancária | L1: NUMERARIO | M1: TOTAL | N1: DEPOSITO | O1: EXTRA | P1: FUNDO CAIXA | R1: Num cert
A2: 44866 | B2: 770.28 | C2: 555.58 | D2: 65.8 | L2: 150 | M2: =C2+D2+E2+F2+G2+H2+I2+J2+L2 -> 771.38 | N2: =L2-O2 -> 148.9 | O2: =M2-B2-F2 -> 1.1 | P2: 73.33
A3: 44867 | B3: 276.18 | C3: 126.46 | D3: 35.98 | L3: 115 | M3: =C3+D3+E3+F3+G3+H3+I3+J3+L3 -> 277.44 | N3: =L3-O3 -> 113.74 | O3: =M3-B3-F3 -> 1.26 | P3: 73.89
A4: 44868 | B4: 279.3 | C4: 202.3 | D4: 12.4 | H4: 20.9 | L4: 50 | M4: =C4+D4+E4+F4+G4+H4+I4+J4+L4+K4 -> 285.6 | N4: =L4-O4 -> 43.7 | O4: =M4-B4-F4 -> 6.3 | P4: 77.29
A5: 44869 | B5: 438.72 | C5: 235.12 | D5: 44.9 | H5: 93.6 | L5: 70 | M5: =C5+D5+E5+F5+G5+H5+I5+J5+L5+K5 -> 443.62 | N5: =L5-O5 -> 65.1 | O5: =M5-B5-F5 -> 4.9 | P5: 72.9
A6: 44870 | B6: 1158.47 | C6: 627.95 | D6: 183.4 | H6: 18.9 | L6: 320 | M6: =C6+D6+E6+F6+G6+H6+I6+J6+L6+K6 -> 1150.25 | N6: =L6-O6 -> 328.22 | O6: =M6-B6-F6 -> -8.22 | P6: 76
A7: 44871 | B7: 750.68 | C7: 404.98 | D7: 114.1 | H7: 83.7 | L7: 150 | M7: =C7+D7+E7+F7+G7+H7+I7+J7+L7+K7 -> 752.78 | N7: =L7-O7 -> 147.9 | O7: =M7-B7-F7 -> 2.1 | P7: 73.1
A8: 44872 | B8: 0 | C8: 0 | D8: 0 | E8: 0 | F8: 0 | G8: 0 | H8: 0 | I8: 0 | J8: 0 | K8: 0 | L8: 0 | M8: =C8+D8+E8+F8+G8+H8+I8+J8+L8+K8 -> 0 | N8: 0 | O8: 0 | P8: 0
A9: 44873 | B9: 76.7 | C9: 25.5 | D9: 3.8 | H9: 18.9 | L9: 25 | M9: =C9+D9+E9+F9+G9+H9+I9+J9+L9+K9 -> 73.2 | N9: =L9-O9 -> 28.5 | O9: =M9-B9-F9 -> -3.5
A10: 44874 | B10: 130 | C10: 54.1 | D10: 27 | L10: 40 | M10: =C10+D10+E10+F10+G10+H10+I10+J10+L10+K10 -> 121.1 | N10: =L10-O10 -> 48.9 | O10: =M10-B10-F10 -> -8.9
A11: 44875 | B11: 286.22 | C11: 146.2 | D11: 11.4 | L11: 130 | M11: =C11+D11+E11+F11+G11+H11+I11+J11+L11+K11 -> 287.6 | N11: =L11-O11 -> 128.62 | O11: =M11-B11-F11 -> 1.38 | P11: 75.86
A12: 44876 | B12: 345.57 | C12: 205.48 | D12: 50 | L12: 95 | M12: =C12+D12+E12+F12+G12+H12+I12+J12+L12+K12 -> 350.48 | N12: =L12-O12 -> 90.09 | O12: =M12-B12-F12 -> 4.91 | P12: 70.96
A13: 44877 | B13: 1435.64 | C13: 847.52 | D13: 169.5 | H13: 74.7 | L13: 365 | M13: =C13+D13+E13+F13+G13+H13+I13+J13+L13+K13 -> 1456.72 | N13: =L13-O13 -> 343.92 | O13: =M13-B13-F13 -> 21.08 | P13: 70.53
A14: 44878 | B14: 443.78 | C14: 265.28 | D14: 49 | L14: 115 | M14: =C14+D14+E14+F14+G14+H14+I14+J14+L14+K14 -> 429.28 | N14: =L14-O14 -> 129.5 | O14: =M14-B14-F14 -> -14.5 | P14: 76.74
A15: 44879 | B15: 0 | C15: 0 | D15: 0 | E15: 0 | F15: 0 | G15: 0 | H15: 0 | I15: 0 | J15: 0 | K15: 0 | L15: 0 | M15: 0 | N15: 0 | O15: 0
A16: 44880 | B16: 192.14 | C16: 172.44 | D16: 0 | L16: 20 | M16: =C16+D16+E16+F16+G16+H16+I16+J16+L16+K16 -> 192.44 | N16: =L16-O16 -> 19.7 | O16: =M16-B16-F16 -> 0.3 | P16: 76.74
A17: 44881 | B17: 59.2 | C17: 59.2 | D17: 0 | L17: 0 | M17: =C17+D17+E17+F17+G17+H17+I17+J17+L17+K17 -> 59.2 | N17: =L17-O17 -> 0 | O17: =M17-B17-F17 -> 0 | P17: 74.46
A18: 44882 | B18: 155.76 | C18: 88.76 | D18: 4.8 | L18: 65 | M18: =C18+D18+E18+F18+G18+H18+I18+J18+L18+K18 -> 158.56 | N18: =L18-O18 -> 62.2 | O18: =M18-B18-F18 -> 2.8 | P18: 70.51
A19: 44883 | B19: 176.18 | C19: 102.28 | D19: 20.5 | L19: 30 | M19: =C19+D19+E19+F19+G19+H19+I19+J19+L19+K19 -> 152.78 | N19: =L19-O19 -> 53.4 | O19: =M19-B19-F19 -> -23.4 | P19: 75.01
A20: 44884 | B20: 386.4 | C20: 253.1 | D20: 48.2 | E20: 11.7 | H20: 18.9 | L20: 55 | M20: =C20+D20+E20+F20+G20+H20+I20+J20+L20+K20 -> 386.9 | N20: =L20-O20 -> 54.5 | O20: =M20-B20-F20 -> 0.5 | P20: 74.54
A21: 44885 | B21: 340.76 | C21: 168.18 | D21: 63.54 | H21: 18.9 | L21: 90 | M21: =C21+D21+E21+F21+G21+H21+I21+J21+L21+K21 -> 340.62 | N21: =L21-O21 -> 90.14 | O21: =M21-B21-F21 -> -0.14 | P21: 73.66
A22: 44886 | B22: 0 | C22: 0 | D22: 0 | E22: 0 | F22: 0 | G22: 0 | H22: 0 | I22: 0 | J22: 0 | K22: 0 | L22: 0 | M22: 0 | N22: =L22-O22 -> 0 | O22: 0 | P22: 0
A23: 44887 | B23: 101.72 | C23: 80.52 | D23: 13.6 | L23: 10 | M23: =C23+D23+E23+F23+G23+H23+I23+J23+L23+K23 -> 104.12 | N23: =L23-O23 -> 7.6 | O23: =M23-B23-F23 -> 2.4 | P23: 71.26
A24: 44888 | B24: 200.03 | C24: 124.13 | D24: 11.4 | L24: 60 | M24: =C24+D24+E24+F24+G24+H24+I24+J24+L24+K24 -> 195.53 | N24: =L24-O24 -> 64.5 | O24: =M24-B24-F24 -> -4.5
A25: 44889 | B25: 104.7 | C25: 55.2 | D25: 0 | L25: 50 | M25: =C25+D25+E25+F25+G25+H25+I25+J25+L25+K25 -> 105.2 | N25: =L25-O25 -> 49.5 | O25: =M25-B25-F25 -> 0.5 | P25: 75.26
A26: 44890 | B26: 518.92 | C26: 121.4 | D26: 28.9 | G26: 18.9 | H26: 18.9 | K26: 254.22 | L26: 75 | M26: =C26+D26+E26+F26+G26+H26+I26+J26+L26+K26 -> 517.32 | N26: =L26-O26 -> 76.6 | O26: =M26-B26-F26 -> -1.6
A27: 44891 | B27: 777.96 | C27: 524.44 | D27: 78.32 | L27: 175 | M27: =C27+D27+E27+F27+G27+H27+I27+J27+L27+K27 -> 777.76 | N27: =L27-O27 -> 175.2 | O27: =M27-B27-F27 -> -0.2 | P27: 76.65
A28: 44892 | B28: 379.81 | C28: 192.93 | D28: 107.18 | L28: 100 | M28: =C28+D28+E28+F28+G28+H28+I28+J28+L28+K28 -> 400.11 | N28: =L28-O28 -> 79.7 | O28: =M28-B28-F28 -> 20.3 | P28: 72.76
A29: 44893 | B29: 675 | C29: 0 | D29: 0 | K29: 675 | L29: 0 | M29: =C29+D29+E29+F29+G29+H29+I29+J29+L29+K29 -> 675 | N29: =L29-O29 -> 0 | O29: =M29-B29-F29 -> 0
A30: 44894 | B30: 0 | C30: 0 | D30: 0 | L30: 0 | M30: =C30+D30+E30+F30+G30+H30+I30+J30+L30+K30 -> 0 | N30: =L30-O30 -> 0 | O30: =M30-B30-F30 -> 0
A31: 44895 | B31: 0 | C31: 0 | D31: 0 | L31: 0 | M31: =C31+D31+E31+F31+G31+H31+I31+J31+L31+K31 -> 0 | N31: =L31-O31 -> 0 | O31: =M31-B31-F31 -> 0
B32: 0 | C32: 0 | D32: 0 | L32: 0 | M32: =C32+D32+E32+F32+G32+H32+I32+J32+L32+K32 -> 0 | N32: =L32-O32 -> 0 | O32: 0
M33: =C33+D33+E33+F33+G33+H33+I33+J33+L33+K33 -> 0 | N33: =L33-O33 -> 0 | O33: =M33-B33-F33 -> 0
A34: TOTAL | M34: =SUM(M2:M33) -> 10464.99 | N34: =M34-O34 -> 10460.12 | O34: =SUM(O2:O33) -> 4.87

Sheet Maio 23
B1: FECHO DO DIA | C1: SALT PAY | D1: SANTANDER | E1: GASTOS C/RECIBO | F1: GASTOS S/RECIBO | G1: GLOVO | H1: UBER EATS | I1: VOLUP | J1: BOLT | K1: Transf. Bancária | L1: NUMERARIO | M1: TOTAL | N1: DEPOSITO | O1: EXTRA | P1: FUNDO CAIXA | R1: Num cert
A2: 45047 | B2: 0 | M2: =C2+D2+E2+F2+G2+H2+I2+J2+L2+K2 -> 0 | N2: =L2-O2 -> 0 | O2: =M2-B2-F2 -> 0
A3: 45048 | B3: 805.8 | C3: 419.7 | D3: 18.7 | H3: 37.8 | L3: 330 | M3: =C3+D3+E3+F3+G3+H3+I3+J3+L3+K3 -> 806.2 | N3: =L3-O3 -> 329.6 | O3: =M3-B3-F3 -> 0.4
A4: 45049 | B4: 291.6 | C4: 176.2 | D4: 64.8 | L4: 50 | M4: =C4+D4+E4+F4+G4+H4+I4+J4+L4+K4 -> 291 | N4: =L4-O4 -> 50.6 | O4: =M4-B4-F4 -> -0.6
A5: 45050 | B5: 477.66 | C5: 354.46 | D5: 26.2 | L5: 100 | M5: =C5+D5+E5+F5+G5+H5+I5+J5+L5+K5 -> 480.66 | N5: =L5-O5 -> 97 | O5: =M5-B5-F5 -> 3 | P5: 74.04
A6: 45051 | B6: 850.52 | C6: 507.22 | D6: 76.91 | H6: 39.9 | K6: 26.55 | L6: 200 | M6: =C6+D6+E6+F6+G6+H6+I6+J6+L6+K6 -> 850.58 | N6: =L6-O6 -> 199.94 | O6: =M6-B6-F6 -> 0.06 | P6: 73.56
A7: 45052 | B7: 1603.78 | C7: 1021.98 | D7: 134.8 | H7: 37.8 | L7: 420 | M7: =C7+D7+E7+F7+G7+H7+I7+J7+L7+K7 -> 1614.58 | N7: =L7-O7 -> 409.2 | O7: =M7-B7-F7 -> 10.8 | P7: 72.61
A8: 45053 | B8: 1891.1 | C8: 1404.9 | D8: 68.8 | H8: 42 | L8: 375 | M8: =C8+D8+E8+F8+G8+H8+I8+J8+L8+K8 -> 1890.7 | N8: =L8-O8 -> 375.4 | O8: =M8-B8-F8 -> -0.4
A9: 45054 | B9: 0 | M9: =C9+D9+E9+F9+G9+H9+I9+J9+L9+K9 -> 0 | N9: =L9-O9 -> 0 | O9: =M9-B9-F9 -> 0
A10: 45055 | B10: 360.42 | C10: 181.7 | D10: 41.02 | L10: 140 | M10: =C10+D10+E10+F10+G10+H10+I10+J10+L10+K10 -> 362.72 | N10: =L10-O10 -> 137.7 | O10: =M10-B10-F10 -> 2.3 | P10: 72.61
A11: 45056 | B11: 368.9 | C11: 221.19 | D11: 10.5 | K11: 55.62 | L11: 90 | M11: =C11+D11+E11+F11+G11+H11+I11+J11+L11+K11 -> 377.31 | N11: =L11-O11 -> 81.59 | O11: =M11-B11-F11 -> 8.41
A12: 45057 | B12: 370.38 | C12: 255.08 | D12: 17.5 | L12: 100 | M12: =C12+D12+E12+F12+G12+H12+I12+J12+L12+K12 -> 372.58 | N12: =L12-O12 -> 97.8 | O12: =M12-B12-F12 -> 2.2
A13: 45058 | B13: 827.7 | C13: 511.72 | D13: 57.6 | H13: 18.9 | K13: 95.88 | L13: 155 | M13: =C13+D13+E13+F13+G13+H13+I13+J13+L13+K13 -> 839.1 | N13: =L13-O13 -> 143.6 | O13: =M13-B13-F13 -> 11.4
A14: 45059 | B14: 1588.41 | C14: 1052 | D14: 133 | H14: 37.8 | L14: 370 | M14: =C14+D14+E14+F14+G14+H14+I14+J14+L14+K14 -> 1592.8 | N14: =L14-O14 -> 365.61 | O14: =M14-B14-F14 -> 4.39
A15: 45060 | B15: 1816.31 | C15: 1279.75 | D15: 113.46 | H15: 18.9 | L15: 410 | M15: =C15+D15+E15+F15+G15+H15+I15+J15+L15+K15 -> 1822.11 | N15: =L15-O15 -> 404.2 | O15: =M15-B15-F15 -> 5.8 | P15: 70.15
A16: 45061 | B16: 554.7 | C16: 440.3 | D16: 29.8 | L16: 90 | M16: =C16+D16+E16+F16+G16+H16+I16+J16+L16+K16 -> 560.1 | N16: =L16-O16 -> 84.6 | O16: =M16-B16-F16 -> 5.4
A17: 45062 | B17: 467.38 | C17: 233.08 | D17: 18.2 | H17: 18.9 | L17: 200 | M17: =C17+D17+E17+F17+G17+H17+I17+J17+L17+K17 -> 470.18 | N17: =L17-O17 -> 197.2 | O17: =M17-B17-F17 -> 2.8
A18: 45063 | B18: 589.8 | C18: 310.7 | D18: 34.6 | H18: 34.1 | L18: 210 | M18: =C18+D18+E18+F18+G18+H18+I18+J18+L18+K18 -> 589.4 | N18: =L18-O18 -> 210.4 | O18: =M18-B18-F18 -> -0.4
A19: 45064 | B19: 544.73 | C19: 396.53 | D19: 38.3 | L19: 110 | M19: =C19+D19+E19+F19+G19+H19+I19+J19+L19+K19 -> 544.83 | N19: =L19-O19 -> 109.9 | O19: =M19-B19-F19 -> 0.1 | P19: 63.78
A20: 45065 | B20: 1296.86 | C20: 565.32 | D20: 127.5 | H20: 94.6 | K20: =236+142.94 -> 378.94 | L20: 135 | M20: =C20+D20+E20+F20+G20+H20+I20+J20+L20+K20 -> 1301.36 | N20: =L20-O20 -> 130.5 | O20: =M20-B20-F20 -> 4.5
A21: 45066 | B21: 1400.19 | C21: 987.99 | D21: 117.9 | H21: 41 | L21: 250 | M21: =C21+D21+E21+F21+G21+H21+I21+J21+L21+K21 -> 1396.89 | N21: =L21-O21 -> 253.3 | O21: =M21-B21-F21 -> -3.3 | P21: 66.58
A22: 45067 | B22: 1700.19 | C22: 1167.55 | D22: 126.06 | L22: 410 | M22: =C22+D22+E22+F22+G22+H22+I22+J22+L22+K22 -> 1703.61 | N22: =L22-O22 -> 406.58 | O22: =M22-B22-F22 -> 3.42
A23: 45068 | B23: 250.1 | C23: 125.3 | D23: 26.6 | L23: 100 | M23: =C23+D23+E23+F23+G23+H23+I23+J23+L23+K23 -> 251.9 | N23: =L23-O23 -> 98.2 | O23: =M23-B23-F23 -> 1.8
A24: 45069 | B24: 567.76 | C24: 315.4 | D24: 46.8 | L24: 210 | M24: =C24+D24+E24+F24+G24+H24+I24+J24+L24+K24 -> 572.2 | N24: =L24-O24 -> 205.56 | O24: =M24-B24-F24 -> 4.44 | P24: 74
A25: 45070 | B25: 451.4 | C25: 296.8 | D25: 2.9 | L25: 160 | M25: =C25+D25+E25+F25+G25+H25+I25+J25+L25+K25 -> 459.7 | N25: =L25-O25 -> 151.7 | O25: =M25-B25-F25 -> 8.3 | P25: 64.31
A26: 45071 | B26: 607.4 | C26: 437.9 | D26: 20.1 | H26: 37.8 | L26: 110 | M26: =C26+D26+E26+F26+G26+H26+I26+J26+L26+K26 -> 605.8 | N26: =L26-O26 -> 111.6 | O26: =M26-B26-F26 -> -1.6
A27: 45072 | B27: =554.7+136.1 -> 690.8 | C27: 417.85 | D27: 21.2 | L27: =130+120 -> 250 | M27: =C27+D27+E27+F27+G27+H27+I27+J27+L27+K27 -> 689.05 | N27: =L27-O27 -> 251.75 | O27: =M27-B27-F27 -> -1.75
A28: 45073 | B28: =1198.38+118.7 -> 1317.08 | C28: 972.88 | D28: 42.7 | H28: 55.8 | L28: =170+75 -> 245 | M28: =C28+D28+E28+F28+G28+H28+I28+J28+L28+K28 -> 1316.38 | N28: =L28-O28 -> 245.7 | O28: =M28-B28-F28 -> -0.7
A29: 45074 | B29: 1096.08 | C29: 577.68 | D29: 72.1 | H29: 65.8 | K29: 260 | L29: 135 | M29: =C29+D29+E29+F29+G29+H29+I29+J29+L29+K29 -> 1110.58 | N29: =L29-O29 -> 120.5 | O29: =M29-B29-F29 -> 14.5
A30: 45075 | B30: 391.86 | C30: 97.12 | D30: 14.4 | K30: 189.66 | L30: 90 | M30: =C30+D30+E30+F30+G30+H30+I30+J30+L30+K30 -> 391.18 | N30: =L30-O30 -> 90.68 | O30: =M30-B30-F30 -> -0.68
A31: 45076 | B31: 536.4 | C31: 251.7 | D31: 57.9 | L31: 225 | M31: =C31+D31+E31+F31+G31+H31+I31+J31+L31+K31 -> 534.6 | N31: =L31-O31 -> 226.8 | O31: =M31-B31-F31 -> -1.8 | P31: 64.36
A32: 45077 | B32: 573.64 | C32: 257.86 | D32: =11.4+16 -> 27.4 | H32: 18.9 | K32: 113.28 | L32: 155 | M32: =C32+D32+E32+F32+G32+H32+I32+J32+L32+K32 -> 572.44 | N32: =L32-O32 -> 156.2 | O32: =M32-B32-F32 -> -1.2
M33: =C33+D33+E33+F33+G33+H33+I33+J33+L33+K33 -> 0 | N33: =L33-O33 -> 0 | O33: =M33-B33-F33 -> 0
A34: TOTAL | M34: =SUM(M2:M33) -> 24370.54 | N34: =M34-O34 -> 24288.95 | O34: =SUM(O2:O33) -> 81.59

Sheet Jun 23 
B1: FECHO DO DIA | C1: SALT PAY | D1: SANTANDER | E1: GASTOS C/RECIBO | F1: GASTOS S/RECIBO | G1: GLOVO | H1: UBER EATS | I1: VOLUP | J1: BOLT | K1: Transf. Bancária | L1: NUMERARIO | M1: TOTAL | N1: DEPOSITO | O1: EXTRA | P1: FUNDO CAIXA | R1: Num cert
A2: 45078 | B2: 709.14 | C2: 408.86 | D2: 62.74 | H2: 91.7 | L2: 160 | M2: =C2+D2+E2+F2+G2+H2+I2+J2+L2+K2 -> 723.3 | N2: =L2-O2 -> 145.84 | O2: =M2-B2-F2 -> 14.16
A3: 45079 | B3: 791.12 | C3: 464.84 | D3: 53.28 | L3: 270 | M3: =C3+D3+E3+F3+G3+H3+I3+J3+L3+K3 -> 788.12 | N3: =L3-O3 -> 273 | O3: =M3-B3-F3 -> -3
A4: 45080 | B4: 1383.24 | C4: 981.14 | D4: 81.5 | L4: 350 | M4: =C4+D4+E4+F4+G4+H4+I4+J4+L4+K4 -> 1412.64 | N4: =L4-O4 -> 320.6 | O4: =M4-B4-F4 -> 29.4
A5: 45081 | B5: 1037.42 | C5: 630.1 | D5: 47.5 | L5: 360 | M5: =C5+D5+E5+F5+G5+H5+I5+J5+L5+K5 -> 1037.6 | N5: =L5-O5 -> 359.82 | O5: =M5-B5-F5 -> 0.18
A6: 45082 | B6: 485.85 | C6: 324.55 | D6: 29.7 | L6: 135 | M6: =C6+D6+E6+F6+G6+H6+I6+J6+L6+K6 -> 489.25 | N6: =L6-O6 -> 131.6 | O6: =M6-B6-F6 -> 3.4
A7: 45083 | B7: 567.26 | C7: 291.6 | D7: 90.1 | H7: 32.9 | K7: 16.96 | L7: 135 | M7: =C7+D7+E7+F7+G7+H7+I7+J7+L7+K7 -> 566.56 | N7: =L7-O7 -> 135.7 | O7: =M7-B7-F7 -> -0.7
A8: 45084 | B8: 888.04 | C8: 193.8 | D8: 44 | K8: =503.59 + 57.85 -> 561.44 | L8: 90 | M8: =C8+D8+E8+F8+G8+H8+I8+J8+L8+K8 -> 889.24 | N8: =L8-O8 -> 88.8 | O8: =M8-B8-F8 -> 1.2
A9: 45085 | B9: 655 | C9: 282.5 | D9: 42.94 | H9: 34 | K9: 176.16 | L9: 120 | M9: =C9+D9+E9+F9+G9+H9+I9+J9+L9+K9 -> 655.6 | N9: =L9-O9 -> 119.4 | O9: =M9-B9-F9 -> 0.6
A10: 45086 | B10: 1176.62 | C10: 428 | D10: 31.5 | K10: 443.22 | L10: 290 | M10: =C10+D10+E10+F10+G10+H10+I10+J10+L10+K10 -> 1192.72 | N10: =L10-O10 -> 273.9 | O10: =M10-B10-F10 -> 16.1
A11: 45087 | B11: 1572.48 | C11: 1057.89 | D11: 114.3 | H11: 18.9 | K11: 60.19 | L11: 330 | M11: =C11+D11+E11+F11+G11+H11+I11+J11+L11+K11 -> 1581.28 | N11: =L11-O11 -> 321.2 | O11: =M11-B11-F11 -> 8.8
A12: 45088 | B12: 1374.1 | C12: 915.9 | D12: 119.4 | H12: 18.9 | L12: 320 | M12: =C12+D12+E12+F12+G12+H12+I12+J12+L12+K12 -> 1374.2 | N12: =L12-O12 -> 319.9 | O12: =M12-B12-F12 -> 0.1
A13: 45089 | B13: 640.96 | C13: 439.02 | D13: 40.24 | H13: 52.8 | L13: 110 | M13: =C13+D13+E13+F13+G13+H13+I13+J13+L13+K13 -> 642.06 | N13: =L13-O13 -> 108.9 | O13: =M13-B13-F13 -> 1.1
A14: 45090 | B14: 537.84 | C14: 329.74 | D14: 24.2 | H14: 18.9 | L14: 165 | M14: =C14+D14+E14+F14+G14+H14+I14+J14+L14+K14 -> 537.84 | N14: =L14-O14 -> 165 | O14: =M14-B14-F14 -> -1.1368684e-13 | P14: 76.81
A15: 45091 | B15: 543.35 | C15: 356.15 | D15: 22 | H15: 19.8 | L15: 145 | M15: =C15+D15+E15+F15+G15+H15+I15+J15+L15+K15 -> 542.95 | N15: =L15-O15 -> 145.4 | O15: =M15-B15-F15 -> -0.4
A16: 45092 | B16: 810.28 | C16: 442.4 | D16: 103.88 | H16: 33.1 | L16: 235 | M16: =C16+D16+E16+F16+G16+H16+I16+J16+L16+K16 -> 814.38 | N16: =L16-O16 -> 230.9 | O16: =M16-B16-F16 -> 4.1
A17: 45093 | B17: 1097.53 | C17: 585.82 | D17: 82.4 | H17: 60.8 | K17: 87.91 | L17: 280 | M17: =C17+D17+E17+F17+G17+H17+I17+J17+L17+K17 -> 1096.93 | N17: =L17-O17 -> 280.6 | O17: =M17-B17-F17 -> -0.6 | P17: 76.83
A18: 45094 | B18: 1773.93 | C18: 1220.82 | D18: 128.91 | H18: 73.7 | L18: 350 | M18: =C18+D18+E18+F18+G18+H18+I18+J18+L18+K18 -> 1773.43 | N18: =L18-O18 -> 350.5 | O18: =M18-B18-F18 -> -0.5
A19: 45095 | B19: 1406.86 | C19: 863.16 | D19: 111.1 | H19: 51.9 | L19: 395 | M19: =C19+D19+E19+F19+G19+H19+I19+J19+L19+K19 -> 1421.16 | N19: =L19-O19 -> 380.7 | O19: =M19-B19-F19 -> 14.3
A20: 45096 | B20: 498.32 | C20: 301.54 | D20: 20 | K20: 25.08 | L20: 150 | M20: =C20+D20+E20+F20+G20+H20+I20+J20+L20+K20 -> 496.62 | N20: =L20-O20 -> 151.7 | O20: =M20-B20-F20 -> -1.7
A21: 45097 | B21: 560.44 | C21: 354.82 | D21: 22.2 | H21: 32.9 | L21: 170 | M21: =C21+D21+E21+F21+G21+H21+I21+J21+L21+K21 -> 579.92 | N21: =L21-O21 -> 150.52 | O21: =M21-B21-F21 -> 19.48
A22: 45098 | B22: 669.26 | C22: 371.48 | D22: 63.2 | H22: 38.9 | L22: 205 | M22: =C22+D22+E22+F22+G22+H22+I22+J22+L22+K22 -> 678.58 | N22: =L22-O22 -> 195.68 | O22: =M22-B22-F22 -> 9.32 | P22: 76.82
A23: 45099 | B23: 958.07 | C23: 622.28 | D23: 64.6 | K23: 56.49 | L23: 210 | M23: =C23+D23+E23+F23+G23+H23+I23+J23+L23+K23 -> 953.37 | N23: =L23-O23 -> 214.7 | O23: =M23-B23-F23 -> -4.7 | P23: 73.59
A24: 45100 | B24: 1299.57 | C24: 780.6 | D24: 75.7 | H24: 37.8 | K24: 89.67 | L24: 320 | M24: =C24+D24+E24+F24+G24+H24+I24+J24+L24+K24 -> 1303.77 | N24: =L24-O24 -> 315.8 | O24: =M24-B24-F24 -> 4.2
A25: 45101 | B25: 2277.21 | C25: 1411.46 | D25: 223.68 | H25: 32.9 | L25: 550 | M25: =C25+D25+E25+F25+G25+H25+I25+J25+L25+K25 -> 2218.04 | N25: =L25-O25 -> 609.17 | O25: =M25-B25-F25 -> -59.17
A26: 45102 | B26: 2148.82 | C26: 1284.82 | D26: 202.4 | G26: 18.9 | L26: 650 | M26: =C26+D26+E26+F26+G26+H26+I26+J26+L26+K26 -> 2156.12 | N26: =L26-O26 -> 642.7 | O26: =M26-B26-F26 -> 7.3
A27: 45103 | B27: 993.02 | C27: 528.18 | D27: 54.2 | H27: 19.9 | K27: 113.24 | L27: 270 | M27: =C27+D27+E27+F27+G27+H27+I27+J27+L27+K27 -> 985.52 | N27: =L27-O27 -> 277.5 | O27: =M27-B27-F27 -> -7.5
A28: 45104 | B28: 1131.86 | C28: 652.46 | D28: 41 | H28: 34 | L28: 420 | M28: =C28+D28+E28+F28+G28+H28+I28+J28+L28+K28 -> 1147.46 | N28: =L28-O28 -> 404.4 | O28: =M28-B28-F28 -> 15.6
A29: 45105 | B29: 907.54 | C29: 477.74 | D29: 75.8 | L29: 350 | M29: =C29+D29+E29+F29+G29+H29+I29+J29+L29+K29 -> 903.54 | N29: =L29-O29 -> 354 | O29: =M29-B29-F29 -> -4
A30: 45106 | B30: 785.39 | C30: 424.59 | D30: 72.2 | L30: 280 | M30: =C30+D30+E30+F30+G30+H30+I30+J30+L30+K30 -> 776.79 | N30: =L30-O30 -> 288.6 | O30: =M30-B30-F30 -> -8.6
A31: 45107 | B31: 1118.33 | C31: 656.49 | D31: 126.4 | H31: 32.9 | L31: 300 | M31: =C31+D31+E31+F31+G31+H31+I31+J31+L31+K31 -> 1115.79 | N31: =L31-O31 -> 302.54 | O31: =M31-B31-F31 -> -2.54
M32: =C32+D32+E32+F32+G32+H32+I32+J32+L32+K32 -> 0 | N32: =L32-O32 -> 0 | O32: =M32-B32-F32 -> 0
A33: TOTAL | M33: =SUM(M2:M32) -> 30854.78 | N33: =M33-O33 -> 30798.85 | O33: =SUM(O2:O32) -> 55.93

Sheet Depositos Bolhão
A1: Dia | B1: Deposito | C1: Num | E1: Pagamentos | F1: Comentario
A2: 45548 | C2: ='Set 24 Bolhão'!Q3 -> 152.7
A3: 45549 | C3: ='Set 24 Bolhão'!Q4 -> 188.3
A4: 45550 | C4: ='Set 24 Bolhão'!Q5 -> 159.9
A5: 45551 | C5: ='Set 24 Bolhão'!Q6 -> 152.3
A6: 45552 | B6: 655 | C6: ='Set 24 Bolhão'!Q7 -> 225
A7: 45553 | C7: ='Set 24 Bolhão'!Q8 -> 96
A8: 45554 | C8: ='Set 24 Bolhão'!Q9 -> 173.1
A9: 45555 | C9: ='Set 24 Bolhão'!Q10 -> 237.3
A10: 45556 | C10: ='Set 24 Bolhão'!Q11 -> 309.6
A11: 45557 | C11: ='Set 24 Bolhão'!Q12 -> 195.1
A12: 45558 | B12: 1230 | C12: ='Set 24 Bolhão'!Q13 -> 0
A13: 45559 | C13: ='Set 24 Bolhão'!Q14 -> 96.4
A14: 45560 | C14: ='Set 24 Bolhão'!Q15 -> 33.8
A15: 45561 | C15: ='Set 24 Bolhão'!Q16 -> 108.4
A16: 45562 | C16: ='Set 24 Bolhão'!Q17 -> 132.3
A17: 45563 | C17: ='Set 24 Bolhão'!Q18 -> 177.8
A18: 45564 | C18: ='Set 24 Bolhão'!Q19 -> 189.8
A19: 45565 | B19: 740 | C19: ='Set 24 Bolhão'!Q20 -> 0
A20: Dia | B20: Deposito | C20: Num | E20: Pagamentos | F20: Comentario
A21: 45566 | C21: ='Out 24 Bolhão'!Q3 -> 47.2
A22: 45567 | C22: ='Out 24 Bolhão'!Q4 -> 63.2
A23: 45568 | C23: ='Out 24 Bolhão'!Q5 -> 100.3
A24: 45569 | C24: ='Out 24 Bolhão'!Q6 -> 148.8
A25: 45570 | C25: ='Out 24 Bolhão'!Q7 -> 109
A26: 45571 | C26: ='Out 24 Bolhão'!Q8 -> 87.9
A27: 45572 | C27: ='Out 24 Bolhão'!Q9 -> 0
A28: 45573 | C28: ='Out 24 Bolhão'!Q10 -> 71.5
A29: 45574 | C29: ='Out 24 Bolhão'!Q11 -> 39.6
A30: 45575 | B30: 625 | C30: ='Out 24 Bolhão'!Q12 -> 49.5
A31: 45576 | C31: ='Out 24 Bolhão'!Q13 -> 93.8
A32: 45577 | C32: ='Out 24 Bolhão'!Q14 -> 226.2
A33: 45578 | C33: ='Out 24 Bolhão'!Q15 -> 144.06
A34: 45579 | C34: ='Out 24 Bolhão'!Q16 -> 0
A35: 45580 | C35: ='Out 24 Bolhão'!Q17 -> 147.3
A36: 45581 | C36: ='Out 24 Bolhão'!Q18 -> 86.6
A37: 45582 | C37: ='Out 24 Bolhão'!Q19 -> 101
A38: 45583 | C38: ='Out 24 Bolhão'!Q20 -> 173.3
A39: 45584 | C39: ='Out 24 Bolhão'!Q21 -> 140.2
A40: 45585 | C40: ='Out 24 Bolhão'!Q22 -> 157.5
A41: 45586 | C41: ='Out 24 Bolhão'!Q23 -> 0
A42: 45587 | B42: 1360 | C42: ='Out 24 Bolhão'!Q24 -> 137.7
A43: 45588 | C43: ='Out 24 Bolhão'!Q25 -> 171
A44: 45589 | C44: ='Out 24 Bolhão'!Q26 -> 152.1
A45: 45590 | C45: ='Out 24 Bolhão'!Q27 -> 126.1
A46: 45591 | C46: ='Out 24 Bolhão'!Q28 -> 142.5
A47: 45592 | C47: ='Out 24 Bolhão'!Q29 -> 168.1
A48: 45593 | B48: 900 | C48: ='Out 24 Bolhão'!Q30 -> 0
A49: 45594 | C49: ='Out 24 Bolhão'!Q31 -> 104.3
A50: 45595 | C50: ='Out 24 Bolhão'!Q32 -> 147.8
A51: 45596 | C51: ='Out 24 Bolhão'!Q33 -> 76.9
A52: Dia | B52: Deposito | C52: Num | E52: Pagamentos | F52: Comentario
A53: 45597 | C53: ='Nov 24 Bolhão'!Q3 -> 254.8
A54: 45598 | C54: ='Nov 24 Bolhão'!Q4 -> 259.4
A55: 45599 | B55: 1005 | C55: ='Nov 24 Bolhão'!Q5 -> 159.9
A56: 45600 | C56: ='Nov 24 Bolhão'!Q6 -> 0
A57: 45601 | C57: ='Nov 24 Bolhão'!Q7 -> 42.2
A58: 45602 | C58: ='Nov 24 Bolhão'!Q8 -> 97.5
A59: 45603 | C59: ='Nov 24 Bolhão'!Q9 -> 145
A60: 45604 | C60: ='Nov 24 Bolhão'!Q10 -> 118.2
A61: 45605 | C61: ='Nov 24 Bolhão'!Q11 -> 72.9
A62: 45606 | C62: ='Nov 24 Bolhão'!Q12 -> 130.8
A63: 45607 | C63: ='Nov 24 Bolhão'!Q13 -> 0
A64: 45608 | C64: ='Nov 24 Bolhão'!Q14 -> 88.4
A65: 45609 | C65: ='Nov 24 Bolhão'!Q15 -> 71.6
A66: 45610 | C66: ='Nov 24 Bolhão'!Q16 -> 46.6
A67: 45611 | C67: ='Nov 24 Bolhão'!Q17 -> 21.5
... A70: 45614 | C70: ='Nov 24 Bolhão'!Q20 -> 0
A71: 45615 | B71: 1135 | C71: ='Nov 24 Bolhão'!Q21 -> 36.9
A72: 45616 | C72: ='Nov 24 Bolhão'!Q22 -> 39.8
A73: 45617 | C73: ='Nov 24 Bolhão'!Q23 -> 44.9
A74: 45618 | C74: ='Nov 24 Bolhão'!Q24 -> 39
A75: 45619 | C75: ='Nov 24 Bolhão'!Q25 -> 70.75
A76: 45620 | C76: ='Nov 24 Bolhão'!Q26 -> 51.6
A77: 45621 | C77: ='Nov 24 Bolhão'!Q27 -> 0
A78: 45622 | B78: 280 | C78: ='Nov 24 Bolhão'!Q28 -> 85.2
A79: 45623 | C79: ='Nov 24 Bolhão'!Q29 -> 47.86 | E79: =5.98+1.41+2+4.59+1.39+3.79 -> 19.16 | F79: Pingo doce e continente
A80: 45624 | C80: ='Nov 24 Bolhão'!Q30 -> 97.4
A81: 45625 | C81: ='Nov 24 Bolhão'!Q31 -> 39.76
A82: 45626 | C82: ='Nov 24 Bolhão'!Q32 -> 131.06
A83: Dia | B83: Deposito | C83: Num | E83: Pagamentos | F83: Comentario
A84: 45627 | C84: ='Dez 24 Bolhao'!O3 -> 95
A85: 45628 | C85: ='Dez 24 Bolhao'!O4 -> 0
A86: 45629 | C86: ='Dez 24 Bolhao'!O5 -> 40
A87: 45630 | C87: ='Dez 24 Bolhao'!O6 -> 80
A88: 45631 | C88: ='Dez 24 Bolhao'!O7 -> 30
A89: 45632 | C89: ='Dez 24 Bolhao'!O8 -> 70
A90: 45633 | C90: ='Dez 24 Bolhao'!O9 -> 80
A91: 45634 | B91: 480 | C91: ='Dez 24 Bolhao'!O10 -> 30 | F91: deposito 26/11 a 01/12
A92: 45635 | C92: ='Dez 24 Bolhao'!O11 -> 0
A93: 45636 | C93: ='Dez 24 Bolhao'!O12 -> 30
A94: 45637 | C94: ='Dez 24 Bolhao'!O13 -> 70
A95: 45638 | C95: ='Dez 24 Bolhao'!O14 -> 20
A96: 45639 | C96: ='Dez 24 Bolhao'!O15 -> 40
A97: 45640 | C97: ='Dez 24 Bolhao'!O16 -> 110
A98: 45641 | C98: ='Dez 24 Bolhao'!O17 -> 45
A99: 45642 | B99: 490 | C99: ='Dez 24 Bolhao'!O18 -> 0 | F99: Depósito de 03 a 13/01
A100: 45643 | C100: ='Dez 24 Bolhao'!O19 -> 10
A101: 45644 | C101: ='Dez 24 Bolhao'!O20 -> 40
A102: 45645 | C102: ='Dez 24 Bolhao'!O21 -> 20
...

Sheet Jul 23
B1: FECHO DO DIA | C1: SALT PAY | D1: SANTANDER | E1: GASTOS C/RECIBO | F1: GASTOS S/RECIBO | G1: GLOVO | H1: UBER EATS | I1: VOLUP | J1: BOLT | K1: Transf. Bancária | L1: NUMERARIO | M1: TOTAL | N1: DEPOSITO | O1: EXTRA | P1: FUNDO CAIXA | R1: Num cert
A2: 45108 | B2: 2301.11 | C2: 1544.31 | D2: 259.7 | H2: 107.7 | L2: 395 | M2: =C2+D2+E2+F2+G2+H2+I2+J2+L2+K2 -> 2306.71 | N2: =L2-O2 -> 389.4 | O2: =M2-B2-F2 -> 5.6 | P2: 70
A3: 45109 | B3: 2085.24 | C3: 1532.44 | D3: 94.4 | H3: 75.8 | L3: 385 | M3: =C3+D3+E3+F3+G3+H3+I3+J3+L3+K3 -> 2087.64 | N3: =L3-O3 -> 382.6 | O3: =M3-B3-F3 -> 2.4 | P3: 65
A4: 45110 | B4: 722.17 | C4: 365.17 | D4: 65.9 | L4: 290 | M4: =C4+D4+E4+F4+G4+H4+I4+J4+L4+K4 -> 721.07 | N4: =L4-O4 -> 291.1 | O4: =M4-B4-F4 -> -1.1
A5: 45111 | B5: 964.04 | C5: 562.84 | D5: 109.3 | H5: 18.9 | L5: 280 | M5: =C5+D5+E5+F5+G5+H5+I5+J5+L5+K5 -> 971.04 | N5: =L5-O5 -> 273 | O5: =M5-B5-F5 -> 7
A6: 45112 | B6: 829.86 | C6: 505.51 | D6: 40 | K6: 25.08 | L6: 260 | M6: =C6+D6+E6+F6+G6+H6+I6+J6+L6+K6 -> 830.59 | N6: =L6-O6 -> 259.27 | O6: =M6-B6-F6 -> 0.73
A7: 45113 | B7: 984.12 | C7: 597.66 | D7: 48.22 | H7: 37.8 | L7: 300 | M7: =C7+D7+E7+F7+G7+H7+I7+J7+L7+K7 -> 983.68 | N7: =L7-O7 -> 300.44 | O7: =M7-B7-F7 -> -0.44
A8: 45114 | B8: 1244.03 | C8: 640.72 | D8: 142.54 | H8: 18.9 | L8: 445 | M8: =C8+D8+E8+F8+G8+H8+I8+J8+L8+K8 -> 1247.16 | N8: =L8-O8 -> 441.87 | O8: =M8-B8-F8 -> 3.13
A9: 45115 | B9: 1671.83 | C9: 1005.7 | D9: 118.1 | L9: 550 | M9: =C9+D9+E9+F9+G9+H9+I9+J9+L9+K9 -> 1673.8 | N9: =L9-O9 -> 548.03 | O9: =M9-B9-F9 -> 1.97
A10: 45116 | B10: 1857.66 | C10: 1242.66 | D10: 120.2 | H10: 82.7 | L10: 405 | M10: =C10+D10+E10+F10+G10+H10+I10+J10+L10+K10 -> 1850.56 | N10: =L10-O10 -> 412.1 | O10: =M10-B10-F10 -> -7.1
A11: 45117 | B11: 890.36 | C11: 442.88 | D11: 91.9 | H11: 19.9 | L11: 335 | M11: =C11+D11+E11+F11+G11+H11+I11+J11+L11+K11 -> 889.68 | N11: =L11-O11 -> 335.68 | O11: =M11-B11-F11 -> -0.68
A12: 45118 | B12: 962.6 | C12: 534.1 | D12: 117.3 | L12: 315 | M12: =C12+D12+E12+F12+G12+H12+I12+J12+L12+K12 -> 966.4 | N12: =L12-O12 -> 311.2 | O12: =M12-B12-F12 -> 3.8
A13: 45119 | B13: 1146.75 | C13: 638.35 | D13: 119.58 | H13: 18.9 | K13: 106.05 | L13: 265 | M13: =C13+D13+E13+F13+G13+H13+I13+J13+L13+K13 -> 1147.88 | N13: =L13-O13 -> 263.87 | O13: =M13-B13-F13 -> 1.13
A14: 45120 | B14: 884.18 | C14: 522.06 | D14: 45.4 | K14: 89.5 | L14: 220 | M14: =C14+D14+E14+F14+G14+H14+I14+J14+L14+K14 -> 876.96 | N14: =L14-O14 -> 227.22 | O14: =M14-B14-F14 -> -7.22
A15: 45121 | B15: 817.28 | C15: 517.96 | D15: 61.6 | L15: 230 | M15: =C15+D15+E15+F15+G15+H15+I15+J15+L15+K15 -> 809.56 | N15: =L15-O15 -> 237.72 | O15: =M15-B15-F15 -> -7.72
A16: 45122 | B16: 1671.18 | C16: 1220.51 | D16: 117.5 | H16: 37.8 | K16: 29.5 | L16: 265 | M16: =C16+D16+E16+F16+G16+H16+I16+J16+L16+K16 -> 1670.31 | N16: =L16-O16 -> 265.87 | O16: =M16-B16-F16 -> -0.87
A17: 45123 | B17: 1542.59 | C17: 1085.85 | D17: 113.22 | H17: 38.8 | L17: 305 | M17: =C17+D17+E17+F17+G17+H17+I17+J17+L17+K17 -> 1542.87 | N17: =L17-O17 -> 304.72 | O17: =M17-B17-F17 -> 0.28
A18: 45124 | B18: 1405 | C18: 425.72 | D18: 40.6 | H18: 20 | K18: =420 + 25.08 -> 445.08 | L18: 475 | M18: =C18+D18+E18+F18+G18+H18+I18+J18+L18+K18 -> 1406.4 | N18: =L18-O18 -> 473.6 | O18: =M18-B18-F18 -> 1.4
A19: 45125 | B19: 1107.06 | C19: 575.56 | D19: 71.1 | H19: 52.8 | L19: 405 | M19: =C19+D19+E19+F19+G19+H19+I19+J19+L19+K19 -> 1104.46 | N19: =L19-O19 -> 407.6 | O19: =M19-B19-F19 -> -2.6
A20: 45126 | B20: 756.72 | C20: 475.62 | D20: 47.7 | H20: 18.9 | L20: 215 | M20: =C20+D20+E20+F20+G20+H20+I20+J20+L20+K20 -> 757.22 | N20: =L20-O20 -> 214.5 | O20: =M20-B20-F20 -> 0.5
A21: 45127 | B21: 928.52 | C21: 605.02 | D21: 53.7 | H21: 18.9 | L21: 250 | M21: =C21+D21+E21+F21+G21+H21+I21+J21+L21+K21 -> 927.62 | N21: =L21-O21 -> 250.9 | O21: =M21-B21-F21 -> -0.9
A22: 45128 | B22: 1157.77 | C22: 755.64 | D22: 61.84 | H22: 18.9 | K22: 38.79 | L22: 285 | M22: =C22+D22+E22+F22+G22+H22+I22+J22+L22+K22 -> 1160.17 | N22: =L22-O22 -> 282.6 | O22: =M22-B22-F22 -> 2.4
A23: 45129 | B23: 2149.51 | C23: 1475.07 | D23: 340.8 | H23: 18.9 | L23: 310 | M23: =C23+D23+E23+F23+G23+H23+I23+J23+L23+K23 -> 2144.77 | N23: =L23-O23 -> 314.74 | O23: =M23-B23-F23 -> -4.74
A24: 45130 | B24: 1676.16 | C24: 1019.53 | D24: 115.73 | G24: 18.9 | L24: 520 | M24: =C24+D24+E24+F24+G24+H24+I24+J24+L24+K24 -> 1674.16 | N24: =L24-O24 -> 522 | O24: =M24-B24-F24 -> -2
A25: 45131 | B25: 984.24 | C25: 551.84 | D25: 44.7 | L25: 390 | M25: =C25+D25+E25+F25+G25+H25+I25+J25+L25+K25 -> 986.54 | N25: =L25-O25 -> 387.7 | O25: =M25-B25-F25 -> 2.3
A26: 45132 | B26: 1675.21 | C26: 438.49 | D26: 86.8 | H26: 19.9 | K26: =795+85.3 -> 880.3 | L26: 250 | M26: =C26+D26+E26+F26+G26+H26+I26+J26+L26+K26 -> 1675.49 | N26: =L26-O26 -> 249.72 | O26: =M26-B26-F26 -> 0.28
A27: 45133 | B27: 1129.04 | C27: 674.54 | D27: 44.9 | L27: 365 | M27: =C27+D27+E27+F27+G27+H27+I27+J27+L27+K27 -> 1084.44 | N27: =L27-O27 -> 409.6 | O27: =M27-B27-F27 -> -44.6
A28: 45134 | B28: 1147.15 | C28: 741.8 | D28: 51.4 | H28: 32.9 | K28: 144.85 | L28: 225 | M28: =C28+D28+E28+F28+G28+H28+I28+J28+L28+K28 -> 1195.95 | N28: =L28-O28 -> 176.2 | O28: =M28-B28-F28 -> 48.8
A29: 45135 | B29: 1552.06 | C29: 977.31 | D29: 101 | H29: 18.9 | K29: =210.33 -> 210.33 | L29: 245 | M29: =C29+D29+E29+F29+G29+H29+I29+J29+L29+K29 -> 1552.54 | N29: =L29-O29 -> 244.52 | O29: =M29-B29-F29 -> 0.48
A30: 45136 | B30: 2039.82 | C30: 1154.12 | D30: 124.9 | H30: 146.5 | L30: 615 | M30: =C30+D30+E30+F30+G30+H30+I30+J30+L30+K30 -> 2040.52 | N30: =L30-O30 -> 614.3 | O30: =M30-B30-F30 -> 0.7
A31: 45137 | B31: 1719.18 | C31: 1090.1 | D31: 113.28 | L31: 515 | M31: =C31+D31+E31+F31+G31+H31+I31+J31+L31+K31 -> 1718.38 | N31: =L31-O31 -> 515.8 | O31: =M31-B31-F31 -> -0.8
A32: 45138 | B32: 1037.4 | C32: 694 | D32: 105.6 | H32: 32.9 | L32: 210 | M32: =C32+D32+E32+F32+G32+H32+I32+J32+L32+K32 -> 1042.5 | N32: =L32-O32 -> 204.9 | O32: =M32-B32-F32 -> 5.1
A33: TOTAL | M33: =SUM(M2:M32) -> 41047.07 | N33: =M33-O33 -> 41039.84 | O33: =SUM(O2:O32) -> 7.23

Sheet Outubro
B1: FECHO DO DIA | C1: SALT PAY | D1: SANTANDER | E1: GASTOS C/RECIBO | F1: GASTOS S/RECIBO | G1: GLOVO | H1: UBER EATS | I1: VOLUP | J1: BOLT | K1: Transf. Bancária | L1: NUMERARIO | M1: TOTAL | N1: DEPOSITO | O1: EXTRA | P1: FUNDO CAIXA | R1: Num cert
A2: 44835 | B2: 1522.94 | C2: 910.14 | D2: 104 | J2: 28.9 | L2: 480 | M2: =C2+D2+E2+F2+G2+H2+I2+J2+L2 -> 1523.04 | N2: =L2-O2 -> 479.9 | O2: =M2-B2-F2 -> 0.1 | P2: 75.05
A3: 44836 | B3: 1501.28 | C3: 1084.68 | D3: 100.95 | L3: 320 | M3: =C3+D3+E3+F3+G3+H3+I3+J3+L3 -> 1505.63 | N3: =L3-O3 -> 315.65 | O3: =M3-B3-F3 -> 4.35 | P3: 74.25
A4: 44837 | B4: 0 | C4: 0 | D4: 0 | L4: 0 | M4: =C4+D4+E4+F4+G4+H4+I4+J4+L4+K4 -> 0 | N4: =L4-O4 -> 0 | O4: =M4-B4-F4 -> 0
A5: 44838 | B5: 539.47 | C5: 251.22 | D5: 42.2 | L5: 245 | M5: =C5+D5+E5+F5+G5+H5+I5+J5+L5+K5 -> 538.42 | N5: =L5-O5 -> 246.05 | O5: =M5-B5-F5 -> -1.05 | P5: 75.25
A6: 44839 | B6: 1503.24 | C6: 738.95 | D6: 99.15 | H6: 56.7 | L6: 610 | M6: =C6+D6+E6+F6+G6+H6+I6+J6+L6+K6 -> 1504.8 | N6: =L6-O6 -> 608.44 | O6: =M6-B6-F6 -> 1.56 | P6: 75.7
A7: 44840 | B7: 412.7 | C7: 301.5 | D7: 17.1 | L7: 95 | M7: =C7+D7+E7+F7+G7+H7+I7+J7+L7+K7 -> 413.6 | N7: =L7-O7 -> 94.1 | O7: =M7-B7-F7 -> 0.9 | P7: 73
A8: 44841 | B8: 538.58 | C8: 285.6 | D8: 56.2 | H8: 46.8 | L8: 150 | M8: =C8+D8+E8+F8+G8+H8+I8+J8+L8+K8 -> 538.6 | N8: =L8-O8 -> 149.98 | O8: =M8-B8-F8 -> 0.02 | P8: 72.9
A9: 44842 | B9: 938.44 | C9: 600.38 | D9: 93 | L9: 245 | M9: =C9+D9+E9+F9+G9+H9+I9+J9+L9+K9 -> 938.38 | N9: =L9-O9 -> 245.06 | O9: =M9-B9-F9 -> -0.06 | P9: 72.75
A10: 44843 | B10: 621.75 | C10: 390.65 | D10: 37.5 | L10: 193.38 | M10: =C10+D10+E10+F10+G10+H10+I10+J10+L10+K10 -> 621.53 | N10: =L10-O10 -> 193.6 | O10: =M10-B10-F10 -> -0.22 | P10: 71.13
A11: 44844 | B11: 0 | C11: 0 | D11: 0 | E11: 0 | F11: 0 | G11: 0 | H11: 0 | I11: 0 | J11: 0 | K11: 0 | L11: 0 | M11: 0 | N11: 0 | O11: 0 | P11: 0
A12: 44845 | B12: 410.77 | C12: 214.63 | D12: 44.6 | H12: 18.9 | L12: 130 | M12: =C12+D12+E12+F12+G12+H12+I12+J12+L12+K12 -> 408.13 | N12: =L12-O12 -> 132.64 | O12: =M12-B12-F12 -> -2.64 | P12: 71.78
A13: 44846 | B13: 600.34 | C13: 211.84 | D13: 55.4 | H13: 18.9 | K13: 201.6 | L13: 115 | M13: =C13+D13+E13+F13+G13+H13+I13+J13+L13+K13 -> 602.74 | N13: =L13-O13 -> 112.6 | O13: =M13-B13-F13 -> 2.4 | P13: 72.98
A14: 44847 | B14: 302.76 | C14: 154.5 | D14: 34.9 | L14: 115 | M14: =C14+D14+E14+F14+G14+H14+I14+J14+L14+K14 -> 304.4 | N14: =L14-O14 -> 113.36 | O14: =M14-B14-F14 -> 1.64 | P14: 71.78
A15: 44848 | B15: 465.58 | C15: 332.14 | D15: 30.5 | L15: 125 | M15: =C15+D15+E15+F15+G15+H15+I15+J15+L15+K15 -> 487.64 | N15: =L15-O15 -> 102.94 | O15: =M15-B15-F15 -> 22.06 | P15: 72.28
A16: 44849 | B16: 599.89 | C16: 336.15 | D16: 8.6 | H16: 18.9 | L16: 235 | M16: =C16+D16+E16+F16+G16+H16+I16+J16+L16+K16 -> 598.65 | N16: =L16-O16 -> 236.24 | O16: =M16-B16-F16 -> -1.24 | P16: 71.27
A17: 44850 | B17: 854.07 | C17: 503.85 | D17: 108 | H17: 36.9 | L17: 205 | M17: =C17+D17+E17+F17+G17+H17+I17+J17+L17+K17 -> 853.75 | N17: =L17-O17 -> 205.32 | O17: =M17-B17-F17 -> -0.32 | P17: 74.12
A18: 44851 | B18: 0 | C18: 0 | D18: 0 | E18: 0 | F18: 0 | G18: 0 | H18: 0 | I18: 0 | J18: 0 | K18: 0 | L18: 0 | M18: =C18+D18+E18+F18+G18+H18+I18+J18+L18+K18 -> 0 | N18: 0 | O18: =M18-B18-F18 -> 0
A19: 44852 | B19: 249.61 | C19: 178.05 | D19: 28.76 | L19: 40 | M19: =C19+D19+E19+F19+G19+H19+I19+J19+L19+K19 -> 246.81 | N19: =L19-O19 -> 42.8 | O19: =M19-B19-F19 -> -2.8
A20: 44853 | B20: 229.95 | C20: 131.95 | D20: 9.6 | K20: 42 | L20: 50 | M20: =C20+D20+E20+F20+G20+H20+I20+J20+L20+K20 -> 233.55 | N20: =L20-O20 -> 46.4 | O20: =M20-B20-F20 -> 3.6 | P20: 73.49
A21: 44854 | B21: 138.06 | C21: 72.76 | D21: 0 | L21: 65 | M21: =C21+D21+E21+F21+G21+H21+I21+J21+L21+K21 -> 137.76 | N21: =L21-O21 -> 65.3 | O21: =M21-B21-F21 -> -0.3 | P21: 74.59
A22: 44855 | B22: 369.86 | C22: 209 | D22: 7.3 | H22: 37.8 | L22: 115 | M22: =C22+D22+E22+F22+G22+H22+I22+J22+L22+K22 -> 369.1 | N22: =L22-O22 -> 115.76 | O22: =M22-B22-F22 -> -0.76 | P22: 75.19
A23: 44856 | B23: 314.13 | C23: 237.13 | D23: 7.6 | L23: 70 | M23: =C23+D23+E23+F23+G23+H23+I23+J23+L23+K23 -> 314.73 | N23: =L23-O23 -> 69.4 | O23: =M23-B23-F23 -> 0.6 | P23: 73.56
A24: 44857 | B24: 429.2 | C24: 206.1 | D24: 17.9 | H24: 37.8 | L24: 170 | M24: =C24+D24+E24+F24+G24+H24+I24+J24+L24+K24 -> 431.8 | N24: =L24-O24 -> 167.4 | O24: =M24-B24-F24 -> 2.6 | P24: 70.92
A25: 44858 | B25: 0 | C25: 0 | D25: 0 | E25: 0 | F25: 0 | G25: 0 | H25: 0 | I25: 0 | J25: 0 | K25: 0 | L25: 0 | M25: 0 | N25: 0 | O25: =M25-B25-F25 -> 0
A26: 44859 | B26: 249.4 | C26: 169.1 | D26: 10 | L26: 70 | M26: =C26+D26+E26+F26+G26+H26+I26+J26+L26+K26 -> 249.1 | N26: =L26-O26 -> 70.3 | O26: =M26-B26-F26 -> -0.3
A27: 44860 | B27: 205.48 | C27: 115.6 | D27: 32.5 | L27: 55 | M27: =C27+D27+E27+F27+G27+H27+I27+J27+L27+K27 -> 203.1 | N27: =L27-O27 -> 57.38 | O27: =M27-B27-F27 -> -2.38 | P27: 73.6
A28: 44861 | B28: 142.52 | C28: 98.04 | D28: 3.2 | L28: 40 | M28: =C28+D28+E28+F28+G28+H28+I28+J28+L28+K28 -> 141.24 | N28: =L28-O28 -> 41.28 | O28: =M28-B28-F28 -> -1.28 | P28: 74.9
A29: 44862 | B29: 176.8 | C29: 83.84 | D29: 14.86 | L29: 80 | M29: =C29+D29+E29+F29+G29+H29+I29+J29+L29+K29 -> 178.7 | N29: =L29-O29 -> 78.1 | O29: =M29-B29-F29 -> 1.9
A30: 44863 | B30: 593.06 | C30: 355.46 | D30: 76.3 | H30: 37.8 | L30: 130 | M30: =C30+D30+E30+F30+G30+H30+I30+J30+L30+K30 -> 599.56 | N30: =L30-O30 -> 123.5 | O30: =M30-B30-F30 -> 6.5 | P30: 77.89
A31: 44864 | B31: 1158.76 | C31: 620.42 | D31: 82.1 | H31: 37.8 | L31: 430 | M31: =C31+D31+E31+F31+G31+H31+I31+J31+L31+K31 -> 1170.32 | N31: =L31-O31 -> 418.44 | O31: =M31-B31-F31 -> 11.56 | P31: 76.33
A32: 44865 | B32: 0 | C32: 0 | D32: 0 | L32: 0 | M32: =C32+D32+E32+F32+G32+H32+I32+J32+L32+K32 -> 0 | N32: 0 | O32: 0
M33: =C33+D33+E33+F33+G33+H33+I33+J33+L33+K33 -> 0 | N33: =L33-O33 -> 0 | O33: =M33-B33-F33 -> 0
A34: TOTAL | M34: =SUM(M2:M33) -> 15115.08 | N34: =M34-O34 -> 15068.64 | O34: =SUM(O2:O33) -> 46.44

Sheet Nov 23
B1: FECHO DO DIA | C1: SALT PAY | D1: SANTANDER | E1: GASTOS C/RECIBO | F1: GASTOS S/RECIBO | G1: GLOVO | H1: UBER EATS | I1: VOLUP | J1: BOLT | K1: Transf. Bancária | L1: NUMERARIO | M1: TOTAL | N1: Numerario Ajustado (depósito) | O1: EXTRA | P1: FUNDO CAIXA | Q1: A DEPOSITAR | R1: Num cert
A2: 45231 | B2: 594.53 | C2: 328.02 | D2: 112.46 | K2: 41.27 | L2: 110 | M2: =C2+D2+E2+F2+G2+H2+I2+J2+L2+K2 -> 591.75 | N2: =L2-O2 -> 112.78 | O2: =M2-B2-F2 -> -2.78
A3: 45232 | B3: 120.66 | C3: 96.96 | D3: 0 | H3: 18.9 | L3: 5 | M3: =C3+D3+E3+F3+G3+H3+I3+J3+L3+K3 -> 120.86 | N3: =L3-O3 -> 4.8 | O3: =M3-B3-F3 -> 0.2
A4: 45233 | B4: 434.24 | C4: 282.54 | D4: 21.9 | H4: 52.8 | L4: 80 | M4: =C4+D4+E4+F4+G4+H4+I4+J4+L4+K4 -> 437.24 | N4: =L4-O4 -> 77 | O4: =M4-B4-F4 -> 3
A5: 45234 | B5: 889.4 | C5: 471.46 | D5: 103.18 | H5: 37.8 | L5: 280 | M5: =C5+D5+E5+F5+G5+H5+I5+J5+L5+K5 -> 892.44 | N5: =L5-O5 -> 276.96 | O5: =M5-B5-F5 -> 3.04
A6: 45235 | B6: 517.88 | C6: 339.62 | D6: 43.2 | H6: 18.9 | L6: 115 | M6: =C6+D6+E6+F6+G6+H6+I6+J6+L6+K6 -> 516.72 | N6: =L6-O6 -> 116.16 | O6: =M6-B6-F6 -> -1.16
A7: 45236 | B7: 195.3 | C7: 165.9 | D7: 0 | L7: 30 | M7: =C7+D7+E7+F7+G7+H7+I7+J7+L7+K7 -> 195.9 | N7: =L7-O7 -> 29.4 | O7: =M7-B7-F7 -> 0.6
A8: 45237 | B8: 153.4 | C8: 94.3 | D8: 15.4 | H8: 18.9 | L8: 25 | M8: =C8+D8+E8+F8+G8+H8+I8+J8+L8+K8 -> 153.6 | N8: =L8-O8 -> 24.8 | O8: =M8-B8-F8 -> 0.2
A9: 45238 | B9: 202.57 | C9: 22.46 | D9: 4.8 | H9: 37.8 | K9: 125.71 | L9: 15 | M9: =C9+D9+E9+F9+G9+H9+I9+J9+L9+K9 -> 205.77 | N9: =L9-O9 -> 11.8 | O9: =M9-B9-F9 -> 3.2
A10: 45239 | B10: 306.42 | C10: 252.62 | D10: 0 | H10: 18.9 | L10: 35 | M10: =C10+D10+E10+F10+G10+H10+I10+J10+L10+K10 -> 306.52 | N10: =L10-O10 -> 34.9 | O10: =M10-B10-F10 -> 0.1
A11: 45240 | B11: 347.3 | C11: 197.35 | D11: 15.9 | H11: 84.7 | L11: 50 | M11: =C11+D11+E11+F11+G11+H11+I11+J11+L11+K11 -> 347.95 | N11: =L11-O11 -> 49.35 | O11: =M11-B11-F11 -> 0.65
A12: 45241 | B12: 714.74 | C12: 469.64 | D12: 25.1 | H12: 37.8 | L12: 180 | M12: =C12+D12+E12+F12+G12+H12+I12+J12+L12+K12 -> 712.54 | N12: =L12-O12 -> 182.2 | O12: =M12-B12-F12 -> -2.2
A13: 45242 | B13: 423.32 | C13: 340.02 | D13: 3.8 | L13: 80 | M13: =C13+D13+E13+F13+G13+H13+I13+J13+L13+K13 -> 423.82 | N13: =L13-O13 -> 79.5 | O13: =M13-B13-F13 -> 0.5
A14: 45243 | B14: 142.4 | C14: 41 | D14: 14.7 | H14: 32.9 | L14: 55 | M14: =C14+D14+E14+F14+G14+H14+I14+J14+L14+K14 -> 143.6 | N14: =L14-O14 -> 53.8 | O14: =M14-B14-F14 -> 1.2
A15: 45244 | B15: 122.2 | C15: 86.4 | D15: 12.2 | L15: 25 | M15: =C15+D15+E15+F15+G15+H15+I15+J15+L15+K15 -> 123.6 | N15: =L15-O15 -> 23.6 | O15: =M15-B15-F15 -> 1.4
A16: 45245 | B16: 266.4 | C16: 174.4 | D16: 21.4 | H16: 19 | L16: 50 | M16: =C16+D16+E16+F16+G16+H16+I16+J16+L16+K16 -> 264.8 | N16: =L16-O16 -> 51.6 | O16: =M16-B16-F16 -> -1.6
A17: 45246 | B17: 148.34 | C17: 109.4 | D17: 4.8 | L17: 40 | M17: =C17+D17+E17+F17+G17+H17+I17+J17+L17+K17 -> 154.2 | N17: =L17-O17 -> 34.14 | O17: =M17-B17-F17 -> 5.86
A18: 45247 | B18: 640.71 | C18: 329.79 | D18: 33 | G18: 18.9 | K18: 74.86 | L18: 185 | M18: =C18+D18+E18+F18+G18+H18+I18+J18+L18+K18 -> 641.55 | N18: =L18-O18 -> 184.16 | O18: =M18-B18-F18 -> 0.84
A19: 45248 | B19: 1320.03 | C19: 882.43 | D19: 187.6 | H19: 51.8 | L19: 200 | M19: =C19+D19+E19+F19+G19+H19+I19+J19+L19+K19 -> 1321.83 | N19: =L19-O19 -> 198.2 | O19: =M19-B19-F19 -> 1.8
A20: 45249 | B20: 1139.94 | C20: 813.48 | D20: 61.1 | H20: 32.9 | L20: 235 | M20: =C20+D20+E20+F20+G20+H20+I20+J20+L20+K20 -> 1142.48 | N20: =L20-O20 -> 232.46 | O20: =M20-B20-F20 -> 2.54
A21: 45250 | B21: 317.74 | C21: 170.48 | D21: 24.6 | H21: 18.9 | K21: =7.38 -> 7.38 | L21: 100 | M21: =C21+D21+E21+F21+G21+H21+I21+J21+L21+K21 -> 321.36 | N21: =L21-O21 -> 96.38 | O21: =M21-B21-F21 -> 3.62
A22: 45251 | B22: 342.9 | C22: 192.7 | D22: 27.4 | H22: 33.9 | L22: 90 | M22: =C22+D22+E22+F22+G22+H22+I22+J22+L22+K22 -> 344 | N22: =L22-O22 -> 88.9 | O22: =M22-B22-F22 -> 1.1
A23: 45252 | B23: 390.18 | C23: 249.56 | D23: 46.6 | K23: =14+16.72 -> 30.72 | L23: 65 | M23: =C23+D23+E23+F23+G23+H23+I23+J23+L23+K23 -> 391.88 | N23: =L23-O23 -> 63.3 | O23: =M23-B23-F23 -> 1.7
A24: 45253 | B24: 322.77 | C24: 176.47 | D24: 44.02 | L24: 100 | M24: =C24+D24+E24+F24+G24+H24+I24+J24+L24+K24 -> 320.49 | N24: =L24-O24 -> 102.28 | O24: =M24-B24-F24 -> -2.28
A25: 45254 | B25: 619.45 | C25: 375.14 | D25: 37.4 | H25: 39.9 | K25: =21.09 -> 21.09 | L25: 145 | M25: =C25+D25+E25+F25+G25+H25+I25+J25+L25+K25 -> 618.53 | N25: =L25-O25 -> 145.92 | O25: =M25-B25-F25 -> -0.92
A26: 45255 | B26: 1108.54 | C26: 688.52 | D26: 73.2 | H26: 69.8 | K26: 40.62 | L26: 195 | M26: =C26+D26+E26+F26+G26+H26+I26+J26+L26+K26 -> 1067.14 | N26: =L26-O26 -> 236.4 | O26: =M26-B26-F26 -> -41.4
A27: 45256 | B27: 552.5 | C27: 355.5 | D27: 73.8 | G27: 18.1 | L27: 125 | M27: =C27+D27+E27+F27+G27+H27+I27+J27+L27+K27 -> 572.4 | N27: =L27-O27 -> 105.1 | O27: =M27-B27-F27 -> 19.9
A28: 45257 | B28: 159.02 | C28: 49.2 | D28: 39.32 | G28: 18.9 | L28: 50 | M28: =C28+D28+E28+F28+G28+H28+I28+J28+L28+K28 -> 157.42 | N28: =L28-O28 -> 51.6 | O28: =M28-B28-F28 -> -1.6
A29: 45258 | B29: 126.4 | C29: 98.7 | D29: 18.1 | L29: 15 | M29: =C29+D29+E29+F29+G29+H29+I29+J29+L29+K29 -> 131.8 | N29: =L29-O29 -> 9.6 | O29: =M29-B29-F29 -> 5.4
A30: 45259 | B30: 65.7 | C30: 28.8 | D30: 11.2 | H30: 18.9 | L30: 10 | M30: =C30+D30+E30+F30+G30+H30+I30+J30+L30+K30 -> 68.9 | N30: =L30-O30 -> 6.8 | O30: =M30-B30-F30 -> 3.2
A31: 45260 | B31: 208.14 | C31: 123.04 | D31: 10.8 | H31: 18.9 | L31: 50 | M31: =C31+D31+E31+F31+G31+H31+I31+J31+L31+K31 -> 202.74 | N31: =L31-O31 -> 55.4 | O31: =M31-B31-F31 -> -5.4
M32: =C32+D32+E32+F32+G32+H32+I32+J32+L32+K32 -> 0 | N32: =L32-O32 -> 0 | O32: =M32-B32-F32 -> 0
A33: TOTAL | M33: =SUM(M2:M32) -> 12893.83 | N33: =M33-O33 -> 12893.12 | O33: =SUM(O2:O32) -> 0.71

Sheet Dezembro
B1: FECHO DO DIA | C1: SALT PAY | D1: SANTANDER | E1: GASTOS C/RECIBO | F1: GASTOS S/RECIBO | G1: GLOVO | H1: UBER EATS | I1: VOLUP | J1: BOLT | K1: Transf. Bancária | L1: NUMERARIO | M1: TOTAL | N1: DEPOSITO | O1: EXTRA | P1: FUNDO CAIXA | R1: Num cert
A2: 44896 | B2: 0 | C2: 0 | D2: 0 | E2: 0 | F2: 0 | G2: 0 | H2: 0 | I2: 0 | J2: 0 | K2: 0 | L2: 0 | M2: =C2+D2+E2+F2+G2+H2+I2+J2+L2+K2 -> 0 | N2: =L2-O2 -> 0 | O2: =M2-B2-F2 -> 0
A3: 44897 | B3: 0 | C3: 0 | D3: 0 | E3: 0 | F3: 0 | G3: 0 | H3: 0 | I3: 0 | J3: 0 | K3: 0 | L3: 0 | M3: =C3+D3+E3+F3+G3+H3+I3+J3+L3+K3 -> 0 | N3: =L3-O3 -> 0 | O3: =M3-B3-F3 -> 0
A4: 44898 | B4: 0 | C4: 0 | D4: 0 | E4: 0 | F4: 0 | G4: 0 | H4: 0 | I4: 0 | J4: 0 | K4: 0 | L4: 0 | M4: =C4+D4+E4+F4+G4+H4+I4+J4+L4+K4 -> 0 | N4: =L4-O4 -> 0 | O4: =M4-B4-F4 -> 0
A5: 44899 | B5: 0 | C5: 0 | D5: 0 | E5: 0 | F5: 0 | G5: 0 | H5: 0 | I5: 0 | J5: 0 | K5: 0 | L5: 0 | M5: =C5+D5+E5+F5+G5+H5+I5+J5+L5+K5 -> 0 | N5: =L5-O5 -> 0 | O5: =M5-B5-F5 -> 0
A6: 44900 | B6: 0 | C6: 0 | D6: 0 | E6: 0 | F6: 0 | G6: 0 | H6: 0 | I6: 0 | J6: 0 | K6: 0 | L6: 0 | M6: =C6+D6+E6+F6+G6+H6+I6+J6+L6+K6 -> 0 | N6: =L6-O6 -> 0 | O6: =M6-B6-F6 -> 0
A7: 44901 | B7: 0 | C7: 0 | D7: 0 | E7: 0 | F7: 0 | G7: 0 | H7: 0 | I7: 0 | J7: 0 | K7: 0 | L7: 0 | M7: =C7+D7+E7+F7+G7+H7+I7+J7+L7+K7 -> 0 | N7: =L7-O7 -> 0 | O7: =M7-B7-F7 -> 0
A8: 44902 | B8: 0 | C8: 0 | D8: 0 | E8: 0 | F8: 0 | G8: 0 | H8: 0 | I8: 0 | J8: 0 | K8: 0 | L8: 0 | M8: =C8+D8+E8+F8+G8+H8+I8+J8+L8+K8 -> 0 | N8: 0 | O8: 0
A9: 44903 | B9: 0 | C9: 0 | D9: 0 | E9: 0 | F9: 0 | G9: 0 | H9: 0 | I9: 0 | J9: 0 | K9: 0 | L9: 0 | M9: =C9+D9+E9+F9+G9+H9+I9+J9+L9+K9 -> 0 | N9: =L9-O9 -> 0 | O9: =M9-B9-F9 -> 0
A10: 44904 | B10: 0 | C10: 0 | D10: 0 | E10: 0 | F10: 0 | G10: 0 | H10: 0 | I10: 0 | J10: 0 | K10: 0 | L10: 0 | M10: =C10+D10+E10+F10+G10+H10+I10+J10+L10+K10 -> 0 | N10: =L10-O10 -> 0 | O10: =M10-B10-F10 -> 0
A11: 44905 | B11: 0 | C11: 0 | D11: 0 | E11: 0 | F11: 0 | G11: 0 | H11: 0 | I11: 0 | J11: 0 | K11: 0 | L11: 0 | M11: =C11+D11+E11+F11+G11+H11+I11+J11+L11+K11 -> 0 | N11: =L11-O11 -> 0 | O11: =M11-B11-F11 -> 0
A12: 44906 | B12: 0 | C12: 0 | D12: 0 | E12: 0 | F12: 0 | G12: 0 | H12: 0 | I12: 0 | J12: 0 | K12: 0 | L12: 0 | M12: =C12+D12+E12+F12+G12+H12+I12+J12+L12+K12 -> 0 | N12: =L12-O12 -> 0 | O12: =M12-B12-F12 -> 0
A13: 44907 | B13: 0 | C13: 0 | D13: 0 | E13: 0 | F13: 0 | G13: 0 | H13: 0 | I13: 0 | J13: 0 | K13: 0 | L13: 0 | M13: =C13+D13+E13+F13+G13+H13+I13+J13+L13+K13 -> 0 | N13: =L13-O13 -> 0 | O13: =M13-B13-F13 -> 0
A14: 44908 | B14: 111.58 | C14: 46.8 | D14: 10.5 | E14: =6.89+1.69 -> 8.58 | L14: 50 | M14: =C14+D14+E14+F14+G14+H14+I14+J14+L14+K14 -> 115.88 | N14: =L14-O14 -> 45.7 | O14: =M14-B14-F14 -> 4.3 | P14: 68.5
A15: 44909 | B15: 105.12 | C15: 35.1 | D15: 15.82 | H15: 37.8 | L15: 10 | M15: =C15+D15+E15+F15+G15+H15+I15+J15+L15+K15 -> 98.72 | N15: =L15-O15 -> 16.4 | O15: =M15-B15-F15 -> -6.4 | P15: 74.86
A16: 44910 | B16: 104.8 | C16: 93 | D16: 2.2 | L16: 10 | M16: =C16+D16+E16+F16+G16+H16+I16+J16+L16+K16 -> 105.2 | N16: =L16-O16 -> 9.6 | O16: =M16-B16-F16 -> 0.4 | P16: 74.5
A17: 44911 | B17: 334 | C17: 198.02 | D17: 7.4 | L17: 130 | M17: =C17+D17+E17+F17+G17+H17+I17+J17+L17+K17 -> 335.42 | N17: =L17-O17 -> 128.58 | O17: =M17-B17-F17 -> 1.42 | P17: 73.28
A18: 44912 | B18: 397.88 | C18: 246.18 | D18: 107 | L18: 45 | M18: =C18+D18+E18+F18+G18+H18+I18+J18+L18+K18 -> 398.18 | N18: =L18-O18 -> 44.7 | O18: =M18-B18-F18 -> 0.3
A19: 44913 | B19: 310.3 | C19: 122.8 | D19: 20 | H19: 95.7 | L19: 80 | M19: =C19+D19+E19+F19+G19+H19+I19+J19+L19+K19 -> 318.5 | N19: =L19-O19 -> 71.8 | O19: =M19-B19-F19 -> 8.2 | P19: 72.48
A20: 44914 | B20: 0 | C20: 0 | D20: 0 | E20: 0 | F20: 0 | G20: 0 | H20: 0 | I20: 0 | J20: 0 | K20: 0 | L20: 0 | M20: 0 | N20: =L20-O20 -> 0 | O20: =M20-B20-F20 -> 0
A21: 44915 | B21: 328.46 | C21: 197.22 | D21: 1.69 | L21: 130 | M21: =C21+D21+E21+F21+G21+H21+I21+J21+L21+K21 -> 328.91 | N21: =L21-O21 -> 129.55 | O21: =M21-B21-F21 -> 0.45 | P21: 72.13
A22: 44916 | B22: 202.32 | C22: 122.44 | D22: 30.18 | L22: 50 | M22: =C22+D22+E22+F22+G22+H22+I22+J22+L22+K22 -> 202.62 | N22: =L22-O22 -> 49.7 | O22: =M22-B22-F22 -> 0.3 | P22: 71.83
A23: 44917 | B23: 259.68 | C23: 189.38 | D23: 44.1 | L23: 25 | M23: =C23+D23+E23+F23+G23+H23+I23+J23+L23+K23 -> 258.48 | N23: =L23-O23 -> 26.2 | O23: =M23-B23-F23 -> -1.2 | P23: 69.81
A24: 44918 | B24: 477.57 | C24: 295.97 | D24: 101.4 | L24: 80 | M24: =C24+D24+E24+F24+G24+H24+I24+J24+L24+K24 -> 477.37 | N24: =L24-O24 -> 80.2 | O24: =M24-B24-F24 -> -0.2 | P24: 70.51
A25: 44919 | B25: 290.77 | C25: 232.69 | D25: 48.48 | L25: 10 | M25: =C25+D25+E25+F25+G25+H25+I25+J25+L25+K25 -> 291.17 | N25: =L25-O25 -> 9.6 | O25: =M25-B25-F25 -> 0.4 | P25: 69.99
A26: 44920 | B26: 0 | M26: =C26+D26+E26+F26+G26+H26+I26+J26+L26+K26 -> 0 | N26: =L26-O26 -> 0 | O26: =M26-B26-F26 -> 0
A27: 44921 | B27: 0 | M27: =C27+D27+E27+F27+G27+H27+I27+J27+L27+K27 -> 0 | N27: =L27-O27 -> 0 | O27: =M27-B27-F27 -> 0
A28: 44922 | B28: 272.9 | C28: 162.2 | D28: 22.7 | E28: =9.4+1.6 -> 11 | L28: 80 | M28: =C28+D28+E28+F28+G28+H28+I28+J28+L28+K28 -> 275.9 | N28: =L28-O28 -> 77 | O28: =M28-B28-F28 -> 3 | P28: 66.91
A29: 44923 | B29: 428.42 | C29: 183.78 | D29: 6.8 | H29: 37.8 | K29: 196.24 | L29: 5 | M29: =C29+D29+E29+F29+G29+H29+I29+J29+L29+K29 -> 429.62 | N29: =L29-O29 -> 3.8 | O29: =M29-B29-F29 -> 1.2 | P29: 65.91
A30: 44924 | B30: 95.28 | C30: 39.3 | D30: 21.3 | L30: 35 | M30: =C30+D30+E30+F30+G30+H30+I30+J30+L30+K30 -> 95.6 | N30: =L30-O30 -> 34.68 | O30: =M30-B30-F30 -> 0.32 | P30: 65.59
A31: 44925 | B31: 483.37 | C31: 286.67 | D31: 46.64 | H31: 18.9 | L31: 135 | M31: =C31+D31+E31+F31+G31+H31+I31+J31+L31+K31 -> 487.21 | N31: =L31-O31 -> 131.16 | O31: =M31-B31-F31 -> 3.84 | P31: 66.75
A32: 44926 | B32: 370.5 | C32: 307.06 | D32: 0 | L32: 65 | M32: =C32+D32+E32+F32+G32+H32+I32+J32+L32+K32 -> 372.06 | N32: =L32-O32 -> 63.44 | O32: =M32-B32-F32 -> 1.56
M33: =C33+D33+E33+F33+G33+H33+I33+J33+L33+K33 -> 0 | N33: =L33-O33 -> 0 | O33: =M33-B33-F33 -> 0
A34: TOTAL | M34: =SUM(M2:M33) -> 4590.84 | N34: =M34-O34 -> 4572.95 | O34: =SUM(O2:O33) -> 17.89

Sheet Dez 23
B1: FECHO DO DIA | C1: SALT PAY | D1: SANTANDER | E1: GASTOS C/RECIBO | F1: GASTOS S/RECIBO | G1: GLOVO | H1: UBER EATS | I1: VOLUP | J1: BOLT | K1: Transf. Bancária | L1: NUMERARIO | M1: TOTAL | N1: DEPOSITO | O1: EXTRA | P1: FUNDO CAIXA | R1: Num cert
A2: 45261 | B2: 429.14 | C2: 351.14 | D2: 15.4 | L2: 60 | M2: =C2+D2+E2+F2+G2+H2+I2+J2+L2+K2 -> 426.54 | N2: =L2-O2 -> 62.6 | O2: =M2-B2-F2 -> -2.6
A3: 45262 | B3: 750.62 | C3: 445.8 | D3: 120.64 | H3: 32.9 | L3: 160 | M3: =C3+D3+E3+F3+G3+H3+I3+J3+L3+K3 -> 759.34 | N3: =L3-O3 -> 151.28 | O3: =M3-B3-F3 -> 8.72
A4: 45263 | B4: 261.72 | C4: 198.02 | D4: 21.6 | L4: 40 | M4: =C4+D4+E4+F4+G4+H4+I4+J4+L4+K4 -> 259.62 | N4: =L4-O4 -> 42.1 | O4: =M4-B4-F4 -> -2.1
A5: 45264 | B5: 174.42 | C5: 80.6 | D5: 52.22 | L5: 40 | M5: =C5+D5+E5+F5+G5+H5+I5+J5+L5+K5 -> 172.82 | N5: =L5-O5 -> 41.6 | O5: =M5-B5-F5 -> -1.6
A6: 45265 | B6: 248.74 | C6: 48.54 | D6: 13.4 | H6: 18.9 | K6: 131.2 | L6: 35 | M6: =C6+D6+E6+F6+G6+H6+I6+J6+L6+K6 -> 247.04 | N6: =L6-O6 -> 36.7 | O6: =M6-B6-F6 -> -1.7
A7: 45266 | B7: 295.35 | C7: 143.78 | D7: 10.6 | K7: 86.97 | L7: 50 | M7: =C7+D7+E7+F7+G7+H7+I7+J7+L7+K7 -> 291.35 | N7: =L7-O7 -> 54 | O7: =M7-B7-F7 -> -4
A8: 45267 | B8: 218.19 | C8: 195.39 | D8: 2.9 | H8: 19.9 | L8: 0 | M8: =C8+D8+E8+F8+G8+H8+I8+J8+L8+K8 -> 218.19 | N8: =L8-O8 -> 0 | O8: =M8-B8-F8 -> 0
A9: 45268 | B9: 646.61 | C9: 323.72 | D9: 49.8 | H9: 39.9 | K9: 73.9 | L9: 160 | M9: =C9+D9+E9+F9+G9+H9+I9+J9+L9+K9 -> 647.32 | N9: =L9-O9 -> 159.29 | O9: =M9-B9-F9 -> 0.71
A10: 45269 | B10: 590.54 | C10: 96.8 | D10: 257.16 | H10: 32.9 | L10: 205 | M10: =C10+D10+E10+F10+G10+H10+I10+J10+L10+K10 -> 591.86 | N10: =L10-O10 -> 203.68 | O10: =M10-B10-F10 -> 1.32
A11: 45270 | B11: 259.52 | C11: 195.3 | D11: 15.62 | L11: 50 | M11: =C11+D11+E11+F11+G11+H11+I11+J11+L11+K11 -> 260.92 | N11: =L11-O11 -> 48.6 | O11: =M11-B11-F11 -> 1.4
A12: 45271 | B12: 158.2 | C12: 89.38 | D12: 19.22 | L12: 50 | M12: =C12+D12+E12+F12+G12+H12+I12+J12+L12+K12 -> 158.6 | N12: =L12-O12 -> 49.6 | O12: =M12-B12-F12 -> 0.4
A13: 45272 | B13: 211.43 | C13: 101.56 | D13: 60.15 | K13: 24.06 | L13: 25 | M13: =C13+D13+E13+F13+G13+H13+I13+J13+L13+K13 -> 210.77 | N13: =L13-O13 -> 25.66 | O13: =M13-B13-F13 -> -0.66
A14: 45273 | B14: 206.46 | C14: 107.36 | D14: 0 | H14: 52.8 | L14: 50 | M14: =C14+D14+E14+F14+G14+H14+I14+J14+L14+K14 -> 210.16 | N14: =L14-O14 -> 46.3 | O14: =M14-B14-F14 -> 3.7
A15: 45274 | B15: 373.8 | C15: 269.5 | D15: 36.1 | L15: 70 | M15: =C15+D15+E15+F15+G15+H15+I15+J15+L15+K15 -> 375.6 | N15: =L15-O15 -> 68.2 | O15: =M15-B15-F15 -> 1.8
A16: 45275 | B16: 705.54 | C16: 342.18 | D16: 2.32 | K16: 209.04 | L16: 150 | M16: =C16+D16+E16+F16+G16+H16+I16+J16+L16+K16 -> 703.54 | N16: =L16-O16 -> 152 | O16: =M16-B16-F16 -> -2
A17: 45276 | B17: 1018.93 | C17: 737.23 | D17: 101 | H17: 18.9 | L17: 150 | M17: =C17+D17+E17+F17+G17+H17+I17+J17+L17+K17 -> 1007.13 | N17: =L17-O17 -> 161.8 | O17: =M17-B17-F17 -> -11.8
A18: 45277 | B18: 801.34 | C18: 608.34 | D18: 30.4 | H18: 51.8 | L18: 110 | M18: =C18+D18+E18+F18+G18+H18+I18+J18+L18+K18 -> 800.54 | N18: =L18-O18 -> 110.8 | O18: =M18-B18-F18 -> -0.8
A19: 45278 | B19: 243.08 | C19: 165.18 | D19: 0 | H19: 33.9 | L19: 45 | M19: =C19+D19+E19+F19+G19+H19+I19+J19+L19+K19 -> 244.08 | N19: =L19-O19 -> 44 | O19: =M19-B19-F19 -> 1
A20: 45279 | B20: 173.8 | C20: 145.2 | D20: 4.8 | L20: 20 | M20: =C20+D20+E20+F20+G20+H20+I20+J20+L20+K20 -> 170 | N20: =L20-O20 -> 23.8 | O20: =M20-B20-F20 -> -3.8
A21: 45280 | B21: 178.4 | C21: 102.8 | D21: 6.3 | L21: 70 | M21: =C21+D21+E21+F21+G21+H21+I21+J21+L21+K21 -> 179.1 | N21: =L21-O21 -> 69.3 | O21: =M21-B21-F21 -> 0.7
A22: 45281 | B22: 400.38 | C22: 292.48 | D22: 18.7 | L22: 90 | M22: =C22+D22+E22+F22+G22+H22+I22+J22+L22+K22 -> 401.18 | N22: =L22-O22 -> 89.2 | O22: =M22-B22-F22 -> 0.8
A23: 45282 | B23: 592.47 | C23: 374.6 | D23: 22 | H23: 51.8 | K23: 78.47 | L23: 70 | M23: =C23+D23+E23+F23+G23+H23+I23+J23+L23+K23 -> 596.87 | N23: =L23-O23 -> 65.6 | O23: =M23-B23-F23 -> 4.4
A24: 45283 | B24: 719.5 | C24: 452.04 | D24: 97.02 | H24: 51.8 | L24: 125 | M24: =C24+D24+E24+F24+G24+H24+I24+J24+L24+K24 -> 725.86 | N24: =L24-O24 -> 118.64 | O24: =M24-B24-F24 -> 6.36
A25: 45284 | B25: 119.68 | C25: 106.94 | D25: 11.74 | L25: 0 | M25: =C25+D25+E25+F25+G25+H25+I25+J25+L25+K25 -> 118.68 | N25: =L25-O25 -> 1 | O25: =M25-B25-F25 -> -1
A26: 45285 | B26: 0 | M26: =C26+D26+E26+F26+G26+H26+I26+J26+L26+K26 -> 0 | N26: =L26-O26 -> 0 | O26: =M26-B26-F26 -> 0
A27: 45286 | B27: 324.34 | C27: 221.94 | D27: 15.4 | H27: 18.9 | L27: 90 | M27: =C27+D27+E27+F27+G27+H27+I27+J27+L27+K27 -> 346.24 | N27: =L27-O27 -> 68.1 | O27: =M27-B27-F27 -> 21.9
A28: 45287 | B28: 305.3 | C28: 170.8 | D28: 15.4 | G28: 37.8 | H28: 39.9 | L28: 40 | M28: =C28+D28+E28+F28+G28+H28+I28+J28+L28+K28 -> 303.9 | N28: =L28-O28 -> 41.4 | O28: =M28-B28-F28 -> -1.4
A29: 45288 | B29: 319.37 | C29: 113.6 | D29: 79.72 | K29: 92.55 | L29: 35 | M29: =C29+D29+E29+F29+G29+H29+I29+J29+L29+K29 -> 320.87 | N29: =L29-O29 -> 33.5 | O29: =M29-B29-F29 -> 1.5
A30: 45289 | B30: 328.98 | C30: 191.44 | D30: 19.9 | L30: 155 | M30: =C30+D30+E30+F30+G30+H30+I30+J30+L30+K30 -> 366.34 | N30: =L30-O30 -> 117.64 | O30: =M30-B30-F30 -> 37.36
A31: 45290 | B31: 639.06 | C31: =379.46+69.7+5.8 -> 454.96 | D31: 43 | H31: 52.8 | L31: 90 | M31: =C31+D31+E31+F31+G31+H31+I31+J31+L31+K31 -> 640.76 | N31: =L31-O31 -> 88.3 | O31: =M31-B31-F31 -> 1.7
A32: 45291 | B32: 468.95 | C32: 430.35 | D32: 3.8 | L32: 45 | M32: =C32+D32+E32+F32+G32+H32+I32+J32+L32+K32 -> 479.15 | N32: =L32-O32 -> 34.8 | O32: =M32-B32-F32 -> 10.2
A33: TOTAL | M33: =SUM(M2:M32) -> 12234.37 | N33: =M33-O33 -> 12163.86 | O33: =SUM(O2:O32) -> 70.51

Sheet Jan 23
B1: FECHO DO DIA | C1: SALT PAY | D1: SANTANDER | E1: GASTOS C/RECIBO | F1: GASTOS S/RECIBO | G1: GLOVO | H1: UBER EATS | I1: VOLUP | J1: BOLT | K1: Transf. Bancária | L1: NUMERARIO | M1: TOTAL | N1: DEPOSITO | O1: EXTRA | P1: FUNDO CAIXA | R1: Num cert
A2: 44927 | B2: 0 | C2: 0 | D2: 0 | E2: 0 | F2: 0 | G2: 0 | H2: 0 | I2: 0 | J2: 0 | K2: 0 | L2: 0 | M2: =C2+D2+E2+F2+G2+H2+I2+J2+L2+K2 -> 0 | N2: =L2-O2 -> 0 | O2: =M2-B2-F2 -> 0
A3: 44928 | B3: 0 | C3: 0 | D3: 0 | E3: 0 | F3: 0 | G3: 0 | H3: 0 | I3: 0 | J3: 0 | K3: 0 | L3: 0 | M3: =C3+D3+E3+F3+G3+H3+I3+J3+L3+K3 -> 0 | N3: =L3-O3 -> 0 | O3: =M3-B3-F3 -> 0 | P3: 0
A4: 44929 | B4: 319.6 | C4: 180.8 | D4: 9.6 | E4: 0 | F4: 0 | G4: 0 | H4: 37.8 | I4: 0 | J4: 0 | K4: 0 | L4: 90 | M4: =C4+D4+E4+F4+G4+H4+I4+J4+L4+K4 -> 318.2 | N4: =L4-O4 -> 91.4 | O4: =M4-B4-F4 -> -1.4 | P4: 66.58
A5: 44930 | B5: 257.22 | C5: 193.86 | D5: 2 | E5: 0 | F5: 0 | G5: 0 | H5: 0 | I5: 0 | J5: 0 | K5: 0 | L5: 60 | M5: =C5+D5+E5+F5+G5+H5+I5+J5+L5+K5 -> 255.86 | N5: =L5-O5 -> 61.36 | O5: =M5-B5-F5 -> -1.36 | P5: 67.5
A6: 44931 | B6: 255.1 | C6: 176.2 | D6: 15.9 | E6: 0 | F6: 0 | G6: 0 | H6: 0 | I6: 0 | J6: 0 | K6: 0 | L6: 65 | M6: =C6+D6+E6+F6+G6+H6+I6+J6+L6+K6 -> 257.1 | N6: =L6-O6 -> 63 | O6: =M6-B6-F6 -> 2 | P6: 64.5
A7: 44932 | B7: 239.65 | C7: 124.63 | D7: 40.42 | E7: 0 | F7: 0 | G7: 0 | H7: 0 | I7: 0 | J7: 0 | K7: 0 | L7: 75 | M7: =C7+D7+E7+F7+G7+H7+I7+J7+L7+K7 -> 240.05 | N7: =L7-O7 -> 74.6 | O7: =M7-B7-F7 -> 0.4 | P7: 77.96
A8: 44933 | B8: 171.4 | C8: 153 | D8: 9.4 | E8: 0 | F8: 0 | G8: 0 | H8: 0 | I8: 0 | J8: 0 | K8: 0 | L8: 10 | M8: =C8+D8+E8+F8+G8+H8+I8+J8+L8+K8 -> 172.4 | N8: =L8-O8 -> 9 | O8: =M8-B8-F8 -> 1 | P8: 74.98
A9: 44934 | B9: 193.24 | C9: 122.44 | D9: 8.6 | E9: 0 | F9: 0 | G9: 0 | H9: 0 | I9: 0 | J9: 0 | K9: 0 | L9: 65 | M9: =C9+D9+E9+F9+G9+H9+I9+J9+L9+K9 -> 196.04 | N9: =L9-O9 -> 62.2 | O9: =M9-B9-F9 -> 2.8 | P9: 72.38
A10: 44935 | B10: 0 | C10: 0 | D10: 0 | E10: 0 | F10: 0 | G10: 0 | H10: 0 | I10: 0 | J10: 0 | K10: 0 | L10: 0 | M10: =C10+D10+E10+F10+G10+H10+I10+J10+L10+K10 -> 0 | N10: =L10-O10 -> 0 | O10: =M10-B10-F10 -> 0 | P10: 0
A11: 44936 | B11: 208.47 | C11: 125.94 | D11: 21 | E11: 0 | F11: 0 | G11: 0 | H11: 18.9 | I11: 0 | J11: 0 | K11: 0 | L11: 45 | M11: =C11+D11+E11+F11+G11+H11+I11+J11+L11+K11 -> 210.84 | N11: =L11-O11 -> 42.63 | O11: =M11-B11-F11 -> 2.37 | P11: 70.01
A12: 44937 | B12: 266.16 | C12: 162.92 | D12: 15.84 | E12: 0 | F12: 0 | G12: 18.9 | H12: 0 | I12: 0 | J12: 0 | K12: 0 | L12: 70 | M12: =C12+D12+E12+F12+G12+H12+I12+J12+L12+K12 -> 267.66 | N12: =L12-O12 -> 68.5 | O12: =M12-B12-F12 -> 1.5 | P12: 0
A13: 44938 | B13: 194.96 | C13: 52.4 | D13: 11.1 | E13: 0 | F13: 0 | G13: 0 | H13: 18.9 | I13: 0 | J13: 0 | K13: 71.36 | L13: 45 | M13: =C13+D13+E13+F13+G13+H13+I13+J13+L13+K13 -> 198.76 | N13: =L13-O13 -> 41.2 | O13: =M13-B13-F13 -> 3.8 | P13: 64.8
A14: 44939 | B14: 337.74 | C14: 192 | D14: 60.84 | E14: 0 | F14: 0 | G14: 0 | H14: 0 | I14: 0 | J14: 0 | K14: 0 | L14: 90 | M14: =C14+D14+E14+F14+G14+H14+I14+J14+L14+K14 -> 342.84 | N14: =L14-O14 -> 84.9 | O14: =M14-B14-F14 -> 5.1 | P14: 0
... A32: 44957 | B32: 225.76 | C32: 132.7 | D32: 40.96 | E32: 0 | F32: 0 | G32: 0 | H32: 18.9 | I32: 0 | J32: 0 | K32: 0 | L32: 30 | M32: =C32+D32+E32+F32+G32+H32+I32+J32+L32+K32 -> 222.56 | N32: =L32-O32 -> 33.2 | O32: =M32-B32-F32 -> -3.2 | P32: 58.42
M33: =C33+D33+E33+F33+G33+H33+I33+J33+L33+K33 -> 0 | N33: =L33-O33 -> 0 | O33: =M33-B33-F33 -> 0 | P33: 0
A34: TOTAL | M34: =SUM(M2:M33) -> 8641.33 | N34: =M34-O34 -> 8585.95 | O34: =SUM(O2:O33) -> 55.38
K37: Kofi

Sheet Fev 23 
B1: FECHO DO DIA | C1: SALT PAY | D1: SANTANDER | E1: GASTOS C/RECIBO | F1: GASTOS S/RECIBO | G1: GLOVO | H1: UBER EATS | I1: VOLUP | J1: BOLT | K1: Transf. Bancária | L1: NUMERARIO | M1: TOTAL | N1: DEPOSITO | O1: EXTRA | P1: FUNDO CAIXA | R1: Num cert
A2: 44958 | B2: 234.18 | C2: 160.68 | D2: 15.2 | L2: 60 | M2: =C2+D2+E2+F2+G2+H2+I2+J2+L2+K2 -> 235.88 | N2: =L2-O2 -> 58.3 | O2: =M2-B2-F2 -> 1.7 | P2: 55.27
A3: 44959 | B3: 252.46 | C3: 123.76 | D3: 20.2 | H3: 37.8 | L3: 75 | M3: =C3+D3+E3+F3+G3+H3+I3+J3+L3+K3 -> 256.76 | N3: =L3-O3 -> 70.7 | O3: =M3-B3-F3 -> 4.3 | P3: 68.66
A4: 44960 | B4: 571.28 | C4: 387.92 | D4: 27.3 | H4: 49.8 | L4: 110 | M4: =C4+D4+E4+F4+G4+H4+I4+J4+L4+K4 -> 575.02 | N4: =L4-O4 -> 106.26 | O4: =M4-B4-F4 -> 3.74 | P4: 64.91
A5: 44961 | B5: 1348.43 | C5: 873.08 | D5: 181.24 | H5: 24.9 | L5: 270 | M5: =C5+D5+E5+F5+G5+H5+I5+J5+L5+K5 -> 1349.22 | N5: =L5-O5 -> 269.21 | O5: =M5-B5-F5 -> 0.79 | P5: 47.91
A6: 44962 | B6: 1031.77 | C6: 749.27 | D6: 83.4 | L6: 200 | M6: =C6+D6+E6+F6+G6+H6+I6+J6+L6+K6 -> 1032.67 | N6: =L6-O6 -> 199.1 | O6: =M6-B6-F6 -> 0.9
A7: 44963 | B7: 0 | C7: 0 | D7: 0 | L7: 0 | M7: =C7+D7+E7+F7+G7+H7+I7+J7+L7+K7 -> 0 | N7: =L7-O7 -> 0 | O7: =M7-B7-F7 -> 0
A8: 44964 | B8: 220.66 | C8: 140.16 | D8: 38 | L8: 40 | M8: =C8+D8+E8+F8+G8+H8+I8+J8+L8+K8 -> 218.16 | N8: =L8-O8 -> 42.5 | O8: =M8-B8-F8 -> -2.5
A9: 44965 | B9: 206.06 | C9: 154.46 | D9: 20.8 | L9: 30 | M9: =C9+D9+E9+F9+G9+H9+I9+J9+L9+K9 -> 205.26 | N9: =L9-O9 -> 30.8 | O9: =M9-B9-F9 -> -0.8
A10: 44966 | B10: 439.2 | C10: 185.7 | D10: 22.8 | K10: 112.42 | L10: 120 | M10: =C10+D10+E10+F10+G10+H10+I10+J10+L10+K10 -> 440.92 | N10: =L10-O10 -> 118.28 | O10: =M10-B10-F10 -> 1.72 | P10: 77.96
A11: 44967 | B11: 460.83 | C11: 344.5 | D11: 53.33 | L11: 60 | M11: =C11+D11+E11+F11+G11+H11+I11+J11+L11+K11 -> 457.83 | N11: =L11-O11 -> 63 | O11: =M11-B11-F11 -> -3 | P11: 62.06
A12: 44968 | B12: 1170.64 | C12: 758.24 | D12: 95.48 | H12: 49.8 | L12: 320 | M12: =C12+D12+E12+F12+G12+H12+I12+J12+L12+K12 -> 1223.52 | N12: =L12-O12 -> 267.12 | O12: =M12-B12-F12 -> 52.88 | P12: 78.56
A13: 44969 | B13: 866.92 | C13: 663.04 | D13: 53.2 | L13: 150 | M13: =C13+D13+E13+F13+G13+H13+I13+J13+L13+K13 -> 866.24 | N13: =L13-O13 -> 150.68 | O13: =M13-B13-F13 -> -0.68 | P13: 74.44
A14: 44970 | M14: =C14+D14+E14+F14+G14+H14+I14+J14+L14+K14 -> 0 | N14: =L14-O14 -> 0 | O14: =M14-B14-F14 -> 0
A15: 44971 | B15: 572.42 | C15: 365.14 | D15: 31.6 | L15: 185 | M15: =C15+D15+E15+F15+G15+H15+I15+J15+L15+K15 -> 581.74 | N15: =L15-O15 -> 175.68 | O15: =M15-B15-F15 -> 9.32 | P15: 71.36
A16: 44972 | B16: 294.4 | C16: 146.5 | D16: 19 | H16: 56.7 | L16: 80 | M16: =C16+D16+E16+F16+G16+H16+I16+J16+L16+K16 -> 302.2 | N16: =L16-O16 -> 72.2 | O16: =M16-B16-F16 -> 7.8 | P16: 62.16
A17: 44973 | B17: 343.3 | C17: 196.2 | D17: 92.4 | L17: 50 | M17: =C17+D17+E17+F17+G17+H17+I17+J17+L17+K17 -> 338.6 | N17: =L17-O17 -> 54.7 | O17: =M17-B17-F17 -> -4.7 | P17: 68.93
A18: 44974 | B18: 579.2 | C18: 365.1 | D18: 16.1 | H18: 18.9 | L18: 190 | M18: =C18+D18+E18+F18+G18+H18+I18+J18+L18+K18 -> 590.1 | N18: =L18-O18 -> 179.1 | O18: =M18-B18-F18 -> 10.9 | P18: 69.03
A19: 44975 | B19: 1002.04 | C19: 699.54 | D19: =17.2+7.2 -> 24.4 | L19: 280 | M19: =C19+D19+E19+F19+G19+H19+I19+J19+L19+K19 -> 1003.94 | N19: =L19-O19 -> 278.1 | O19: =M19-B19-F19 -> 1.9
A20: 44976 | B20: 879.3 | C20: 555.42 | D20: 89.08 | H20: 18.9 | L20: 215 | M20: =C20+D20+E20+F20+G20+H20+I20+J20+L20+K20 -> 878.4 | N20: =L20-O20 -> 215.9 | O20: =M20-B20-F20 -> -0.9 | P20: 62.25
A21: 44977 | M21: =C21+D21+E21+F21+G21+H21+I21+J21+L21+K21 -> 0 | N21: =L21-O21 -> 0 | O21: =M21-B21-F21 -> 0
A22: 44978 | B22: 640.68 | C22: 362.08 | D22: 26.5 | H22: 36.9 | L22: 210 | M22: =C22+D22+E22+F22+G22+H22+I22+J22+L22+K22 -> 635.48 | N22: =L22-O22 -> 215.2 | O22: =M22-B22-F22 -> -5.2 | P22: 67.35
A23: 44979 | B23: 327.1 | C23: 182.9 | D23: 34.1 | L23: 110 | M23: =C23+D23+E23+F23+G23+H23+I23+J23+L23+K23 -> 327 | N23: =L23-O23 -> 110.1 | O23: =M23-B23-F23 -> -0.1 | P23: 73.74
A24: 44980 | B24: 744.4 | C24: 96 | D24: 33.9 | K24: 585 | L24: 30 | M24: =C24+D24+E24+F24+G24+H24+I24+J24+L24+K24 -> 744.9 | N24: =L24-O24 -> 29.5 | O24: =M24-B24-F24 -> 0.5 | P24: 72.75
A25: 44981 | B25: 416.56 | C25: 209.76 | D25: 50.8 | H25: 37.8 | L25: 130 | M25: =C25+D25+E25+F25+G25+H25+I25+J25+L25+K25 -> 428.36 | N25: =L25-O25 -> 118.2 | O25: =M25-B25-F25 -> 11.8 | P25: 74.95
A26: 44982 | B26: 566.54 | C26: 362.36 | D26: 14.8 | H26: 18.9 | K26: 59 | L26: 120 | M26: =C26+D26+E26+F26+G26+H26+I26+J26+L26+K26 -> 575.06 | N26: =L26-O26 -> 111.48 | O26: =M26-B26-F26 -> 8.52
A27: 44983 | B27: 1136.1 | C27: 805.2 | D27: 81.3 | H27: 18.9 | L27: 230 | M27: =C27+D27+E27+F27+G27+H27+I27+J27+L27+K27 -> 1135.4 | N27: =L27-O27 -> 230.7 | O27: =M27-B27-F27 -> -0.7
A28: 44984 | M28: =C28+D28+E28+F28+G28+H28+I28+J28+L28+K28 -> 0 | N28: =L28-O28 -> 0 | O28: =M28-B28-F28 -> 0
A29: 44985 | B29: 223.3 | C29: 133.2 | D29: 7.6 | L29: 80 | M29: =C29+D29+E29+F29+G29+H29+I29+J29+L29+K29 -> 220.8 | N29: =L29-O29 -> 82.5 | O29: =M29-B29-F29 -> -2.5 | P29: 76.62
M30: =C30+D30+E30+F30+G30+H30+I30+J30+L30+K30 -> 0 | N30: =L30-O30 -> 0 | O30: =M30-B30-F30 -> 0
M31: =C31+D31+E31+F31+G31+H31+I31+J31+L31+K31 -> 0 | N31: =L31-O31 -> 0 | O31: =M31-B31-F31 -> 0
M32: =C32+D32+E32+F32+G32+H32+I32+J32+L32+K32 -> 0 | N32: =L32-O32 -> 0 | O32: =M32-B32-F32 -> 0
M33: =C33+D33+E33+F33+G33+H33+I33+J33+L33+K33 -> 0 | N33: =L33-O33 -> 0 | O33: =M33-B33-F33 -> 0
A34: TOTAL | M34: =SUM(M2:M33) -> 14623.46 | N34: =M34-O34 -> 14527.77 | O34: =SUM(O2:O33) -> 95.69
K37: kofi
K38: cofco
K39: semea

Sheet Mar 23
B1: FECHO DO DIA | C1: SALT PAY | D1: SANTANDER | E1: GASTOS C/RECIBO | F1: GASTOS S/RECIBO | G1: GLOVO | H1: UBER EATS | I1: VOLUP | J1: BOLT | K1: Transf. Bancária | L1: NUMERARIO | M1: TOTAL | N1: DEPOSITO | O1: EXTRA | P1: FUNDO CAIXA | R1: Num cert
A2: 44986 | B2: 220.4 | C2: 148.7 | D2: 17.4 | L2: 60 | M2: =C2+D2+E2+F2+G2+H2+I2+J2+L2+K2 -> 226.1 | N2: =L2-O2 -> 54.3 | O2: =M2-B2-F2 -> 5.7 | P2: 68.03
A3: 44987 | B3: 344.56 | C3: 230.36 | D3: 36.1 | H3: 56.7 | L3: 20 | M3: =C3+D3+E3+F3+G3+H3+I3+J3+L3+K3 -> 343.16 | N3: =L3-O3 -> 21.4 | O3: =M3-B3-F3 -> -1.4 | P3: 71.43
A4: 44988 | B4: 447.32 | C4: 254.18 | D4: 40.64 | H4: 63.8 | L4: 90 | M4: =C4+D4+E4+F4+G4+H4+I4+J4+L4+K4 -> 448.62 | N4: =L4-O4 -> 88.7 | O4: =M4-B4-F4 -> 1.3 | P4: 77.89
A5: 44989 | B5: 1253.03 | C5: 736.11 | D5: 88 | H5: 18.9 | L5: 410 | M5: =C5+D5+E5+F5+G5+H5+I5+J5+L5+K5 -> 1253.01 | N5: =L5-O5 -> 410.02 | O5: =M5-B5-F5 -> -0.02
A6: 44990 | B6: 257.68 | C6: 173.34 | D6: 18.2 | L6: 70 | M6: =C6+D6+E6+F6+G6+H6+I6+J6+L6+K6 -> 261.54 | N6: =L6-O6 -> 66.14 | O6: =M6-B6-F6 -> 3.86 | P6: 70.25
A7: 44991 | B7: 0 | M7: =C7+D7+E7+F7+G7+H7+I7+J7+L7+K7 -> 0 | N7: =L7-O7 -> 0 | O7: =M7-B7-F7 -> 0
A8: 44992 | B8: 208.2 | C8: 106 | D8: 7.6 | L8: 90 | M8: =C8+D8+E8+F8+G8+H8+I8+J8+L8+K8 -> 203.6 | N8: =L8-O8 -> 94.6 | O8: =M8-B8-F8 -> -4.6 | P8: 74.24
A9: 44993 | B9: 438.36 | C9: 53.36 | D9: 12 | H9: 18.9 | K9: =#REF!+#REF! -> #REF! | L9: 20 | M9: =C9+D9+E9+F9+G9+H9+I9+J9+L9+K9 -> #REF! | N9: =L9-O9 -> #REF! | O9: =M9-B9-F9 -> #REF!
A10: 44994 | B10: 167.34 | C10: 137.84 | D10: 9.6 | L10: 25 | M10: =C10+D10+E10+F10+G10+H10+I10+J10+L10+K10 -> 172.44 | N10: =L10-O10 -> 19.9 | O10: =M10-B10-F10 -> 5.1
A11: 44995 | B11: 168.22 | C11: 141.42 | D11: 0 | L11: 25 | M11: =C11+D11+E11+F11+G11+H11+I11+J11+L11+K11 -> 166.42 | N11: =L11-O11 -> 26.8 | O11: =M11-B11-F11 -> -1.8
A12: 44996 | B12: 954.81 | C12: 615.5 | D12: 91.8 | H12: 18.9 | L12: 230 | M12: =C12+D12+E12+F12+G12+H12+I12+J12+L12+K12 -> 956.2 | N12: =L12-O12 -> 228.61 | O12: =M12-B12-F12 -> 1.39
A13: 44997 | B13: 1308.24 | C13: 858.34 | D13: 44.4 | L13: 410 | M13: =C13+D13+E13+F13+G13+H13+I13+J13+L13+K13 -> 1312.74 | N13: =L13-O13 -> 405.5 | O13: =M13-B13-F13 -> 4.5 | P13: 74.28
A14: 44998 | B14: 0 | M14: =C14+D14+E14+F14+G14+H14+I14+J14+L14+K14 -> 0 | N14: =L14-O14 -> 0 | O14: =M14-B14-F14 -> 0
A15: 44999 | B15: 267.5 | C15: 175.2 | D15: 19.1 | L15: 75 | M15: =C15+D15+E15+F15+G15+H15+I15+J15+L15+K15 -> 269.3 | N15: =L15-O15 -> 73.2 | O15: =M15-B15-F15 -> 1.8
A16: 45000 | B16: 370.38 | C16: 252.76 | D16: 27 | L16: 90 | M16: =C16+D16+E16+F16+G16+H16+I16+J16+L16+K16 -> 369.76 | N16: =L16-O16 -> 90.62 | O16: =M16-B16-F16 -> -0.62 | P16: 76.4
A17: 45001 | B17: 168.04 | C17: 118.44 | D17: 0 | L17: 40 | M17: =C17+D17+E17+F17+G17+H17+I17+J17+L17+K17 -> 158.44 | N17: =L17-O17 -> 49.6 | O17: =M17-B17-F17 -> -9.6
A18: 45002 | B18: 404.99 | C18: 179.82 | D18: 12.4 | G18: 11 | H18: 18.9 | K18: =#REF! -> #REF! | L18: 100 | M18: =C18+D18+E18+F18+G18+H18+I18+J18+L18+K18 -> #REF! | N18: =L18-O18 -> #REF! | O18: =M18-B18-F18 -> #REF!
A19: 45003 | B19: 1227.61 | C19: 631.47 | D19: 166.32 | K19: =#REF! -> #REF! | L19: 225 | M19: =C19+D19+E19+F19+G19+H19+I19+J19+L19+K19 -> #REF! | N19: =L19-O19 -> #REF! | O19: =M19-B19-F19 -> #REF!
A20: 45004 | B20: 1519.93 | C20: 995.86 | D20: 145.34 | H20: 70.7 | L20: 310 | M20: =C20+D20+E20+F20+G20+H20+I20+J20+L20+K20 -> 1521.9 | N20: =L20-O20 -> 308.03 | O20: =M20-B20-F20 -> 1.97
A21: 45005 | B21: 0 | M21: =C21+D21+E21+F21+G21+H21+I21+J21+L21+K21 -> 0 | N21: =L21-O21 -> 0 | O21: =M21-B21-F21 -> 0
A22: 45006 | B22: 366.32 | C22: 211.8 | D22: 33.7 | L22: 120 | M22: =C22+D22+E22+F22+G22+H22+I22+J22+L22+K22 -> 365.5 | N22: =L22-O22 -> 120.82 | O22: =M22-B22-F22 -> -0.82
A23: 45007 | B23: 280.84 | C23: 100.82 | D23: 30.6 | L23: 150 | M23: =C23+D23+E23+F23+G23+H23+I23+J23+L23+K23 -> 281.42 | N23: =L23-O23 -> 149.42 | O23: =M23-B23-F23 -> 0.58 | P23: 76.48
A24: 45008 | B24: 90.6 | C24: 45 | D24: 0 | H24: 18.9 | L24: 30 | M24: =C24+D24+E24+F24+G24+H24+I24+J24+L24+K24 -> 93.9 | N24: =L24-O24 -> 26.7 | O24: =M24-B24-F24 -> 3.3 | P24: 72.88
A25: 45009 | B25: 730.16 | C25: 460.4 | D25: 37.5 | H25: 18.9 | L25: 215 | M25: =C25+D25+E25+F25+G25+H25+I25+J25+L25+K25 -> 731.8 | N25: =L25-O25 -> 213.36 | O25: =M25-B25-F25 -> 1.64
A26: 45010 | B26: 739.82 | C26: 468.94 | D26: 81.5 | L26: 195 | M26: =C26+D26+E26+F26+G26+H26+I26+J26+L26+K26 -> 745.44 | N26: =L26-O26 -> 189.38 | O26: =M26-B26-F26 -> 5.62 | P26: 65.79
A27: 45011 | B27: 1666.88 | C27: 1139.98 | D27: 133.8 | H27: 20.9 | L27: 360 | M27: =C27+D27+E27+F27+G27+H27+I27+J27+L27+K27 -> 1654.68 | N27: =L27-O27 -> 372.2 | O27: =M27-B27-F27 -> -12.2 | P27: 78.14
A28: 45012 | B28: 0 | M28: =C28+D28+E28+F28+G28+H28+I28+J28+L28+K28 -> 0 | N28: =L28-O28 -> 0 | O28: =M28-B28-F28 -> 0
A29: 45013 | B29: 511.7 | C29: 354.6 | D29: 39.9 | L29: 120 | M29: =C29+D29+E29+F29+G29+H29+I29+J29+L29+K29 -> 514.5 | N29: =L29-O29 -> 117.2 | O29: =M29-B29-F29 -> 2.8 | P29: 75.84
A30: 45014 | B30: 385.1 | C30: 105.2 | D30: 4.8 | G30: 18.9 | K30: 142.4 | L30: 115 | M30: =C30+D30+E30+F30+G30+H30+I30+J30+L30+K30 -> 386.3 | N30: =L30-O30 -> 113.8 | O30: =M30-B30-F30 -> 1.2 | P30: 75.91
A31: 45015 | B31: 249 | C31: 155.5 | D31: 12.4 | H31: 18.9 | L31: 65 | M31: =C31+D31+E31+F31+G31+H31+I31+J31+L31+K31 -> 251.8 | N31: =L31-O31 -> 62.2 | O31: =M31-B31-F31 -> 2.8
A32: 45016 | B32: 688.39 | C32: 432.19 | D32: 74.3 | H32: 36.9 | L32: 150 | M32: =C32+D32+E32+F32+G32+H32+I32+J32+L32+K32 -> 693.39 | N32: =L32-O32 -> 145 | O32: =M32-B32-F32 -> 5
M33: =C33+D33+E33+F33+G33+H33+I33+J33+L33+K33 -> 0 | N33: =L33-O33 -> 0 | O33: =M33-B33-F33 -> 0
A34: TOTAL | M34: =SUM(M2:M33) -> #REF! | N34: =M34-O34 -> #REF! | O34: =SUM(O2:O33) -> #REF!

Sheet Abril 23
B1: FECHO DO DIA | C1: SALT PAY | D1: SANTANDER | E1: GASTOS C/RECIBO | F1: GASTOS S/RECIBO | G1: GLOVO | H1: UBER EATS | I1: VOLUP | J1: BOLT | K1: Transf. Bancária | L1: NUMERARIO | M1: TOTAL | N1: DEPOSITO | O1: EXTRA | P1: FUNDO CAIXA | R1: Num cert
A2: 45017 | B2: 688.39 | C2: 432.19 | D2: 74.3 | H2: 36.9 | L2: 150 | M2: =C2+D2+E2+F2+G2+H2+I2+J2+L2+K2 -> 693.39 | N2: =L2-O2 -> 145 | O2: =M2-B2-F2 -> 5
A3: 45018 | B3: 1748.08 | C3: 1000.5 | D3: 140.68 | H3: 18.9 | L3: 600 | M3: =C3+D3+E3+F3+G3+H3+I3+J3+L3+K3 -> 1760.08 | N3: =L3-O3 -> 588 | O3: =M3-B3-F3 -> 12 | P3: 74.51
A4: 45019 | B4: 0 | M4: =C4+D4+E4+F4+G4+H4+I4+J4+L4+K4 -> 0 | N4: =L4-O4 -> 0 | O4: =M4-B4-F4 -> 0
A5: 45020 | B5: 943.18 | C5: 545.78 | D5: 124.5 | H5: 32.9 | L5: 240 | M5: =C5+D5+E5+F5+G5+H5+I5+J5+L5+K5 -> 943.18 | N5: =L5-O5 -> 240 | O5: =M5-B5-F5 -> 0 | P5: 74.31
A6: 45021 | B6: 907 | C6: 409.7 | D6: 59.3 | H6: 20 | L6: 430 | M6: =C6+D6+E6+F6+G6+H6+I6+J6+L6+K6 -> 919 | N6: =L6-O6 -> 418 | O6: =M6-B6-F6 -> 12 | P6: 74.38
A7: 45022 | B7: 1430.3 | C7: 792.84 | D7: 120.6 | K7: 87.76 | L7: 435 | M7: =C7+D7+E7+F7+G7+H7+I7+J7+L7+K7 -> 1436.2 | N7: =L7-O7 -> 429.1 | O7: =M7-B7-F7 -> 5.9 | P7: 73.84
A8: 45023 | B8: 1572.58 | C8: 1057.28 | D8: 66.6 | H8: 18.9 | L8: 440 | M8: =C8+D8+E8+F8+G8+H8+I8+J8+L8+K8 -> 1582.78 | N8: =L8-O8 -> 429.8 | O8: =M8-B8-F8 -> 10.2 | P8: 72.27
A9: 45024 | B9: 1595.56 | C9: 1106.56 | D9: 130.3 | L9: 360 | M9: =C9+D9+E9+F9+G9+H9+I9+J9+L9+K9 -> 1596.86 | N9: =L9-O9 -> 358.7 | O9: =M9-B9-F9 -> 1.3 | P9: 70.44
A10: 45025 | B10: 723.54 | C10: 531.68 | D10: 68.56 | L10: 120 | M10: =C10+D10+E10+F10+G10+H10+I10+J10+L10+K10 -> 720.24 | N10: =L10-O10 -> 123.3 | O10: =M10-B10-F10 -> -3.3 | P10: 73.8
A11: 45026 | B11: 0 | M11: =C11+D11+E11+F11+G11+H11+I11+J11+L11+K11 -> 0 | N11: =L11-O11 -> 0 | O11: =M11-B11-F11 -> 0
A12: 45027 | B12: 524.3 | C12: 265.6 | D12: 31.6 | H12: 18.9 | L12: 215 | M12: =C12+D12+E12+F12+G12+H12+I12+J12+L12+K12 -> 531.1 | N12: =L12-O12 -> 208.2 | O12: =M12-B12-F12 -> 6.8 | P12: 75.32
A13: 45028 | B13: 373.46 | C13: 158.48 | D13: 43.4 | H13: 20 | L13: 160 | M13: =C13+D13+E13+F13+G13+H13+I13+J13+L13+K13 -> 381.88 | N13: =L13-O13 -> 151.58 | O13: =M13-B13-F13 -> 8.42 | P13: 66.3
A14: 45029 | B14: 439.2 | C14: 173.7 | D14: 4.8 | H14: 32.9 | L14: 220 | M14: =C14+D14+E14+F14+G14+H14+I14+J14+L14+K14 -> 431.4 | N14: =L14-O14 -> 227.8 | O14: =M14-B14-F14 -> -7.8 | P14: 73.99
A15: 45030 | B15: 345.99 | C15: 136.7 | D15: 0 | K15: =115.04+14.75 -> 129.79 | L15: 80 | M15: =C15+D15+E15+F15+G15+H15+I15+J15+L15+K15 -> 346.49 | N15: =L15-O15 -> 79.5 | O15: =M15-B15-F15 -> 0.5 | P15: 73.26
A16: 45031 | B16: 1607.4 | C16: 1118.18 | D16: 131.42 | H16: 33.9 | L16: 310 | M16: =C16+D16+E16+F16+G16+H16+I16+J16+L16+K16 -> 1593.5 | N16: =L16-O16 -> 323.9 | O16: =M16-B16-F16 -> -13.9
A17: 45032 | B17: 2238.97 | C17: 1385.37 | D17: 281.28 | H17: 18.9 | L17: 560 | M17: =C17+D17+E17+F17+G17+H17+I17+J17+L17+K17 -> 2245.55 | N17: =L17-O17 -> 553.42 | O17: =M17-B17-F17 -> 6.58 | P17: 72.05
A18: 45033 | B18: 0 | M18: =C18+D18+E18+F18+G18+H18+I18+J18+L18+K18 -> 0 | N18: =L18-O18 -> 0 | O18: =M18-B18-F18 -> 0
A19: 45034 | B19: 610.84 | C19: 432.74 | D19: 23.8 | L19: 140 | M19: =C19+D19+E19+F19+G19+H19+I19+J19+L19+K19 -> 596.54 | N19: =L19-O19 -> 154.3 | O19: =M19-B19-F19 -> -14.3 | P19: 73
A20: 45035 | B20: 595.4 | C20: 273.3 | D20: 26.8 | H20: 79.7 | L20: 215 | M20: =C20+D20+E20+F20+G20+H20+I20+J20+L20+K20 -> 594.8 | N20: =L20-O20 -> 215.6 | O20: =M20-B20-F20 -> -0.6
A21: 45036 | B21: 572.95 | C21: 348.25 | D21: 55.3 | L21: 170 | M21: =C21+D21+E21+F21+G21+H21+I21+J21+L21+K21 -> 573.55 | N21: =L21-O21 -> 169.4 | O21: =M21-B21-F21 -> 0.6
A22: 45037 | B22: 440 | C22: 210.4 | D22: 39.1 | H22: 18.9 | K22: 53.38 | L22: 120 | M22: =C22+D22+E22+F22+G22+H22+I22+J22+L22+K22 -> 441.78 | N22: =L22-O22 -> 118.22 | O22: =M22-B22-F22 -> 1.78
A23: 45038 | B23: 1219.06 | C23: 951.76 | D23: 57.6 | L23: 210 | M23: =C23+D23+E23+F23+G23+H23+I23+J23+L23+K23 -> 1219.36 | N23: =L23-O23 -> 209.7 | O23: =M23-B23-F23 -> 0.3
A24: 45039 | B24: 772.18 | C24: 597.48 | D24: 59.1 | L24: 120 | M24: =C24+D24+E24+F24+G24+H24+I24+J24+L24+K24 -> 776.58 | N24: =L24-O24 -> 115.6 | O24: =M24-B24-F24 -> 4.4 | P24: 69.19
A25: 45040 | B25: 0 | M25: =C25+D25+E25+F25+G25+H25+I25+J25+L25+K25 -> 0 | N25: =L25-O25 -> 0 | O25: =M25-B25-F25 -> 0
A26: 45041 | B26: 1681.46 | C26: 1093.26 | D26: 136.7 | G26: 20.9 | H26: 40.9 | L26: 390 | M26: =C26+D26+E26+F26+G26+H26+I26+J26+L26+K26 -> 1681.76 | N26: =L26-O26 -> 389.7 | O26: =M26-B26-F26 -> 0.3
A27: 45042 | B27: 394.07 | C27: 203.82 | D27: 28.6 | H27: 19.9 | L27: 140 | M27: =C27+D27+E27+F27+G27+H27+I27+J27+L27+K27 -> 392.32 | N27: =L27-O27 -> 141.75 | O27: =M27-B27-F27 -> -1.75
A28: 45043 | B28: 424.9 | C28: 232.3 | D28: 5.3 | L28: 190 | M28: =C28+D28+E28+F28+G28+H28+I28+J28+L28+K28 -> 427.6 | N28: =L28-O28 -> 187.3 | O28: =M28-B28-F28 -> 2.7
A29: 45044 | B29: 767.04 | C29: 360.35 | D29: 26.6 | H29: 89.8 | K29: =115.54+14.75 -> 130.29 | L29: 160 | M29: =C29+D29+E29+F29+G29+H29+I29+J29+L29+K29 -> 767.04 | N29: =L29-O29 -> 160 | O29: =M29-B29-F29 -> 0
A30: 45045 | B30: 1294.93 | C30: 906.93 | D30: 115.3 | L30: 280 | M30: =C30+D30+E30+F30+G30+H30+I30+J30+L30+K30 -> 1302.23 | N30: =L30-O30 -> 272.7 | O30: =M30-B30-F30 -> 7.3
A31: 45046 | B31: 1458.88 | C31: 1010.32 | D31: 36.3 | H31: 18.9 | L31: 400 | M31: =C31+D31+E31+F31+G31+H31+I31+J31+L31+K31 -> 1465.52 | N31: =L31-O31 -> 393.36 | O31: =M31-B31-F31 -> 6.64
M32: =C32+D32+E32+F32+G32+H32+I32+J32+L32+K32 -> 0 | N32: =L32-O32 -> 0 | O32: =M32-B32-F32 -> 0
M33: =C33+D33+E33+F33+G33+H33+I33+J33+L33+K33 -> 0 | N33: =L33-O33 -> 0 | O33: =M33-B33-F33 -> 0
A34: TOTAL | M34: =SUM(M2:M33) -> 25420.73 | N34: =M34-O34 -> 25369.66 | O34: =SUM(O2:O33) -> 51.07

Sheet Jan 24
B1: FECHO DO DIA | C1: SALT PAY | D1: SANTANDER | E1: GASTOS C/RECIBO | F1: GASTOS S/RECIBO | G1: GLOVO | H1: UBER EATS | I1: VOLUP | J1: BOLT | K1: Transf. Bancária | L1: NUMERARIO | M1: TOTAL | N1: DEPOSITO | O1: EXTRA | P1: FUNDO CAIXA | R1: Num cert
A2: 45292 | B2: 0 | C2: 0 | D2: 0 | L2: 0 | M2: =C2+D2+E2+F2+G2+H2+I2+J2+L2+K2 -> 0 | N2: =L2-O2 -> 0 | O2: =M2-B2-F2 -> 0
A3: 45293 | B3: 188.45 | C3: 69.96 | D3: 20.5 | H3: 18.9 | L3: 80 | M3: =C3+D3+E3+F3+G3+H3+I3+J3+L3+K3 -> 189.36 | N3: =L3-O3 -> 79.09 | O3: =M3-B3-F3 -> 0.91
A4: 45294 | B4: 154.4 | C4: 134.4 | D4: 0 | L4: 20 | M4: =C4+D4+E4+F4+G4+H4+I4+J4+L4+K4 -> 154.4 | N4: =L4-O4 -> 20 | O4: =M4-B4-F4 -> 0
A5: 45295 | B5: 128.4 | C5: 71.93 | D5: 16.5 | H5: 18.9 | L5: 20 | M5: =C5+D5+E5+F5+G5+H5+I5+J5+L5+K5 -> 127.33 | N5: =L5-O5 -> 21.07 | O5: =M5-B5-F5 -> -1.07
A6: 45296 | B6: 355.95 | C6: 235.85 | D6: 5.8 | H6: 66.7 | L6: 45 | M6: =C6+D6+E6+F6+G6+H6+I6+J6+L6+K6 -> 353.35 | N6: =L6-O6 -> 47.6 | O6: =M6-B6-F6 -> -2.6
A7: 45297 | B7: 907.84 | C7: 602.46 | D7: 68.9 | H7: 18.9 | L7: 215 | M7: =C7+D7+E7+F7+G7+H7+I7+J7+L7+K7 -> 905.26 | N7: =L7-O7 -> 217.58 | O7: =M7-B7-F7 -> -2.58
A8: 45298 | B8: 1111.92 | C8: 772.42 | D8: 95.5 | H8: 32.9 | L8: 210 | M8: =C8+D8+E8+F8+G8+H8+I8+J8+L8+K8 -> 1110.82 | N8: =L8-O8 -> 211.1 | O8: =M8-B8-F8 -> -1.1
A9: 45299 | B9: 61.48 | C9: 31.6 | D9: 29.88 | L9: 0 | M9: =C9+D9+E9+F9+G9+H9+I9+J9+L9+K9 -> 61.48 | N9: =L9-O9 -> -7.1054274e-15 | O9: =M9-B9-F9 -> 7.1054274e-15
A10: 45300 | B10: 91.2 | C10: 45.7 | D10: 14.4 | L10: 30 | M10: =C10+D10+E10+F10+G10+H10+I10+J10+L10+K10 -> 90.1 | N10: =L10-O10 -> 31.1 | O10: =M10-B10-F10 -> -1.1
A11: 45301 | B11: 254.13 | C11: 56.26 | D11: 12.39 | H11: 72.8 | K11: 85.18 | L11: 60 | M11: =C11+D11+E11+F11+G11+H11+I11+J11+L11+K11 -> 286.63 | N11: =L11-O11 -> 27.5 | O11: =M11-B11-F11 -> 32.5
A12: 45302 | B12: 241.64 | C12: 171.84 | D12: 0 | L12: 80 | M12: =C12+D12+E12+F12+G12+H12+I12+J12+L12+K12 -> 251.84 | N12: =L12-O12 -> 69.8 | O12: =M12-B12-F12 -> 10.2
A13: 45303 | B13: 524.2 | C13: 288.84 | D13: 103.46 | H13: 89.6 | L13: 50 | M13: =C13+D13+E13+F13+G13+H13+I13+J13+L13+K13 -> 531.9 | N13: =L13-O13 -> 42.3 | O13: =M13-B13-F13 -> 7.7
A14: 45304 | B14: 382.14 | C14: 272.58 | D14: 10 | H14: 38.8 | L14: 60 | M14: =C14+D14+E14+F14+G14+H14+I14+J14+L14+K14 -> 381.38 | N14: =L14-O14 -> 60.76 | O14: =M14-B14-F14 -> -0.76
A15: 45305 | B15: 484.1 | C15: 330.3 | D15: 19 | L15: 135 | M15: =C15+D15+E15+F15+G15+H15+I15+J15+L15+K15 -> 484.3 | N15: =L15-O15 -> 134.8 | O15: =M15-B15-F15 -> 0.2
A16: 45306 | B16: 29.4 | C16: 24.6 | D16: 0 | L16: 5 | M16: =C16+D16+E16+F16+G16+H16+I16+J16+L16+K16 -> 29.6 | N16: =L16-O16 -> 4.8 | O16: =M16-B16-F16 -> 0.2
A17: 45307 | B17: 139.2 | C17: 72.5 | D17: 0 | H17: 18.9 | L17: 50 | M17: =C17+D17+E17+F17+G17+H17+I17+J17+L17+K17 -> 141.4 | N17: =L17-O17 -> 47.8 | O17: =M17-B17-F17 -> 2.2
A18: 45308 | B18: 111.9 | C18: 95.2 | D18: 4.3 | L18: 15 | M18: =C18+D18+E18+F18+G18+H18+I18+J18+L18+K18 -> 114.5 | N18: =L18-O18 -> 12.4 | O18: =M18-B18-F18 -> 2.6
A19: 45309 | B19: 217.82 | C19: 123.52 | D19: 22.1 | L19: 75 | M19: =C19+D19+E19+F19+G19+H19+I19+J19+L19+K19 -> 220.62 | N19: =L19-O19 -> 72.2 | O19: =M19-B19-F19 -> 2.8
A20: 45310 | B20: 664.62 | C20: 393.82 | D20: 72.8 | H20: 90.5 | L20: 110 | M20: =C20+D20+E20+F20+G20+H20+I20+J20+L20+K20 -> 667.12 | N20: =L20-O20 -> 107.5 | O20: =M20-B20-F20 -> 2.5
A21: 45311 | B21: 1384.99 | C21: 947.97 | D21: 147.2 | H21: 77.7 | L21: 215 | M21: =C21+D21+E21+F21+G21+H21+I21+J21+L21+K21 -> 1387.87 | N21: =L21-O21 -> 212.12 | O21: =M21-B21-F21 -> 2.88
A22: 45312 | B22: 876.2 | C22: 571.96 | D22: 56 | H22: 37.8 | L22: 210 | M22: =C22+D22+E22+F22+G22+H22+I22+J22+L22+K22 -> 875.76 | N22: =L22-O22 -> 210.44 | O22: =M22-B22-F22 -> -0.44
A23: 45313 | B23: 148.83 | C23: 114.03 | D23: 11.4 | L23: 20 | M23: =C23+D23+E23+F23+G23+H23+I23+J23+L23+K23 -> 145.43 | N23: =L23-O23 -> 23.4 | O23: =M23-B23-F23 -> -3.4
A24: 45314 | B24: 411.73 | C24: 281.31 | D24: 24.6 | K24: 52.52 | L24: 55 | M24: =C24+D24+E24+F24+G24+H24+I24+J24+L24+K24 -> 413.43 | N24: =L24-O24 -> 53.3 | O24: =M24-B24-F24 -> 1.7
A25: 45315 | B25: 644.93 | C25: 366.2 | D25: 109.75 | K25: 81.78 | L25: 90 | M25: =C25+D25+E25+F25+G25+H25+I25+J25+L25+K25 -> 647.73 | N25: =L25-O25 -> 87.2 | O25: =M25-B25-F25 -> 2.8
A26: 45316 | B26: 407.14 | C26: 238.14 | D26: 19.8 | H26: 51.8 | L26: 100 | M26: =C26+D26+E26+F26+G26+H26+I26+J26+L26+K26 -> 409.74 | N26: =L26-O26 -> 97.4 | O26: =M26-B26-F26 -> 2.6
A27: 45317 | B27: 697.71 | C27: 483.31 | D27: 70.7 | H27: 58.8 | L27: 85 | M27: =C27+D27+E27+F27+G27+H27+I27+J27+L27+K27 -> 697.81 | N27: =L27-O27 -> 84.9 | O27: =M27-B27-F27 -> 0.1
A28: 45318 | B28: 1818.31 | C28: 1332.2 | D28: 197.5 | H28: 18.9 | L28: 275 | M28: =C28+D28+E28+F28+G28+H28+I28+J28+L28+K28 -> 1823.6 | N28: =L28-O28 -> 269.71 | O28: =M28-B28-F28 -> 5.29
A29: 45319 | B29: 1495.85 | C29: 1097.81 | D29: 188.34 | L29: 220 | M29: =C29+D29+E29+F29+G29+H29+I29+J29+L29+K29 -> 1506.15 | N29: =L29-O29 -> 209.7 | O29: =M29-B29-F29 -> 10.3
A30: 45320 | B30: 383.34 | C30: 251.04 | D30: 42.4 | H30: 18.9 | L30: 70 | M30: =C30+D30+E30+F30+G30+H30+I30+J30+L30+K30 -> 382.34 | N30: =L30-O30 -> 71 | O30: =M30-B30-F30 -> -1
A31: 45321 | B31: 461.21 | C31: 279.73 | D31: 67.07 | L31: 115 | M31: =C31+D31+E31+F31+G31+H31+I31+J31+L31+K31 -> 461.8 | N31: =L31-O31 -> 114.41 | O31: =M31-B31-F31 -> 0.59
A32: 45322 | B32: 493.35 | C32: 330.09 | D32: 81.76 | L32: 80 | M32: =C32+D32+E32+F32+G32+H32+I32+J32+L32+K32 -> 491.85 | N32: =L32-O32 -> 81.5 | O32: =M32-B32-F32 -> -1.5
A33: TOTAL | M33: =SUM(M2:M32) -> 15344.9 | N33: =M33-O33 -> 15272.38 | O33: =SUM(O2:O32) -> 72.52

Sheet Fev 24
B1: FECHO DO DIA | C1: SALT PAY | D1: SANTANDER | E1: GASTOS C/RECIBO | F1: GASTOS S/RECIBO | G1: GLOVO | H1: UBER EATS | I1: VOLUP | J1: BOLT | K1: Transf. Bancária | L1: NUMERARIO | M1: TOTAL | N1: DEPOSITO | O1: EXTRA | P1: FUNDO CAIXA | R1: Num cert
A2: 45323 | B2: 518.5 | C2: 355 | D2: 43 | H2: 32.9 | L2: 80 | M2: =C2+D2+E2+F2+G2+H2+I2+J2+L2+K2 -> 510.9 | N2: =L2-O2 -> 87.6 | O2: =M2-B2-F2 -> -7.6
A3: 45324 | B3: 807.46 | C3: 552.3 | D3: 83.56 | H3: 39.9 | L3: 135 | M3: =C3+D3+E3+F3+G3+H3+I3+J3+L3+K3 -> 810.76 | N3: =L3-O3 -> 131.7 | O3: =M3-B3-F3 -> 3.3
A4: 45325 | B4: 1953.12 | C4: 1385.93 | D4: 188.1 | H4: 56.7 | L4: 320 | M4: =C4+D4+E4+F4+G4+H4+I4+J4+L4+K4 -> 1950.73 | N4: =L4-O4 -> 322.39 | O4: =M4-B4-F4 -> -2.39
A5: 45326 | B5: 1558.32 | C5: 1112.52 | D5: 156.2 | L5: 290 | M5: =C5+D5+E5+F5+G5+H5+I5+J5+L5+K5 -> 1558.72 | N5: =L5-O5 -> 289.6 | O5: =M5-B5-F5 -> 0.4
A6: 45327 | B6: 221.28 | C6: 129.94 | D6: 23.54 | L6: 70 | M6: =C6+D6+E6+F6+G6+H6+I6+J6+L6+K6 -> 223.48 | N6: =L6-O6 -> 67.8 | O6: =M6-B6-F6 -> 2.2
A7: 45328 | B7: 339.86 | C7: 236.46 | D7: 24.6 | H7: 37.8 | L7: 40 | M7: =C7+D7+E7+F7+G7+H7+I7+J7+L7+K7 -> 338.86 | N7: =L7-O7 -> 41 | O7: =M7-B7-F7 -> -1
A8: 45329 | B8: 90.1 | C8: 77.8 | D8: 0 | L8: 25 | M8: =C8+D8+E8+F8+G8+H8+I8+J8+L8+K8 -> 102.8 | N8: =L8-O8 -> 12.3 | O8: =M8-B8-F8 -> 12.7
A9: 45330 | B9: 104.68 | C9: 12.2 | D9: 10.2 | K9: 72.17 | L9: 10 | M9: =C9+D9+E9+F9+G9+H9+I9+J9+L9+K9 -> 104.57 | N9: =L9-O9 -> 10.11 | O9: =M9-B9-F9 -> -0.11
A10: 45331 | B10: 246.3 | C10: 189.9 | D10: 17.6 | H10: 18.9 | L10: 20 | M10: =C10+D10+E10+F10+G10+H10+I10+J10+L10+K10 -> 246.4 | N10: =L10-O10 -> 19.9 | O10: =M10-B10-F10 -> 0.1
A11: 45332 | B11: 716.4 | C11: 507.75 | D11: 59.75 | H11: 51.8 | L11: 90 | M11: =C11+D11+E11+F11+G11+H11+I11+J11+L11+K11 -> 709.3 | N11: =L11-O11 -> 97.1 | O11: =M11-B11-F11 -> -7.1
A12: 45333 | B12: 536.52 | C12: 287.09 | D12: 60.44 | H12: 32.9 | L12: 160 | M12: =C12+D12+E12+F12+G12+H12+I12+J12+L12+K12 -> 540.43 | N12: =L12-O12 -> 156.09 | O12: =M12-B12-F12 -> 3.91
A13: 45334 | B13: 628.45 | C13: 355.25 | D13: 60.4 | H13: 32.9 | L13: 180 | M13: =C13+D13+E13+F13+G13+H13+I13+J13+L13+K13 -> 628.55 | N13: =L13-O13 -> 179.9 | O13: =M13-B13-F13 -> 0.1
A14: 45335 | B14: 773.27 | C14: 595.37 | D14: 53.2 | H14: 32.9 | L14: 100 | M14: =C14+D14+E14+F14+G14+H14+I14+J14+L14+K14 -> 781.47 | N14: =L14-O14 -> 91.8 | O14: =M14-B14-F14 -> 8.2
A15: 45336 | B15: 629.41 | C15: 348.53 | D15: 81.48 | L15: 190 | M15: =C15+D15+E15+F15+G15+H15+I15+J15+L15+K15 -> 620.01 | N15: =L15-O15 -> 199.4 | O15: =M15-B15-F15 -> -9.4
A16: 45337 | B16: 289.54 | C16: 86.6 | D16: 31 | K16: 71.1 | L16: 100 | M16: =C16+D16+E16+F16+G16+H16+I16+J16+L16+K16 -> 288.7 | N16: =L16-O16 -> 100.84 | O16: =M16-B16-F16 -> -0.84
A17: 45338 | B17: 713.01 | C17: 442.31 | D17: 80.1 | H17: 85.7 | L17: 105 | M17: =C17+D17+E17+F17+G17+H17+I17+J17+L17+K17 -> 713.11 | N17: =L17-O17 -> 104.9 | O17: =M17-B17-F17 -> 0.1
A18: 45339 | B18: 1779.86 | C18: 1168.2 | D18: 256.2 | L18: 355 | M18: =C18+D18+E18+F18+G18+H18+I18+J18+L18+K18 -> 1779.4 | N18: =L18-O18 -> 355.46 | O18: =M18-B18-F18 -> -0.46
A19: 45340 | B19: 1629.58 | C19: 1067.39 | D19: 143.5 | L19: 420 | M19: =C19+D19+E19+F19+G19+H19+I19+J19+L19+K19 -> 1630.89 | N19: =L19-O19 -> 418.69 | O19: =M19-B19-F19 -> 1.31
A20: 45341 | B20: 627.11 | C20: 422.32 | D20: 31.5 | K20: 57.39 | L20: 120 | M20: =C20+D20+E20+F20+G20+H20+I20+J20+L20+K20 -> 631.21 | N20: =L20-O20 -> 115.9 | O20: =M20-B20-F20 -> 4.1
A21: 45342 | B21: 403.1 | C21: 220.5 | D21: 61.4 | L21: 120 | M21: =C21+D21+E21+F21+G21+H21+I21+J21+L21+K21 -> 401.9 | N21: =L21-O21 -> 121.2 | O21: =M21-B21-F21 -> -1.2
A22: 45343 | B22: 283.03 | C22: 162.15 | D22: 39.28 | H22: 18.9 | L22: 65 | M22: =C22+D22+E22+F22+G22+H22+I22+J22+L22+K22 -> 285.33 | N22: =L22-O22 -> 62.7 | O22: =M22-B22-F22 -> 2.3
A23: 45344 | B23: 136.61 | C23: 89.81 | D23: 0 | L23: 40 | M23: =C23+D23+E23+F23+G23+H23+I23+J23+L23+K23 -> 129.81 | N23: =L23-O23 -> 46.8 | O23: =M23-B23-F23 -> -6.8
A24: 45345 | B24: 525.52 | C24: 254.78 | D24: 49.77 | H24: 73.7 | K24: 70.57 | L24: 70 | M24: =C24+D24+E24+F24+G24+H24+I24+J24+L24+K24 -> 518.82 | N24: =L24-O24 -> 76.7 | O24: =M24-B24-F24 -> -6.7
A25: 45346 | B25: 881.38 | C25: 549.93 | D25: 67.62 | K25: 134.97 | L25: 130 | M25: =C25+D25+E25+F25+G25+H25+I25+J25+L25+K25 -> 882.52 | N25: =L25-O25 -> 128.86 | O25: =M25-B25-F25 -> 1.14
A26: 45347 | B26: 426.8 | C26: 286.85 | D26: 23 | H26: 18.9 | L26: 100 | M26: =C26+D26+E26+F26+G26+H26+I26+J26+L26+K26 -> 428.75 | N26: =L26-O26 -> 98.05 | O26: =M26-B26-F26 -> 1.95
A27: 45348 | B27: 433.91 | C27: 249.51 | D27: 175.6 | L27: 10 | M27: =C27+D27+E27+F27+G27+H27+I27+J27+L27+K27 -> 435.11 | N27: =L27-O27 -> 8.8 | O27: =M27-B27-F27 -> 1.2
A28: 45349 | B28: 281.26 | C28: 169.66 | D28: 27.9 | L28: 80 | M28: =C28+D28+E28+F28+G28+H28+I28+J28+L28+K28 -> 277.56 | N28: =L28-O28 -> 83.7 | O28: =M28-B28-F28 -> -3.7
A29: 45350 | B29: 296.7 | C29: 243.5 | D29: 0 | L29: 50 | M29: =C29+D29+E29+F29+G29+H29+I29+J29+L29+K29 -> 293.5 | N29: =L29-O29 -> 53.2 | O29: =M29-B29-F29 -> -3.2
A30: 45351 | B30: 173.35 | C30: 128.4 | D30: 29.45 | L30: 25 | M30: =C30+D30+E30+F30+G30+H30+I30+J30+L30+K30 -> 182.85 | N30: =L30-O30 -> 15.5 | O30: =M30-B30-F30 -> 9.5
M31: =C31+D31+E31+F31+G31+H31+I31+J31+L31+K31 -> 0 | N31: =L31-O31 -> 0 | O31: =M31-B31-F31 -> 0
M32: =C32+D32+E32+F32+G32+H32+I32+J32+L32+K32 -> 0 | N32: =L32-O32 -> 0 | O32: =M32-B32-F32 -> 0
A33: TOTAL | M33: =SUM(M2:M32) -> 18006.44 | N33: =M33-O33 -> 18004.43 | O33: =SUM(O2:O32) -> 2.01

Sheet Mar 24
B1: FECHO DO DIA | C1: SALT PAY | D1: SANTANDER | E1: GASTOS C/RECIBO | F1: GASTOS S/RECIBO | G1: GLOVO | H1: UBER EATS | I1: VOLUP | J1: BOLT | K1: Transf. Bancária | L1: NUMERARIO | M1: TOTAL | N1: DEPOSITO | O1: EXTRA | P1: FUNDO CAIXA | R1: Num cert
A2: 45352 | B2: 348.31 | C2: 179.84 | D2: 76.34 | H2: 18.9 | K2: 59.73 | L2: 15 | M2: =C2+D2+E2+F2+G2+H2+I2+J2+L2+K2 -> 349.81 | N2: =L2-O2 -> 13.5 | O2: =M2-B2-F2 -> 1.5
A3: 45353 | B3: 465.93 | C3: 322.53 | D3: 20.8 | H3: 18.9 | L3: 105 | M3: =C3+D3+E3+F3+G3+H3+I3+J3+L3+K3 -> 467.23 | N3: =L3-O3 -> 103.7 | O3: =M3-B3-F3 -> 1.3
A4: 45354 | B4: 804.95 | C4: 549.65 | D4: 113.5 | H4: 37.8 | L4: 105 | M4: =C4+D4+E4+F4+G4+H4+I4+J4+L4+K4 -> 805.95 | N4: =L4-O4 -> 104 | O4: =M4-B4-F4 -> 1
A5: 45355 | B5: 242.6 | C5: 138.6 | D5: 10.5 | H5: 18.9 | L5: 70 | M5: =C5+D5+E5+F5+G5+H5+I5+J5+L5+K5 -> 238 | N5: =L5-O5 -> 74.6 | O5: =M5-B5-F5 -> -4.6
A6: 45356 | B6: 306 | C6: 227 | D6: 13.3 | L6: 75 | M6: =C6+D6+E6+F6+G6+H6+I6+J6+L6+K6 -> 315.3 | N6: =L6-O6 -> 65.7 | O6: =M6-B6-F6 -> 9.3
A7: 45357 | B7: 314.86 | C7: 140.2 | D7: 39.5 | H7: 32.9 | K7: 97.16 | L7: 10 | M7: =C7+D7+E7+F7+G7+H7+I7+J7+L7+K7 -> 319.76 | N7: =L7-O7 -> 5.1 | O7: =M7-B7-F7 -> 4.9
A8: 45358 | B8: 128.9 | C8: 87.9 | D8: 4.7 | L8: 35 | M8: =C8+D8+E8+F8+G8+H8+I8+J8+L8+K8 -> 127.6 | N8: =L8-O8 -> 36.3 | O8: =M8-B8-F8 -> -1.3
A9: 45359 | B9: 264.9 | C9: 147.1 | D9: 26.5 | H9: 58.8 | L9: 30 | M9: =C9+D9+E9+F9+G9+H9+I9+J9+L9+K9 -> 262.4 | N9: =L9-O9 -> 32.5 | O9: =M9-B9-F9 -> -2.5
A10: 45360 | B10: 692.87 | C10: 446.32 | D10: 113.84 | H10: 65.8 | L10: 70 | M10: =C10+D10+E10+F10+G10+H10+I10+J10+L10+K10 -> 695.96 | N10: =L10-O10 -> 66.91 | O10: =M10-B10-F10 -> 3.09
A11: 45361 | B11: 638.2 | C11: 423.5 | D11: 48 | H11: 51.8 | L11: 115 | M11: =C11+D11+E11+F11+G11+H11+I11+J11+L11+K11 -> 638.3 | N11: =L11-O11 -> 114.9 | O11: =M11-B11-F11 -> 0.1
A12: 45362 | B12: 346.89 | C12: 253.49 | D12: 23.8 | L12: 70 | M12: =C12+D12+E12+F12+G12+H12+I12+J12+L12+K12 -> 347.29 | N12: =L12-O12 -> 69.6 | O12: =M12-B12-F12 -> 0.4
A13: 45363 | B13: 395.96 | C13: 225.36 | D13: 20.5 | L13: 150 | M13: =C13+D13+E13+F13+G13+H13+I13+J13+L13+K13 -> 395.86 | N13: =L13-O13 -> 150.1 | O13: =M13-B13-F13 -> -0.1
A14: 45364 | B14: 493.46 | C14: 346.66 | D14: 64.3 | L14: 80 | M14: =C14+D14+E14+F14+G14+H14+I14+J14+L14+K14 -> 490.96 | N14: =L14-O14 -> 82.5 | O14: =M14-B14-F14 -> -2.5
A15: 45365 | B15: 125.5 | C15: 100 | D15: 0 | L15: 20 | M15: =C15+D15+E15+F15+G15+H15+I15+J15+L15+K15 -> 120 | N15: =L15-O15 -> 25.5 | O15: =M15-B15-F15 -> -5.5
A16: 45366 | B16: 767.23 | C16: 543.43 | D16: 70.2 | L16: 150 | M16: =C16+D16+E16+F16+G16+H16+I16+J16+L16+K16 -> 763.63 | N16: =L16-O16 -> 153.6 | O16: =M16-B16-F16 -> -3.6
A17: 45367 | B17: 1088.1 | C17: 742.5 | D17: 86 | H17: 37.8 | L17: 220 | M17: =C17+D17+E17+F17+G17+H17+I17+J17+L17+K17 -> 1086.3 | N17: =L17-O17 -> 221.8 | O17: =M17-B17-F17 -> -1.8
A18: 45368 | B18: 1556.21 | C18: 1018.19 | D18: 142.25 | H18: 32.9 | L18: 340 | M18: =C18+D18+E18+F18+G18+H18+I18+J18+L18+K18 -> 1533.34 | N18: =L18-O18 -> 362.87 | O18: =M18-B18-F18 -> -22.87
A19: 45369 | B19: 658.85 | C19: 439.25 | D19: 67 | H19: 32.9 | L19: 120 | M19: =C19+D19+E19+F19+G19+H19+I19+J19+L19+K19 -> 659.15 | N19: =L19-O19 -> 119.7 | O19: =M19-B19-F19 -> 0.3
A20: 45370 | B20: 677.94 | C20: 331.07 | D20: 161.24 | K20: 109.43 | L20: 70 | M20: =C20+D20+E20+F20+G20+H20+I20+J20+L20+K20 -> 671.74 | N20: =L20-O20 -> 76.2 | O20: =M20-B20-F20 -> -6.2
A21: 45371 | B21: 321.5 | C21: 171.4 | D21: 0 | H21: 39.9 | L21: 110 | M21: =C21+D21+E21+F21+G21+H21+I21+J21+L21+K21 -> 321.3 | N21: =L21-O21 -> 110.2 | O21: =M21-B21-F21 -> -0.2
A22: 45372 | B22: 828.17 | C22: 563.33 | D22: 48.9 | K22: 29.5 | L22: 185 | M22: =C22+D22+E22+F22+G22+H22+I22+J22+L22+K22 -> 826.73 | N22: =L22-O22 -> 186.44 | O22: =M22-B22-F22 -> -1.44
A23: 45373 | B23: 1559.87 | C23: 944.74 | D23: 265 | L23: 350 | M23: =C23+D23+E23+F23+G23+H23+I23+J23+L23+K23 -> 1559.74 | N23: =L23-O23 -> 350.13 | O23: =M23-B23-F23 -> -0.13
A24: 45374 | B24: 2732.73 | C24: 1940.96 | D24: 308.6 | H24: 32.9 | L24: 445 | M24: =C24+D24+E24+F24+G24+H24+I24+J24+L24+K24 -> 2727.46 | N24: =L24-O24 -> 450.27 | O24: =M24-B24-F24 -> -5.27
A25: 45375 | B25: 2438.67 | C25: 1745.31 | D25: 173.46 | L25: 510 | M25: =C25+D25+E25+F25+G25+H25+I25+J25+L25+K25 -> 2428.77 | N25: =L25-O25 -> 519.9 | O25: =M25-B25-F25 -> -9.9
A26: 45376 | B26: 228.1 | C26: 143.6 | D26: 36.5 | L26: 50 | M26: =C26+D26+E26+F26+G26+H26+I26+J26+L26+K26 -> 230.1 | N26: =L26-O26 -> 48 | O26: =M26-B26-F26 -> 2
A27: 45377 | B27: 181.75 | C27: 76.35 | D27: 39.83 | L27: 70 | M27: =C27+D27+E27+F27+G27+H27+I27+J27+L27+K27 -> 186.18 | N27: =L27-O27 -> 65.57 | O27: =M27-B27-F27 -> 4.43
A28: 45378 | B28: 359.73 | C28: 157.67 | D28: 42.3 | K28: 135.16 | L28: 25 | M28: =C28+D28+E28+F28+G28+H28+I28+J28+L28+K28 -> 360.13 | N28: =L28-O28 -> 24.6 | O28: =M28-B28-F28 -> 0.4
A29: 45379 | B29: 336.17 | C29: 125.3 | D29: 62.35 | H29: 18.9 | K29: 116.32 | L29: 15 | M29: =C29+D29+E29+F29+G29+H29+I29+J29+L29+K29 -> 337.87 | N29: =L29-O29 -> 13.3 | O29: =M29-B29-F29 -> 1.7
A30: 45380 | B30: 674.42 | C30: 471.84 | D30: 98.2 | G30: 18.9 | L30: 85 | M30: =C30+D30+E30+F30+G30+H30+I30+J30+L30+K30 -> 673.94 | N30: =L30-O30 -> 85.48 | O30: =M30-B30-F30 -> -0.48
A31: 45381 | B31: 516.17 | C31: 443.47 | D31: 13.3 | L31: 60 | M31: =C31+D31+E31+F31+G31+H31+I31+J31+L31+K31 -> 516.77 | N31: =L31-O31 -> 59.4 | O31: =M31-B31-F31 -> 0.6
A32: 45382 | B32: 340.92 | C32: 224.32 | D32: 0 | L32: 120 | M32: =C32+D32+E32+F32+G32+H32+I32+J32+L32+K32 -> 344.32 | N32: =L32-O32 -> 116.6 | O32: =M32-B32-F32 -> 3.4
A33: TOTAL | M33: =SUM(M2:M32) -> 20801.89 | N33: =M33-O33 -> 20835.86 | O33: =SUM(O2:O32) -> -33.97

Sheet Abr 24 
B1: FECHO DO DIA | C1: SALT PAY | D1: SANTANDER | E1: GASTOS C/RECIBO | F1: GASTOS S/RECIBO | G1: GLOVO | H1: UBER EATS | I1: VOLUP | J1: BOLT | K1: Transf. Bancária | L1: NUMERARIO | M1: TOTAL | N1: DEPOSITO | O1: EXTRA | P1: FUNDO CAIXA | R1: Num cert
A2: 45383 | B2: 400.4 | C2: 270 | D2: 56.7 | L2: 80 | M2: =C2+D2+E2+F2+G2+H2+I2+J2+L2+K2 -> 406.7 | N2: =L2-O2 -> 73.7 | O2: =M2-B2-F2 -> 6.3
A3: 45384 | B3: 37.9 | C3: 35.5 | D3: 0 | L3: 5 | M3: =C3+D3+E3+F3+G3+H3+I3+J3+L3+K3 -> 40.5 | N3: =L3-O3 -> 2.4 | O3: =M3-B3-F3 -> 2.6
A4: 45385 | B4: 395.17 | C4: 272.47 | D4: 22.9 | L4: 100 | M4: =C4+D4+E4+F4+G4+H4+I4+J4+L4+K4 -> 395.37 | N4: =L4-O4 -> 99.8 | O4: =M4-B4-F4 -> 0.2
A5: 45386 | B5: 458.49 | C5: 290.2 | D5: 16.8 | K5: 76.68 | L5: 80 | M5: =C5+D5+E5+F5+G5+H5+I5+J5+L5+K5 -> 463.68 | N5: =L5-O5 -> 74.81 | O5: =M5-B5-F5 -> 5.19
A6: 45387 | B6: 1404.2 | C6: 882.6 | D6: 188.9 | H6: 1 | L6: 340 | M6: =C6+D6+E6+F6+G6+H6+I6+J6+L6+K6 -> 1412.5 | N6: =L6-O6 -> 331.7 | O6: =M6-B6-F6 -> 8.3
A7: 45388 | B7: 1441.19 | C7: 978.63 | D7: 159.46 | L7: 300 | M7: =C7+D7+E7+F7+G7+H7+I7+J7+L7+K7 -> 1438.09 | N7: =L7-O7 -> 303.1 | O7: =M7-B7-F7 -> -3.1
A8: 45389 | B8: 1568 | C8: 881.09 | D8: 134.17 | H8: 37.8 | L8: 520 | M8: =C8+D8+E8+F8+G8+H8+I8+J8+L8+K8 -> 1573.06 | N8: =L8-O8 -> 514.94 | O8: =M8-B8-F8 -> 5.06
A9: 45390 | B9: 270.6 | C9: 143.4 | D9: 14.3 | H9: 58.8 | L9: 55 | M9: =C9+D9+E9+F9+G9+H9+I9+J9+L9+K9 -> 271.5 | N9: =L9-O9 -> 54.1 | O9: =M9-B9-F9 -> 0.9
A10: 45391 | B10: 480.61 | C10: 285.6 | D10: 49.7 | L10: 145 | M10: =C10+D10+E10+F10+G10+H10+I10+J10+L10+K10 -> 480.3 | N10: =L10-O10 -> 145.31 | O10: =M10-B10-F10 -> -0.31
A11: 45392 | B11: 555.64 | C11: 256.09 | D11: 75.15 | K11: =150.5 -> 150.5 | L11: 80 | M11: =C11+D11+E11+F11+G11+H11+I11+J11+L11+K11 -> 561.74 | N11: =L11-O11 -> 73.9 | O11: =M11-B11-F11 -> 6.1
A12: 45393 | B12: 865.25 | C12: 572.33 | D12: 78.52 | L12: 200 | M12: =C12+D12+E12+F12+G12+H12+I12+J12+L12+K12 -> 850.85 | N12: =L12-O12 -> 214.4 | O12: =M12-B12-F12 -> -14.4
A13: 45394 | B13: 1974.06 | C13: 1260.11 | D13: 236.24 | H13: 18.9 | L13: 450 | M13: =C13+D13+E13+F13+G13+H13+I13+J13+L13+K13 -> 1965.25 | N13: =L13-O13 -> 458.81 | O13: =M13-B13-F13 -> -8.81
A14: 45395 | B14: 2878.99 | C14: 1924.79 | D14: 287.1 | H14: 18.9 | K14: 61.95 | L14: 610 | M14: =C14+D14+E14+F14+G14+H14+I14+J14+L14+K14 -> 2902.74 | N14: =L14-O14 -> 586.25 | O14: =M14-B14-F14 -> 23.75
A15: 45396 | B15: 2431.14 | C15: 1541.74 | D15: 256.1 | L15: 600 | M15: =C15+D15+E15+F15+G15+H15+I15+J15+L15+K15 -> 2397.84 | N15: =L15-O15 -> 633.3 | O15: =M15-B15-F15 -> -33.3
A16: 45397 | B16: 706.2 | C16: 484.4 | D16: 55.8 | H16: 37.8 | L16: 130 | M16: =C16+D16+E16+F16+G16+H16+I16+J16+L16+K16 -> 708 | N16: =L16-O16 -> 128.2 | O16: =M16-B16-F16 -> 1.8
A17: 45398 | B17: 938.7 | C17: 604.8 | D17: 64.1 | H17: 18.9 | L17: 250 | M17: =C17+D17+E17+F17+G17+H17+I17+J17+L17+K17 -> 937.8 | N17: =L17-O17 -> 250.9 | O17: =M17-B17-F17 -> -0.9
A18: 45399 | B18: 1097.81 | C18: 672.99 | D18: 128.8 | K18: 101.2 | L18: 200 | M18: =C18+D18+E18+F18+G18+H18+I18+J18+L18+K18 -> 1102.99 | N18: =L18-O18 -> 194.82 | O18: =M18-B18-F18 -> 5.18
A19: 45400 | B19: 1002.08 | C19: 569.58 | D19: 60 | H19: 32.9 | L19: 335 | M19: =C19+D19+E19+F19+G19+H19+I19+J19+L19+K19 -> 997.48 | N19: =L19-O19 -> 339.6 | O19: =M19-B19-F19 -> -4.6
A20: 45401 | B20: 1176.57 | C20: 618.1 | D20: 159 | H20: 58.8 | K20: 79.56 | L20: 290 | M20: =C20+D20+E20+F20+G20+H20+I20+J20+L20+K20 -> 1205.46 | N20: =L20-O20 -> 261.11 | O20: =M20-B20-F20 -> 28.89
A21: 45402 | B21: 2483.95 | C21: 1533.87 | D21: 349.96 | G21: 18.9 | H21: 56.7 | L21: 525 | M21: =C21+D21+E21+F21+G21+H21+I21+J21+L21+K21 -> 2484.43 | N21: =L21-O21 -> 524.52 | O21: =M21-B21-F21 -> 0.48
A22: 45403 | B22: 2566.96 | C22: 1805.03 | D22: 148.57 | H22: 74.7 | K22: 59.26 | L22: 480 | M22: =C22+D22+E22+F22+G22+H22+I22+J22+L22+K22 -> 2567.56 | N22: =L22-O22 -> 479.4 | O22: =M22-B22-F22 -> 0.6
A23: 45404 | B23: 2084.2 | C23: 546.5 | D23: 38 | K23: =59.15+642.41+444.82+58.63 -> 1205.01 | L23: 300 | M23: =C23+D23+E23+F23+G23+H23+I23+J23+L23+K23 -> 2089.51 | N23: =L23-O23 -> 294.69 | O23: =M23-B23-F23 -> 5.31
A24: 45405 | B24: 551.9 | C24: 347.6 | D24: 47.1 | L24: 160 | M24: =C24+D24+E24+F24+G24+H24+I24+J24+L24+K24 -> 554.7 | N24: =L24-O24 -> 157.2 | O24: =M24-B24-F24 -> 2.8
A25: 45406 | B25: 878.13 | C25: 495.8 | D25: 92.2 | G25: 18.9 | K25: =57.15+25.33+74.15 -> 156.63 | L25: 115 | M25: =C25+D25+E25+F25+G25+H25+I25+J25+L25+K25 -> 878.53 | N25: =L25-O25 -> 114.6 | O25: =M25-B25-F25 -> 0.4
A26: 45407 | B26: 1601.47 | C26: 1019.1 | D26: 167.42 | G26: 36.9 | H26: 37.8 | L26: 320 | M26: =C26+D26+E26+F26+G26+H26+I26+J26+L26+K26 -> 1581.22 | N26: =L26-O26 -> 340.25 | O26: =M26-B26-F26 -> -20.25
A27: 45408 | B27: 505.4 | C27: 287.63 | D27: 63.81 | H27: 90.6 | L27: 60 | M27: =C27+D27+E27+F27+G27+H27+I27+J27+L27+K27 -> 502.04 | N27: =L27-O27 -> 63.36 | O27: =M27-B27-F27 -> -3.36
A28: 45409 | B28: 1438.54 | C28: 948.44 | D28: 113.44 | H28: 89.6 | L28: 290 | M28: =C28+D28+E28+F28+G28+H28+I28+J28+L28+K28 -> 1441.48 | N28: =L28-O28 -> 287.06 | O28: =M28-B28-F28 -> 2.94
A29: 45410 | B29: 1282.6 | C29: 947.53 | D29: 65.6 | H29: 18.9 | L29: 250 | M29: =C29+D29+E29+F29+G29+H29+I29+J29+L29+K29 -> 1282.03 | N29: =L29-O29 -> 250.57 | O29: =M29-B29-F29 -> -0.57
A30: 45411 | B30: 753.1 | C30: 418.18 | D30: 7.6 | K30: 219.52 | L30: 110 | M30: =C30+D30+E30+F30+G30+H30+I30+J30+L30+K30 -> 755.3 | N30: =L30-O30 -> 107.8 | O30: =M30-B30-F30 -> 2.2
A31: 45412 | B31: 299.47 | C31: 157.79 | D31: 9.1 | H31: 33.9 | L31: 100 | M31: =C31+D31+E31+F31+G31+H31+I31+J31+L31+K31 -> 300.79 | N31: =L31-O31 -> 98.68 | O31: =M31-B31-F31 -> 1.32
A32: TOTAL | M32: =SUM(M2:M31) -> 34549.44 | N32: =M32-O32 -> 34528.72 | O32: =SUM(O2:O31) -> 20.72

Sheet Mai 24
B1: FECHO DO DIA | C1: SALT PAY | D1: SANTANDER | E1: GASTOS C/RECIBO | F1: GASTOS S/RECIBO | G1: GLOVO | H1: UBER EATS | I1: VOLUP | J1: BOLT | K1: Transf. Bancária | L1: NUMERARIO | M1: TOTAL | N1: DEPOSITO | O1: EXTRA | P1: FUNDO CAIXA | R1: Num cert
A2: 45413 | B2: 1031.12 | C2: 700.19 | D2: 104.25 | H2: 56.7 | L2: 170 | M2: =C2+D2+E2+F2+G2+H2+I2+J2+L2+K2 -> 1031.14 | N2: =L2-O2 -> 169.98 | O2: =M2-B2-F2 -> 0.02
A3: 45414 | B3: 335.86 | C3: 227.18 | D3: 16.9 | K3: 28.88 | L3: 60 | M3: =C3+D3+E3+F3+G3+H3+I3+J3+L3+K3 -> 332.96 | N3: =L3-O3 -> 62.9 | O3: =M3-B3-F3 -> -2.9
A4: 45415 | B4: 444.01 | C4: 354.31 | D4: 28.7 | L4: 60 | M4: =C4+D4+E4+F4+G4+H4+I4+J4+L4+K4 -> 443.01 | N4: =L4-O4 -> 61 | O4: =M4-B4-F4 -> -1
A5: 45416 | B5: 1257.54 | C5: 911.82 | D5: 142.06 | H5: 65.8 | L5: 145 | M5: =C5+D5+E5+F5+G5+H5+I5+J5+L5+K5 -> 1264.68 | N5: =L5-O5 -> 137.86 | O5: =M5-B5-F5 -> 7.14
A6: 45417 | B6: 825.69 | C6: 495.41 | D6: 28.1 | K6: 146.18 | L6: 160 | M6: =C6+D6+E6+F6+G6+H6+I6+J6+L6+K6 -> 829.69 | N6: =L6-O6 -> 156 | O6: =M6-B6-F6 -> 4
A7: 45418 | B7: 619.7 | C7: 461.1 | D7: 20.3 | H7: 19.9 | L7: 110 | M7: =C7+D7+E7+F7+G7+H7+I7+J7+L7+K7 -> 611.3 | N7: =L7-O7 -> 118.4 | O7: =M7-B7-F7 -> -8.4
A8: 45419 | B8: 726.2 | C8: 447.8 | D8: 86.23 | G8: 9.8 | H8: 18.9 | L8: 170 | M8: =C8+D8+E8+F8+G8+H8+I8+J8+L8+K8 -> 732.73 | N8: =L8-O8 -> 163.47 | O8: =M8-B8-F8 -> 6.53
A9: 45420 | B9: =1656.85-16.9 -> 1639.95 | C9: 991.92 | D9: 62.5 | K9: =139.65+170.88 -> 310.53 | L9: 275 | M9: =C9+D9+E9+F9+G9+H9+I9+J9+L9+K9 -> 1639.95 | N9: =L9-O9 -> 275 | O9: =M9-B9-F9 -> 2.2737368e-13
A10: 45421 | B10: 1287.56 | C10: 843.57 | D10: 91.1 | H10: 71.7 | L10: 280 | M10: =C10+D10+E10+F10+G10+H10+I10+J10+L10+K10 -> 1286.37 | N10: =L10-O10 -> 281.19 | O10: =M10-B10-F10 -> -1.19
A11: 45422 | B11: 1327.1 | C11: 670.8 | D11: 164.01 | H11: 19 | K11: 229.03 | L11: 240 | M11: =C11+D11+E11+F11+G11+H11+I11+J11+L11+K11 -> 1322.84 | N11: =L11-O11 -> 244.26 | O11: =M11-B11-F11 -> -4.26
A12: 45423 | B12: 1521.27 | C12: 1049.7 | D12: 179.44 | H12: 37.8 | L12: 260 | M12: =C12+D12+E12+F12+G12+H12+I12+J12+L12+K12 -> 1526.94 | N12: =L12-O12 -> 254.33 | O12: =M12-B12-F12 -> 5.67
A13: 45424 | B13: 1573.47 | C13: 1118.72 | D13: 78.1 | H13: 52.9 | L13: 320 | M13: =C13+D13+E13+F13+G13+H13+I13+J13+L13+K13 -> 1569.72 | N13: =L13-O13 -> 323.75 | O13: =M13-B13-F13 -> -3.75
A14: 45425 | B14: 678.14 | C14: 169.9 | D14: 0 | H14: 18.9 | K14: 489.84 | L14: 0 | M14: =C14+D14+E14+F14+G14+H14+I14+J14+L14+K14 -> 678.64 | N14: =L14-O14 -> -0.5 | O14: =M14-B14-F14 -> 0.5
A15: 45426 | B15: 1218.75 | C15: 366.37 | D15: 13.3 | K15: =679.93+88.65 -> 768.58 | L15: 70 | M15: =C15+D15+E15+F15+G15+H15+I15+J15+L15+K15 -> 1218.25 | N15: =L15-O15 -> 70.5 | O15: =M15-B15-F15 -> -0.5
A16: 45427 | B16: 349.13 | C16: 261.03 | D16: 27.1 | H16: 19.9 | L16: 45 | M16: =C16+D16+E16+F16+G16+H16+I16+J16+L16+K16 -> 353.03 | N16: =L16-O16 -> 41.1 | O16: =M16-B16-F16 -> 3.9
A17: 45428 | B17: 552.3 | C17: 151.39 | D17: 20.3 | H17: 40 | K17: =171.12+56.83 -> 227.95 | L17: 110 | M17: =C17+D17+E17+F17+G17+H17+I17+J17+L17+K17 -> 549.64 | N17: =L17-O17 -> 112.66 | O17: =M17-B17-F17 -> -2.66
A18: 45429 | B18: 843.79 | C18: 446.46 | D18: 92.83 | H18: 18.9 | K18: 29.5 | L18: 260 | M18: =C18+D18+E18+F18+G18+H18+I18+J18+L18+K18 -> 847.69 | N18: =L18-O18 -> 256.1 | O18: =M18-B18-F18 -> 3.9
A19: 45430 | B19: 1092.63 | C19: 618.63 | D19: 135.56 | H19: 51.8 | L19: 280 | M19: =C19+D19+E19+F19+G19+H19+I19+J19+L19+K19 -> 1085.99 | N19: =L19-O19 -> 286.64 | O19: =M19-B19-F19 -> -6.64
A20: 45431 | B20: 1814.81 | C20: 1256.77 | D20: 145.77 | G20: 36.9 | L20: 375 | M20: =C20+D20+E20+F20+G20+H20+I20+J20+L20+K20 -> 1814.44 | N20: =L20-O20 -> 375.37 | O20: =M20-B20-F20 -> -0.37
A21: 45432 | B21: 613.02 | C21: 350.12 | D21: 28.58 | H21: 65.8 | L21: 170 | M21: =C21+D21+E21+F21+G21+H21+I21+J21+L21+K21 -> 614.5 | N21: =L21-O21 -> 168.52 | O21: =M21-B21-F21 -> 1.48
A22: 45433 | B22: 505.04 | C22: 377.34 | D22: 32.76 | H22: 37.8 | L22: 60 | M22: =C22+D22+E22+F22+G22+H22+I22+J22+L22+K22 -> 507.9 | N22: =L22-O22 -> 57.14 | O22: =M22-B22-F22 -> 2.86
A23: 45434 | B23: 587.4 | C23: 316 | D23: 21.3 | K23: =183.1 -> 183.1 | L23: 70 | M23: =C23+D23+E23+F23+G23+H23+I23+J23+L23+K23 -> 590.4 | N23: =L23-O23 -> 67 | O23: =M23-B23-F23 -> 3
A24: 45435 | B24: 553.36 | C24: 392.66 | D24: 26.3 | H24: 18.9 | L24: 115 | M24: =C24+D24+E24+F24+G24+H24+I24+J24+L24+K24 -> 552.86 | N24: =L24-O24 -> 115.5 | O24: =M24-B24-F24 -> -0.5
A25: 45436 | B25: 561.55 | C25: 403.65 | D25: 73.31 | L25: 90 | M25: =C25+D25+E25+F25+G25+H25+I25+J25+L25+K25 -> 566.96 | N25: =L25-O25 -> 84.59 | O25: =M25-B25-F25 -> 5.41
A26: 45437 | B26: 1546.21 | C26: 766.43 | D26: 111.58 | H26: 89.6 | K26: 369 | L26: 210 | M26: =C26+D26+E26+F26+G26+H26+I26+J26+L26+K26 -> 1546.61 | N26: =L26-O26 -> 209.6 | O26: =M26-B26-F26 -> 0.4
A27: 45438 | B27: 1501.61 | C27: 908.37 | D27: 165.74 | H27: 38.8 | L27: 390 | M27: =C27+D27+E27+F27+G27+H27+I27+J27+L27+K27 -> 1502.91 | N27: =L27-O27 -> 388.7 | O27: =M27-B27-F27 -> 1.3
A28: 45439 | B28: 408.4 | C28: 170.8 | D28: 29.1 | H28: 32.9 | L28: 160 | M28: =C28+D28+E28+F28+G28+H28+I28+J28+L28+K28 -> 392.8 | N28: =L28-O28 -> 175.6 | O28: =M28-B28-F28 -> -15.6
A29: 45440 | B29: 1409.73 | C29: 420.09 | D29: 48.8 | H29: 65.9 | K29: =150.17+669.27 -> 819.44 | L29: 55 | M29: =C29+D29+E29+F29+G29+H29+I29+J29+L29+K29 -> 1409.23 | N29: =L29-O29 -> 55.5 | O29: =M29-B29-F29 -> -0.5
A30: 45441 | B30: 763.7 | C30: 490.8 | D30: 91.9 | H30: 72.8 | L30: 115 | M30: =C30+D30+E30+F30+G30+H30+I30+J30+L30+K30 -> 770.5 | N30: =L30-O30 -> 108.2 | O30: =M30-B30-F30 -> 6.8
A31: 45442 | B31: 2265.66 | C31: 1514.81 | D31: 273.4 | H31: 18.9 | L31: 460 | M31: =C31+D31+E31+F31+G31+H31+I31+J31+L31+K31 -> 2267.11 | N31: =L31-O31 -> 458.55 | O31: =M31-B31-F31 -> 1.45
A32: 45443 | B32: 1798.78 | C32: 960.79 | D32: 131.08 | H32: 18.9 | K32: =89.86+204 -> 293.86 | L32: 400 | M32: =C32+D32+E32+F32+G32+H32+I32+J32+L32+K32 -> 1804.63 | N32: =L32-O32 -> 394.15 | O32: =M32-B32-F32 -> 5.85
A33: TOTAL | M33: =SUM(M2:M32) -> 31665.42 | N33: =M33-O33 -> 31653.48 | O33: =SUM(O2:O32) -> 11.94

Sheet Jun 24
B1: FECHO DO DIA | C1: SALT PAY | D1: SANTANDER | E1: GASTOS C/RECIBO | F1: GASTOS S/RECIBO | G1: GLOVO | H1: UBER EATS | I1: VOLUP | J1: BOLT | K1: Transf. Bancária | L1: NUMERARIO | M1: TOTAL | N1: DEPOSITO | O1: EXTRA | P1: FUNDO CAIXA | R1: Num cert
A2: 45444 | B2: 2543.89 | C2: 1463.82 | D2: 344.15 | H2: 162.5 | L2: 570 | M2: =C2+D2+E2+F2+G2+H2+I2+J2+L2+K2 -> 2540.47 | N2: =L2-O2 -> 573.42 | O2: =M2-B2-F2 -> -3.42
A3: 45445 | B3: 1996.6 | C3: 1329.85 | D3: 151.9 | H3: 39.9 | L3: 480 | M3: =C3+D3+E3+F3+G3+H3+I3+J3+L3+K3 -> 2001.65 | N3: =L3-O3 -> 474.95 | O3: =M3-B3-F3 -> 5.05
A4: 45446 | B4: 1229.39 | C4: 623.91 | D4: 71.5 | H4: 51.8 | K4: 142.98 | L4: 340 | M4: =C4+D4+E4+F4+G4+H4+I4+J4+L4+K4 -> 1230.19 | N4: =L4-O4 -> 339.2 | O4: =M4-B4-F4 -> 0.8
A5: 45447 | B5: 1157.5 | C5: 474.7 | D5: 59.6 | H5: 18.9 | K5: =391.33+84.77 -> 476.1 | L5: 130 | M5: =C5+D5+E5+F5+G5+H5+I5+J5+L5+K5 -> 1159.3 | N5: =L5-O5 -> 128.2 | O5: =M5-B5-F5 -> 1.8
A6: 45448 | B6: 640.24 | C6: 394.63 | D6: 83.5 | H6: 18.9 | K6: 48.11 | L6: 100 | M6: =C6+D6+E6+F6+G6+H6+I6+J6+L6+K6 -> 645.14 | N6: =L6-O6 -> 95.1 | O6: =M6-B6-F6 -> 4.9
A7: 45449 | B7: 645.98 | C7: 422.93 | D7: 65.85 | H7: 32.9 | L7: 130 | M7: =C7+D7+E7+F7+G7+H7+I7+J7+L7+K7 -> 651.68 | N7: =L7-O7 -> 124.3 | O7: =M7-B7-F7 -> 5.7
A8: 45450 | B8: 1262.81 | C8: 850.47 | D8: 138.54 | H8: 58.8 | L8: 250 | M8: =C8+D8+E8+F8+G8+H8+I8+J8+L8+K8 -> 1297.81 | N8: =L8-O8 -> 215 | O8: =M8-B8-F8 -> 35
A9: 45451 | B9: 2227.96 | C9: 755.13 | D9: 130.96 | H9: 32.9 | K9: 952.17 | L9: 360 | M9: =C9+D9+E9+F9+G9+H9+I9+J9+L9+K9 -> 2231.16 | N9: =L9-O9 -> 356.8 | O9: =M9-B9-F9 -> 3.2
A10: 45452 | B10: 1854.94 | C10: 1181.83 | D10: 146.6 | H10: 103.6 | L10: 420 | M10: =C10+D10+E10+F10+G10+H10+I10+J10+L10+K10 -> 1852.03 | N10: =L10-O10 -> 422.91 | O10: =M10-B10-F10 -> -2.91
A11: 45453 | B11: 2334.66 | C11: 1527.16 | D11: 193.6 | H11: 70.7 | K11: 146.6 | L11: 390 | M11: =C11+D11+E11+F11+G11+H11+I11+J11+L11+K11 -> 2328.06 | N11: =L11-O11 -> 396.6 | O11: =M11-B11-F11 -> -6.6
A12: 45454 | B12: 870.99 | C12: 543.93 | D12: 83.7 | K12: 29.21 | L12: 220 | M12: =C12+D12+E12+F12+G12+H12+I12+J12+L12+K12 -> 876.84 | N12: =L12-O12 -> 214.15 | O12: =M12-B12-F12 -> 5.85
A13: 45455 | B13: 975.7 | C13: 437.8 | D13: 64.22 | K13: 294 | L13: 180 | M13: =C13+D13+E13+F13+G13+H13+I13+J13+L13+K13 -> 976.02 | N13: =L13-O13 -> 179.68 | O13: =M13-B13-F13 -> 0.32
A14: 45456 | B14: 638.52 | C14: 402.12 | D14: 78.8 | L14: 160 | M14: =C14+D14+E14+F14+G14+H14+I14+J14+L14+K14 -> 640.92 | N14: =L14-O14 -> 157.6 | O14: =M14-B14-F14 -> 2.4
A15: 45457 | B15: 1143.66 | C15: 596.25 | D15: 25.6 | H15: 88.7 | K15: =153.44+48.73+147.24 -> 349.41 | L15: 96.49 | M15: =C15+D15+E15+F15+G15+H15+I15+J15+L15+K15 -> 1156.45 | N15: =L15-O15 -> 83.7 | O15: =M15-B15-F15 -> 12.79
A16: 45458 | B16: 1859.81 | C16: 1342.61 | D16: 112.6 | H16: 85.8 | L16: 330 | M16: =C16+D16+E16+F16+G16+H16+I16+J16+L16+K16 -> 1871.01 | N16: =L16-O16 -> 318.8 | O16: =M16-B16-F16 -> 11.2
A17: 45459 | B17: 1293.29 | C17: 973.98 | D17: 86.9 | H17: 32.9 | L17: 200 | M17: =C17+D17+E17+F17+G17+H17+I17+J17+L17+K17 -> 1293.78 | N17: =L17-O17 -> 199.51 | O17: =M17-B17-F17 -> 0.49
A18: 45460 | B18: 195.2 | C18: 159.9 | D18: 2.4 | L18: 35 | M18: =C18+D18+E18+F18+G18+H18+I18+J18+L18+K18 -> 197.3 | N18: =L18-O18 -> 32.9 | O18: =M18-B18-F18 -> 2.1
A19: 45461 | B19: 593.33 | C19: 399.95 | D19: 8.2 | L19: 190 | M19: =C19+D19+E19+F19+G19+H19+I19+J19+L19+K19 -> 598.15 | N19: =L19-O19 -> 185.18 | O19: =M19-B19-F19 -> 4.82
A20: 45462 | B20: 1380.21 | C20: 450.8 | D20: 10.2 | K20: =178.96+194.77+491.58 -> 865.31 | L20: 55 | M20: =C20+D20+E20+F20+G20+H20+I20+J20+L20+K20 -> 1381.31 | N20: =L20-O20 -> 53.9 | O20: =M20-B20-F20 -> 1.1
A21: 45463 | B21: 687.74 | C21: 422.7 | D21: 84.13 | H21: 32.9 | L21: 150 | M21: =C21+D21+E21+F21+G21+H21+I21+J21+L21+K21 -> 689.73 | N21: =L21-O21 -> 148.01 | O21: =M21-B21-F21 -> 1.99
A22: 45464 | B22: 1227.96 | C22: 898.5 | D22: 106.9 | H22: 65.8 | L22: 160 | M22: =C22+D22+E22+F22+G22+H22+I22+J22+L22+K22 -> 1231.2 | N22: =L22-O22 -> 156.76 | O22: =M22-B22-F22 -> 3.24
A23: 45465 | B23: 1743.42 | C23: 1014.36 | D23: 143.1 | K23: 200 | L23: 390 | M23: =C23+D23+E23+F23+G23+H23+I23+J23+L23+K23 -> 1747.46 | N23: =L23-O23 -> 385.96 | O23: =M23-B23-F23 -> 4.04
A24: 45466 | B24: 1452.67 | C24: 958.57 | D24: 87.7 | H24: 144.5 | L24: 260 | M24: =C24+D24+E24+F24+G24+H24+I24+J24+L24+K24 -> 1450.77 | N24: =L24-O24 -> 261.9 | O24: =M24-B24-F24 -> -1.9
A25: 45467 | B25: 2226.52 | C25: 1474.42 | D25: 153.4 | H25: 103.6 | L25: 490 | M25: =C25+D25+E25+F25+G25+H25+I25+J25+L25+K25 -> 2221.42 | N25: =L25-O25 -> 495.1 | O25: =M25-B25-F25 -> -5.1
A26: 45468 | B26: 301.15 | C26: 144.5 | D26: 26.5 | H26: 18.9 | K26: 29.31 | L26: 80 | M26: =C26+D26+E26+F26+G26+H26+I26+J26+L26+K26 -> 299.21 | N26: =L26-O26 -> 81.94 | O26: =M26-B26-F26 -> -1.94
A27: 45469 | B27: 750.23 | C27: 499.54 | D27: 72.69 | L27: 180 | M27: =C27+D27+E27+F27+G27+H27+I27+J27+L27+K27 -> 752.23 | N27: =L27-O27 -> 178 | O27: =M27-B27-F27 -> 2
A28: 45470 | B28: 898.05 | C28: 525.06 | D28: 31.1 | H28: 37.8 | K28: 96.59 | L28: 210 | M28: =C28+D28+E28+F28+G28+H28+I28+J28+L28+K28 -> 900.55 | N28: =L28-O28 -> 207.5 | O28: =M28-B28-F28 -> 2.5
A29: 45471 | B29: 1060.42 | C29: 765 | D29: 55.72 | H29: 19 | L29: 220 | M29: =C29+D29+E29+F29+G29+H29+I29+J29+L29+K29 -> 1059.72 | N29: =L29-O29 -> 220.7 | O29: =M29-B29-F29 -> -0.7
A30: 45472 | B30: 1856.2 | C30: 1266.5 | D30: 212.5 | H30: 34.9 | L30: 340 | M30: =C30+D30+E30+F30+G30+H30+I30+J30+L30+K30 -> 1853.9 | N30: =L30-O30 -> 342.3 | O30: =M30-B30-F30 -> -2.3
A31: 45473 | B31: 1611.25 | C31: 1124.16 | D31: 138.4 | L31: 350 | M31: =C31+D31+E31+F31+G31+H31+I31+J31+L31+K31 -> 1612.56 | N31: =L31-O31 -> 348.69 | O31: =M31-B31-F31 -> 1.31
M32: =C32+D32+E32+F32+G32+H32+I32+J32+L32+K32 -> 0 | N32: =L32-O32 -> 0 | O32: =M32-B32-F32 -> 0
A33: TOTAL | M33: =SUM(M2:M32) -> 38748.02 | N33: =M33-O33 -> 38660.29 | O33: =SUM(O2:O32) -> 87.73

Sheet Jul 24
B1: FECHO DO DIA | C1: SALT PAY | D1: SANTANDER | E1: GASTOS C/RECIBO | F1: GASTOS S/RECIBO | G1: GLOVO | H1: UBER EATS | I1: VOLUP | J1: BOLT | K1: Transf. Bancária | L1: NUMERARIO | M1: TOTAL | N1: DEPOSITO | O1: EXTRA | P1: FUNDO CAIXA | R1: Num cert
A2: 45474 | B2: 1003.64 | C2: 520.16 | D2: 136.48 | L2: 340 | M2: =C2+D2+E2+F2+G2+H2+I2+J2+L2+K2 -> 996.64 | N2: =L2-O2 -> 347 | O2: =M2-B2-F2 -> -7
A3: 45475 | B3: 1460.83 | C3: 963.85 | D3: 126.18 | H3: 65.8 | L3: 300 | M3: =C3+D3+E3+F3+G3+H3+I3+J3+L3+K3 -> 1455.83 | N3: =L3-O3 -> 305 | O3: =M3-B3-F3 -> -5
A4: 45476 | B4: 2327.44 | C4: 943.86 | D4: 191.03 | K4: =639.78+374.57 -> 1014.35 | L4: 170 | M4: =C4+D4+E4+F4+G4+H4+I4+J4+L4+K4 -> 2319.24 | N4: =L4-O4 -> 178.2 | O4: =M4-B4-F4 -> -8.2
A5: 45477 | B5: 2497.17 | C5: 1130.88 | D5: 124.73 | H5: 39.9 | K5: =98.36+19.91+27.11+81.45+82.08+71.93+328 -> 708.84 | L5: 490 | M5: =C5+D5+E5+F5+G5+H5+I5+J5+L5+K5 -> 2494.35 | N5: =L5-O5 -> 492.82 | O5: =M5-B5-F5 -> -2.82
A6: 45478 | B6: 1152.12 | C6: 628.02 | D6: 76.3 | H6: 203.6 | L6: 245 | M6: =C6+D6+E6+F6+G6+H6+I6+J6+L6+K6 -> 1152.92 | N6: =L6-O6 -> 244.2 | O6: =M6-B6-F6 -> 0.8
A7: 45479 | B7: 1941.12 | C7: 1340.13 | D7: 175.6 | H7: 32.9 | L7: 400 | M7: =C7+D7+E7+F7+G7+H7+I7+J7+L7+K7 -> 1948.63 | N7: =L7-O7 -> 392.49 | O7: =M7-B7-F7 -> 7.51
A8: 45480 | B8: 1719.65 | C8: 1134.85 | D8: 149 | H8: 18.9 | L8: 410 | M8: =C8+D8+E8+F8+G8+H8+I8+J8+L8+K8 -> 1712.75 | N8: =L8-O8 -> 416.9 | O8: =M8-B8-F8 -> -6.9
A9: 45481 | B9: 938.78 | C9: 646.19 | D9: 31.87 | K9: =59.59 -> 59.59 | L9: 205 | M9: =C9+D9+E9+F9+G9+H9+I9+J9+L9+K9 -> 942.65 | N9: =L9-O9 -> 201.13 | O9: =M9-B9-F9 -> 3.87
A10: 45482 | B10: 1366.52 | C10: 270.15 | D10: 28.7 | H10: 51.9 | K10: 962.27 | L10: 50 | M10: =C10+D10+E10+F10+G10+H10+I10+J10+L10+K10 -> 1363.02 | N10: =L10-O10 -> 53.5 | O10: =M10-B10-F10 -> -3.5
A11: 45483 | B11: 837.92 | C11: 430.32 | D11: 65.4 | H11: 33.9 | L11: 310 | M11: =C11+D11+E11+F11+G11+H11+I11+J11+L11+K11 -> 839.62 | N11: =L11-O11 -> 308.3 | O11: =M11-B11-F11 -> 1.7
A12: 45484 | B12: 1080.44 | C12: 482.3 | D12: 121 | H12: 91.7 | K12: 195.16 | L12: 190 | M12: =C12+D12+E12+F12+G12+H12+I12+J12+L12+K12 -> 1080.16 | N12: =L12-O12 -> 190.28 | O12: =M12-B12-F12 -> -0.28
A13: 45485 | B13: 1614.91 | C13: 143.74 | D13: 945.99 | H13: 19.9 | K13: 214.02 | L13: 290 | M13: =C13+D13+E13+F13+G13+H13+I13+J13+L13+K13 -> 1613.65 | N13: =L13-O13 -> 291.26 | O13: =M13-B13-F13 -> -1.26
A14: 45486 | B14: 2274.71 | C14: 1546.27 | D14: 210.2 | H14: 103.6 | L14: 410 | M14: =C14+D14+E14+F14+G14+H14+I14+J14+L14+K14 -> 2270.07 | N14: =L14-O14 -> 414.64 | O14: =M14-B14-F14 -> -4.64
A15: 45487 | B15: 1199.85 | C15: 773.55 | D15: 76.9 | H15: 18.9 | L15: 330 | M15: =C15+D15+E15+F15+G15+H15+I15+J15+L15+K15 -> 1199.35 | N15: =L15-O15 -> 330.5 | O15: =M15-B15-F15 -> -0.5
A16: 45488 | B16: 1160.27 | C16: 660.02 | D16: 178.92 | L16: 320 | M16: =C16+D16+E16+F16+G16+H16+I16+J16+L16+K16 -> 1158.94 | N16: =L16-O16 -> 321.33 | O16: =M16-B16-F16 -> -1.33
A17: 45489 | B17: 1252.17 | C17: 885.52 | D17: 117.02 | L17: 250 | M17: =C17+D17+E17+F17+G17+H17+I17+J17+L17+K17 -> 1252.54 | N17: =L17-O17 -> 249.63 | O17: =M17-B17-F17 -> 0.37
A18: 45490 | B18: 1263.92 | C18: 807.42 | D18: 107.2 | H18: 38.8 | L18: 320 | M18: =C18+D18+E18+F18+G18+H18+I18+J18+L18+K18 -> 1273.42 | N18: =L18-O18 -> 310.5 | O18: =M18-B18-F18 -> 9.5
A19: 45491 | B19: 2315.54 | C19: 1039.5 | D19: 144.93 | H19: 67.8 | K19: =500+99.48+27.88+22.63+115.72 -> 765.71 | L19: 300 | M19: =C19+D19+E19+F19+G19+H19+I19+J19+L19+K19 -> 2317.94 | N19: =L19-O19 -> 297.6 | O19: =M19-B19-F19 -> 2.4
A20: 45492 | B20: 2004.47 | C20: 1021.21 | D20: 81.3 | K20: =578 -> 578 | L20: 320 | M20: =C20+D20+E20+F20+G20+H20+I20+J20+L20+K20 -> 2000.51 | N20: =L20-O20 -> 323.96 | O20: =M20-B20-F20 -> -3.96
A21: 45493 | B21: 1740.78 | C21: 1233.87 | D21: 226.3 | H21: 18.9 | L21: 260 | M21: =C21+D21+E21+F21+G21+H21+I21+J21+L21+K21 -> 1739.07 | N21: =L21-O21 -> 261.71 | O21: =M21-B21-F21 -> -1.71
A22: 45494 | B22: 2483.61 | C22: 1669.14 | D22: 183.6 | H22: 37.8 | L22: 595 | M22: =C22+D22+E22+F22+G22+H22+I22+J22+L22+K22 -> 2485.54 | N22: =L22-O22 -> 593.07 | O22: =M22-B22-F22 -> 1.93
A23: 45495 | B23: 2201.4 | C23: 1438.46 | D23: 300.84 | H23: 32.9 | L23: 440 | M23: =C23+D23+E23+F23+G23+H23+I23+J23+L23+K23 -> 2212.2 | N23: =L23-O23 -> 429.2 | O23: =M23-B23-F23 -> 10.8
A24: 45496 | B24: 1719.54 | C24: 1117.7 | D24: 171.44 | H24: 18.9 | L24: 405 | M24: =C24+D24+E24+F24+G24+H24+I24+J24+L24+K24 -> 1713.04 | N24: =L24-O24 -> 411.5 | O24: =M24-B24-F24 -> -6.5
A25: 45497 | B25: 1505.19 | C25: 971.81 | D25: 156.96 | H25: 32.9 | L25: 350 | M25: =C25+D25+E25+F25+G25+H25+I25+J25+L25+K25 -> 1511.67 | N25: =L25-O25 -> 343.52 | O25: =M25-B25-F25 -> 6.48
A26: 45498 | B26: 1611.27 | C26: 804.43 | D26: 212.38 | H26: 18.9 | K26: =96.72+56.49+116.42 -> 269.63 | L26: 300 | M26: =C26+D26+E26+F26+G26+H26+I26+J26+L26+K26 -> 1605.34 | N26: =L26-O26 -> 305.93 | O26: =M26-B26-F26 -> -5.93
A27: 45499 | B27: 3024.66 | C27: 929.26 | D27: 151.38 | K27: =472.5+1071.42 -> 1543.92 | L27: 375 | M27: =C27+D27+E27+F27+G27+H27+I27+J27+L27+K27 -> 2999.56 | N27: =L27-O27 -> 400.1 | O27: =M27-B27-F27 -> -25.1
A28: 45500 | B28: 2807.73 | C28: 1784.87 | D28: 164.2 | H28: 37.8 | K28: 111.66 | L28: 730 | M28: =C28+D28+E28+F28+G28+H28+I28+J28+L28+K28 -> 2828.53 | N28: =L28-O28 -> 709.2 | O28: =M28-B28-F28 -> 20.8
A29: 45501 | B29: 1866.3 | C29: 1217.88 | D29: 198.42 | H29: 52.8 | L29: 400 | M29: =C29+D29+E29+F29+G29+H29+I29+J29+L29+K29 -> 1869.1 | N29: =L29-O29 -> 397.2 | O29: =M29-B29-F29 -> 2.8
A30: 45502 | B30: 1042.45 | C30: 704.51 | D30: 57.3 | H30: 71.7 | L30: 210 | M30: =C30+D30+E30+F30+G30+H30+I30+J30+L30+K30 -> 1043.51 | N30: =L30-O30 -> 208.94 | O30: =M30-B30-F30 -> 1.06
A31: 45503 | B31: 1383.2 | C31: 875 | D31: 59.8 | H31: 51.9 | L31: 390 | M31: =C31+D31+E31+F31+G31+H31+I31+J31+L31+K31 -> 1376.7 | N31: =L31-O31 -> 396.5 | O31: =M31-B31-F31 -> -6.5
A32: 45504 | B32: 1709.9 | C32: 608.26 | D32: 123.4 | H32: 51.8 | K32: =445.92+139.84+148.5 -> 734.26 | L32: 195 | M32: =C32+D32+E32+F32+G32+H32+I32+J32+L32+K32 -> 1712.72 | N32: =L32-O32 -> 192.18 | O32: =M32-B32-F32 -> 2.82
A33: TOTAL | M33: =SUM(M2:M32) -> 52489.21 | N33: =M33-O33 -> 52507.5 | O33: =SUM(O2:O32) -> -18.29

Sheet Ago 23
B1: FECHO DO DIA | C1: SALT PAY | D1: SANTANDER | E1: GASTOS C/RECIBO | F1: GASTOS S/RECIBO | G1: GLOVO | H1: UBER EATS | I1: VOLUP | J1: BOLT | K1: Transf. Bancária | L1: NUMERARIO | M1: TOTAL | N1: DEPOSITO | O1: EXTRA | P1: FUNDO CAIXA | R1: Num cert
A2: 45139 | B2: 939.35 | C2: 416.7 | D2: 126.65 | H2: 65.8 | L2: 330 | M2: =C2+D2+E2+F2+G2+H2+I2+J2+L2+K2 -> 939.15 | N2: =L2-O2 -> 330.2 | O2: =M2-B2-F2 -> -0.2 | P2: 70
A3: 45140 | B3: 950.04 | C3: 545.48 | D3: 63.9 | K3: 141.58 | L3: 200 | M3: =C3+D3+E3+F3+G3+H3+I3+J3+L3+K3 -> 950.96 | N3: =L3-O3 -> 199.08 | O3: =M3-B3-F3 -> 0.92 | P3: 65
A4: 45141 | B4: 1019.64 | C4: 707.84 | D4: 58.4 | G4: 18.9 | L4: 235 | M4: =C4+D4+E4+F4+G4+H4+I4+J4+L4+K4 -> 1020.14 | N4: =L4-O4 -> 234.5 | O4: =M4-B4-F4 -> 0.5
A5: 45142 | B5: 1284.32 | C5: 867.8 | D5: 55.8 | L5: 360 | M5: =C5+D5+E5+F5+G5+H5+I5+J5+L5+K5 -> 1283.6 | N5: =L5-O5 -> 360.72 | O5: =M5-B5-F5 -> -0.72
A6: 45143 | B6: 2145.32 | C6: 1475.7 | D6: 156.7 | H6: 20.9 | L6: 510 | M6: =C6+D6+E6+F6+G6+H6+I6+J6+L6+K6 -> 2163.3 | N6: =L6-O6 -> 492.02 | O6: =M6-B6-F6 -> 17.98
A7: 45144 | B7: 2096.28 | C7: 1256.8 | D7: 228.48 | H7: 73.8 | L7: 530 | M7: =C7+D7+E7+F7+G7+H7+I7+J7+L7+K7 -> 2089.08 | N7: =L7-O7 -> 537.2 | O7: =M7-B7-F7 -> -7.2
A8: 45145 | B8: 1858.46 | C8: 984.46 | D8: 173.7 | H8: 58.7 | L8: 645 | M8: =C8+D8+E8+F8+G8+H8+I8+J8+L8+K8 -> 1861.86 | N8: =L8-O8 -> 641.6 | O8: =M8-B8-F8 -> 3.4
A9: 45146 | B9: 1845.52 | C9: 826.02 | D9: 121.7 | H9: 37.8 | K9: 350 | L9: 510 | M9: =C9+D9+E9+F9+G9+H9+I9+J9+L9+K9 -> 1845.52 | N9: =L9-O9 -> 510 | O9: =M9-B9-F9 -> 0
A10: 45147 | B10: 1305.67 | C10: 719.8 | D10: 77.9 | H10: 18.9 | K10: 111.57 | L10: 380 | M10: =C10+D10+E10+F10+G10+H10+I10+J10+L10+K10 -> 1308.17 | N10: =L10-O10 -> 377.5 | O10: =M10-B10-F10 -> 2.5
A11: 45148 | B11: 1322.82 | C11: 802 | D11: 112.82 | H11: 32.9 | L11: 375 | M11: =C11+D11+E11+F11+G11+H11+I11+J11+L11+K11 -> 1322.72 | N11: =L11-O11 -> 375.1 | O11: =M11-B11-F11 -> -0.1
A12: 45149 | B12: 1547.86 | C12: 957.32 | D12: 110.1 | G12: 18.9 | L12: 460 | M12: =C12+D12+E12+F12+G12+H12+I12+J12+L12+K12 -> 1546.32 | N12: =L12-O12 -> 461.54 | O12: =M12-B12-F12 -> -1.54
A13: 45150 | B13: 1617.92 | C13: 1070.12 | D13: 57.3 | H13: 19.9 | L13: 470 | M13: =C13+D13+E13+F13+G13+H13+I13+J13+L13+K13 -> 1617.32 | N13: =L13-O13 -> 470.6 | O13: =M13-B13-F13 -> -0.6
A14: 45151 | B14: 1573.86 | C14: 1150.8 | D14: 0 | H14: 36.9 | L14: 380 | M14: =C14+D14+E14+F14+G14+H14+I14+J14+L14+K14 -> 1567.7 | N14: =L14-O14 -> 386.16 | O14: =M14-B14-F14 -> -6.16
A15: 45152 | B15: 1149.38 | C15: 676.88 | D15: 88.2 | H15: 37.8 | L15: 345 | M15: =C15+D15+E15+F15+G15+H15+I15+J15+L15+K15 -> 1147.88 | N15: =L15-O15 -> 346.5 | O15: =M15-B15-F15 -> -1.5
A16: 45153 | B16: 1995.91 | C16: 1228.65 | D16: 140.8 | G16: 18.9 | H16: 19 | L16: 590 | M16: =C16+D16+E16+F16+G16+H16+I16+J16+L16+K16 -> 1997.35 | N16: =L16-O16 -> 588.56 | O16: =M16-B16-F16 -> 1.44
A17: 45154 | B17: 1091.24 | C17: 785.44 | D17: 60.7 | H17: 18.9 | L17: 230 | M17: =C17+D17+E17+F17+G17+H17+I17+J17+L17+K17 -> 1095.04 | N17: =L17-O17 -> 226.2 | O17: =M17-B17-F17 -> 3.8
A18: 45155 | B18: 1069.54 | C18: 590.8 | D18: 70.7 | K18: 140.94 | L18: 265 | M18: =C18+D18+E18+F18+G18+H18+I18+J18+L18+K18 -> 1067.44 | N18: =L18-O18 -> 267.1 | O18: =M18-B18-F18 -> -2.1
A19: 45156 | B19: 1128.48 | C19: 608.4 | D19: 132.88 | L19: 405 | M19: =C19+D19+E19+F19+G19+H19+I19+J19+L19+K19 -> 1146.28 | N19: =L19-O19 -> 387.2 | O19: =M19-B19-F19 -> 17.8
A20: 45157 | B20: 1201.95 | C20: 716.5 | D20: 104.2 | H20: 18.9 | L20: 360 | M20: =C20+D20+E20+F20+G20+H20+I20+J20+L20+K20 -> 1199.6 | N20: =L20-O20 -> 362.35 | O20: =M20-B20-F20 -> -2.35
A21: 45158 | B21: 1765.44 | C21: 1154.74 | D21: 128.1 | L21: 485 | M21: =C21+D21+E21+F21+G21+H21+I21+J21+L21+K21 -> 1767.84 | N21: =L21-O21 -> 482.6 | O21: =M21-B21-F21 -> 2.4
A22: 45159 | B22: 1510.12 | C22: 832 | D22: 72.6 | G22: 18.9 | H22: 37.8 | L22: 540 | M22: =C22+D22+E22+F22+G22+H22+I22+J22+L22+K22 -> 1501.3 | N22: =L22-O22 -> 548.82 | O22: =M22-B22-F22 -> -8.82
A23: 45160 | B23: 1694.84 | C23: 989.4 | D23: 100.9 | H23: 93.7 | L23: 510 | M23: =C23+D23+E23+F23+G23+H23+I23+J23+L23+K23 -> 1694 | N23: =L23-O23 -> 510.84 | O23: =M23-B23-F23 -> -0.84
A24: 45161 | B24: 4100.11 | C24: 1046.7 | D24: 160.18 | K24: =2261.53+201.5 -> 2463.03 | L24: 440 | M24: =C24+D24+E24+F24+G24+H24+I24+J24+L24+K24 -> 4109.91 | N24: =L24-O24 -> 430.2 | O24: =M24-B24-F24 -> 9.8
A25: 45162 | B25: 1419.82 | C25: 1003.18 | D25: 66.1 | H25: 27.3 | L25: 325 | M25: =C25+D25+E25+F25+G25+H25+I25+J25+L25+K25 -> 1421.58 | N25: =L25-O25 -> 323.24 | O25: =M25-B25-F25 -> 1.76
A26: 45163 | B26: 1156.68 | C26: 693.78 | D26: 57.4 | H26: 51.8 | L26: 350 | M26: =C26+D26+E26+F26+G26+H26+I26+J26+L26+K26 -> 1152.98 | N26: =L26-O26 -> 353.7 | O26: =M26-B26-F26 -> -3.7
A27: 45164 | B27: 1683.96 | C27: 1122.22 | D27: 96.7 | H27: 38.8 | L27: 420 | M27: =C27+D27+E27+F27+G27+H27+I27+J27+L27+K27 -> 1677.72 | N27: =L27-O27 -> 426.24 | O27: =M27-B27-F27 -> -6.24
A28: 45165 | B28: 1450.06 | C28: 926.88 | D28: 86.3 | H28: 43.9 | L28: 390 | M28: =C28+D28+E28+F28+G28+H28+I28+J28+L28+K28 -> 1447.08 | N28: =L28-O28 -> 392.98 | O28: =M28-B28-F28 -> -2.98
A29: 45166 | B29: 896.43 | C29: 636.33 | D29: 32.3 | H29: 18.9 | L29: 205 | M29: =C29+D29+E29+F29+G29+H29+I29+J29+L29+K29 -> 892.53 | N29: =L29-O29 -> 208.9 | O29: =M29-B29-F29 -> -3.9
A30: 45167 | B30: 892.24 | C30: 475.82 | D30: 75.74 | L30: 340 | M30: =C30+D30+E30+F30+G30+H30+I30+J30+L30+K30 -> 891.56 | N30: =L30-O30 -> 340.68 | O30: =M30-B30-F30 -> -0.68
A31: 45168 | B31: 867.46 | C31: 538.06 | D31: 26.4 | L31: 280 | M31: =C31+D31+E31+F31+G31+H31+I31+J31+L31+K31 -> 844.46 | N31: =L31-O31 -> 303 | O31: =M31-B31-F31 -> -23
A32: 45169 | B32: 1199.81 | C32: 626.63 | D32: 124.5 | H32: 51.8 | L32: 390 | M32: =C32+D32+E32+F32+G32+H32+I32+J32+L32+K32 -> 1192.93 | N32: =L32-O32 -> 396.88 | O32: =M32-B32-F32 -> -6.88
A33: TOTAL | M33: =SUM(M2:M32) -> 45763.32 | N33: =M33-O33 -> 45780.53 | O33: =SUM(O2:O32) -> -17.21

Sheet Ago 24
C1: =MEDIAN(C3:C17) -> 2152.83
B2: Loja | C2: FECHO TOTAL | D2: FECHO MATOSINHOS | E2: SALT PAY | F2: SANTANDER | G2: GASTOS C/RECIBO | H2: GASTOS S/RECIBO | I2: GLOVO | J2: UBER EATS | K2: VOLUP | L2: BOLT | M2: Transf. Bancária | N2: TIME OUT MARKET | O2: NUMERARIO | P2: TOTAL | Q2: DEPOSITO | R2: EXTRA | S2: FUNDO CAIXA
A3: 45505 | B3: Matosinhos;TimeOut;Bolhão | C3: =D3+N3 -> 974.66 | D3: =974.66+0 -> 974.66 | E3: 594.45 | F3: 83.31 | J3: 32.9 | O3: 270 | P3: =E3+F3+G3+H3+I3+J3+K3+L3+O3+M3+N3 -> 980.66 | Q3: =O3-R3 -> 264 | R3: =P3-C3-H3 -> 6
A4: 45506 | B4: Matosinhos | C4: =D4+N4 -> 1345.81 | D4: =1345.81+0 -> 1345.81 | E4: 955.51 | F4: 92.6 | J4: 34 | O4: 260 | P4: =E4+F4+G4+H4+I4+J4+K4+L4+O4+M4+N4 -> 1342.11 | Q4: =O4-R4 -> 263.7 | R4: =P4-C4-H4 -> -3.7
A5: 45507 | B5: Matosinhos | C5: =D5+N5 -> 2501.74 | D5: =2501.74+0 -> 2501.74 | E5: 1655.36 | F5: 237.05 | J5: 98.7 | M5: =86.15+4.44 -> 90.59 | O5: 420 | P5: =E5+F5+G5+H5+I5+J5+K5+L5+O5+M5+N5 -> 2501.7 | Q5: =O5-R5 -> 420.04 | R5: =P5-C5-H5 -> -0.04
A6: 45508 | B6: Matosinhos | C6: =D6+N6 -> 2152.83 | D6: =2152.83+0 -> 2152.83 | E6: 1464.53 | F6: 148.9 | J6: 65.8 | O6: 470 | P6: =E6+F6+G6+H6+I6+J6+K6+L6+O6+M6+N6 -> 2149.23 | Q6: =O6-R6 -> 473.6 | R6: =P6-C6-H6 -> -3.6
A7: 45509 | B7: Matosinhos | C7: =D7+N7 -> 1140.2 | D7: =1140.2+0 -> 1140.2 | E7: 721.74 | F7: 65.7 | O7: 350 | P7: =E7+F7+G7+H7+I7+J7+K7+L7+O7+M7+N7 -> 1137.44 | Q7: =O7-R7 -> 352.76 | R7: =P7-C7-H7 -> -2.76
A8: 45510 | B8: Matosinhos | C8: =D8+N8 -> 1892.15 | D8: =1192.55+0 -> 1192.55 | E8: 699.45 | F8: 113.14 | J8: 85.8 | N8: 699.6 | O8: 290 | P8: =E8+F8+G8+H8+I8+J8+K8+L8+O8+M8+N8 -> 1887.99 | Q8: =O8-R8 -> 294.16 | R8: =P8-C8-H8 -> -4.16
A9: 45511 | C9: =D9+N9 -> 2094.87 | D9: 1646.47 | E9: 857.7 | F9: 113.22 | J9: 65.8 | M9: =121.73+190.62+114.5 -> 426.85 | N9: 448.4 | O9: 180 | P9: =E9+F9+G9+H9+I9+J9+K9+L9+O9+M9+N9 -> 2091.97 | Q9: =O9-R9 -> 182.9 | R9: =P9-C9-H9 -> -2.9
A10: 45512 | C10: =D10+N10 -> 2190.54 | D10: 1543.74 | E10: 664.5 | F10: 112.78 | J10: 32.9 | M10: =28.76+425.5 -> 454.26 | N10: 646.8 | O10: 280 | P10: =E10+F10+G10+H10+I10+J10+K10+L10+O10+M10+N10 -> 2191.24 | Q10: =O10-R10 -> 279.3 | R10: =P10-C10-H10 -> 0.7
A11: 45513 | C11: =D11+N11 -> 3604.4 | D11: 3035.2 | E11: 1255.62 | F11: 132.5 | J11: 70.7 | M11: 1178.3 | N11: 569.2 | O11: 400 | P11: =E11+F11+G11+H11+I11+J11+K11+L11+O11+M11+N11 -> 3606.32 | Q11: =O11-R11 -> 398.08 | R11: =P11-C11-H11 -> 1.92
A12: 45514 | C12: =D12+N12 -> 3324.05 | D12: 2649.25 | E12: 1793.15 | F12: 225.9 | J12: 71.7 | M12: 58.62 | N12: 674.8 | O12: 490 | P12: =E12+F12+G12+H12+I12+J12+K12+L12+O12+M12+N12 -> 3314.17 | Q12: =O12-R12 -> 499.88 | R12: =P12-C12-H12 -> -9.88
A13: 45515 | C13: =D13+N13 -> 2433.92 | D13: 1772.92 | E13: 1244.97 | F13: 172.35 | J13: 98.7 | N13: 661 | O13: 260 | P13: =E13+F13+G13+H13+I13+J13+K13+L13+O13+M13+N13 -> 2437.02 | Q13: =O13-R13 -> 256.9 | R13: =P13-C13-H13 -> 3.1
A14: 45516 | C14: =D14+N14 -> 1801.96 | D14: 1322.96 | E14: 858 | F14: 138.86 | J14: 19 | N14: 479 | O14: 310 | P14: =E14+F14+G14+H14+I14+J14+K14+L14+O14+M14+N14 -> 1804.86 | Q14: =O14-R14 -> 307.1 | R14: =P14-C14-H14 -> 2.9
A15: 45517 | C15: =D15+N15 -> 1596.26 | D15: 972.86 | E15: 613.16 | F15: 67.4 | J15: 18.9 | N15: 623.4 | O15: 270 | P15: =E15+F15+G15+H15+I15+J15+K15+L15+O15+M15+N15 -> 1592.86 | Q15: =O15-R15 -> 273.4 | R15: =P15-C15-H15 -> -3.4
A16: 45518 | C16: =D16+N16 -> 2344.43 | D16: 1788.43 | E16: 1175.4 | F16: 117.2 | J16: 32.9 | M16: 74.45 | N16: 556 | O16: 390 | P16: =E16+F16+G16+H16+I16+J16+K16+L16+O16+M16+N16 -> 2345.95 | Q16: =O16-R16 -> 388.48 | R16: =P16-C16-H16 -> 1.52
A17: 45519 | C17: =D17+N17 -> 3007.33 | D17: 2289.53 | E17: 1446.43 | F17: 218.82 | J17: 66.8 | N17: 717.8 | O17: 550 | P17: =E17+F17+G17+H17+I17+J17+K17+L17+O17+M17+N17 -> 2999.85 | Q17: =O17-R17 -> 557.48 | R17: =P17-C17-H17 -> -7.48
A18: 45520 | C18: =D18+N18 -> 2595.51 | D18: 1833.51 | E18: 1175.1 | F18: 125 | J18: 89.8 | M18: 27.11 | N18: 762 | O18: 430 | P18: =E18+F18+G18+H18+I18+J18+K18+L18+O18+M18+N18 -> 2609.01 | Q18: =O18-R18 -> 416.5 | R18: =P18-C18-H18 -> 13.5
A19: 45521 | C19: =D19+N19 -> 2451.13 | D19: 1957.73 | E19: 1392.29 | F19: 101.38 | N19: 493.4 | O19: 460 | P19: =E19+F19+G19+H19+I19+J19+K19+L19+O19+M19+N19 -> 2447.07 | Q19: =O19-R19 -> 464.06 | R19: =P19-C19-H19 -> -4.06
A20: 45522 | C20: =D20+N20 -> 2749.72 | D20: 2164.52 | E20: 1274.78 | F20: 204.45 | J20: 58.7 | N20: 585.2 | O20: 630 | P20: =E20+F20+G20+H20+I20+J20+K20+L20+O20+M20+N20 -> 2753.13 | Q20: =O20-R20 -> 626.59 | R20: =P20-C20-H20 -> 3.41
A21: 45523 | C21: =D21+N21 -> 2075.56 | D21: 1372.16 | E21: 818.08 | F21: 73.9 | J21: 51.9 | N21: 703.4 | O21: 430 | P21: =E21+F21+G21+H21+I21+J21+K21+L21+O21+M21+N21 -> 2077.28 | Q21: =O21-R21 -> 428.28 | R21: =P21-C21-H21 -> 1.72
A22: 45524 | C22: =D22+N22 -> 1769.84 | D22: 1317.24 | E22: 934.14 | F22: 101.09 | J22: 56.7 | N22: 452.6 | O22: 220 | P22: =E22+F22+G22+H22+I22+J22+K22+L22+O22+M22+N22 -> 1764.53 | Q22: =O22-R22 -> 225.31 | R22: =P22-C22-H22 -> -5.31
A23: 45525 | C23: =D23+N23 -> 2339.2 | D23: 2052.8 | E23: 1005 | F23: 166.6 | J23: 85.7 | M23: =116.26+87.83+10.36+209.25 -> 423.7 | N23: 286.4 | O23: 370 | P23: =E23+F23+G23+H23+I23+J23+K23+L23+O23+M23+N23 -> 2337.4 | Q23: =O23-R23 -> 371.8 | R23: =P23-C23-H23 -> -1.8
A24: 45526 | C24: =D24+N24 -> 1484.21 | D24: 1090.61 | E24: 753.31 | F24: 102.3 | J24: 19.9 | N24: 393.6 | O24: 215 | P24: =E24+F24+G24+H24+I24+J24+K24+L24+O24+M24+N24 -> 1484.11 | Q24: =O24-R24 -> 215.1 | R24: =P24-C24-H24 -> -0.1
A25: 45527 | C25: =D25+N25 -> 3247.57 | D25: 2877.17 | E25: 1183.43 | F25: 116.6 | J25: 65.8 | M25: 1187.35 | N25: 370.4 | O25: 325 | P25: =E25+F25+G25+H25+I25+J25+K25+L25+O25+M25+N25 -> 3248.58 | Q25: =O25-R25 -> 323.99 | R25: =P25-C25-H25 -> 1.01
A26: 45528 | C26: =D26+N26 -> 2576.15 | D26: 2054.95 | E26: 1334.85 | F26: 192.99 | J26: 108.6 | M26: 90.31 | N26: 521.2 | O26: 330 | P26: =E26+F26+G26+H26+I26+J26+K26+L26+O26+M26+N26 -> 2577.95 | Q26: =O26-R26 -> 328.2 | R26: =P26-C26-H26 -> 1.8
A27: 45529 | C27: =D27+N27 -> 2642.61 | D27: 2063.01 | E27: 1362.57 | F27: 122.2 | J27: 92.6 | N27: 579.6 | O27: 490 | P27: =E27+F27+G27+H27+I27+J27+K27+L27+O27+M27+N27 -> 2646.97 | Q27: =O27-R27 -> 485.64 | R27: =P27-C27-H27 -> 4.36
A28: 45530 | C28: =D28+N28 -> 1887.13 | D28: 1477.93 | E28: 973.73 | F28: 78.5 | J28: 20.9 | N28: 409.2 | O28: 400 | P28: =E28+F28+G28+H28+I28+J28+K28+L28+O28+M28+N28 -> 1882.33 | Q28: =O28-R28 -> 404.8 | R28: =P28-C28-H28 -> -4.8
A29: 45531 | C29: =D29+N29 -> 2209.99 | D29: 1813.99 | E29: 650.84 | F29: 126.75 | J29: =84.7+32.9 -> 117.6 | M29: 714 | N29: 396 | O29: 205 | P29: =E29+F29+G29+H29+I29+J29+K29+L29+O29+M29+N29 -> 2210.19 | Q29: =O29-R29 -> 204.8 | R29: =P29-C29-H29 -> 0.2
A30: 45532 | C30: =D30+N30 -> 2380.6 | D30: 1944.8 | E30: 700.9 | F30: 58.3 | M30: 965 | N30: 435.8 | O30: 220 | P30: =E30+F30+G30+H30+I30+J30+K30+L30+O30+M30+N30 -> 2380 | Q30: =O30-R30 -> 220.6 | R30: =P30-C30-H30 -> -0.6
A31: 45533 | C31: =D31+N31 -> 2254.02 | D31: 1926.22 | E31: 933.6 | F31: 134.09 | M31: 526.79 | N31: 327.8 | O31: 330 | P31: =E31+F31+G31+H31+I31+J31+K31+L31+O31+M31+N31 -> 2252.28 | Q31: =O31-R31 -> 331.74 | R31: =P31-C31-H31 -> -1.74
A32: 45534 | C32: =D32+N32 -> 1643.99 | D32: 1324.79 | E32: 887.89 | F32: 124.43 | J32: 18.9 | M32: =26.26 -> 26.26 | N32: 319.2 | O32: 285 | P32: =E32+F32+G32+H32+I32+J32+K32+L32+O32+M32+N32 -> 1661.68 | Q32: =O32-R32 -> 267.31 | R32: =P32-C32-H32 -> 17.69
A33: 45535 | C33: =D33+N33 -> 1805.54 | D33: 1400.94 | E33: 976.21 | F33: 87.68 | N33: 404.6 | O33: 340 | P33: =E33+F33+G33+H33+I33+J33+K33+L33+O33+M33+N33 -> 1808.49 | Q33: =O33-R33 -> 337.05 | R33: =P33-C33-H33 -> 2.95
A34: TOTAL | P34: =SUM(P3:P33) -> 68524.37 | Q34: =P34-R34 -> 68517.92 | R34: =SUM(R3:R33) -> 6.45

Sheet Set 23
B1: FECHO DO DIA | C1: SALT PAY | D1: SANTANDER | E1: GASTOS C/RECIBO | F1: GASTOS S/RECIBO | G1: GLOVO | H1: UBER EATS | I1: VOLUP | J1: BOLT | K1: Transf. Bancária | L1: NUMERARIO | M1: TOTAL | N1: DEPOSITO | O1: EXTRA | P1: FUNDO CAIXA | R1: Num cert
A2: 45170 | B2: 1166.55 | C2: 687.29 | D2: 56.8 | H2: 98.7 | L2: 325 | M2: =C2+D2+E2+F2+G2+H2+I2+J2+L2+K2 -> 1167.79 | N2: =L2-O2 -> 323.76 | O2: =M2-B2-F2 -> 1.24 | P2: 70
A3: 45171 | B3: 1531.37 | C3: 970.27 | D3: 132.5 | H3: 37.8 | L3: 400 | M3: =C3+D3+E3+F3+G3+H3+I3+J3+L3+K3 -> 1540.57 | N3: =L3-O3 -> 390.8 | O3: =M3-B3-F3 -> 9.2 | P3: 65
A4: 45172 | B4: 1131.26 | C4: 750.48 | D4: 111.8 | H4: 18.9 | L4: 270 | M4: =C4+D4+E4+F4+G4+H4+I4+J4+L4+K4 -> 1151.18 | N4: =L4-O4 -> 250.08 | O4: =M4-B4-F4 -> 19.92
A5: 45173 | B5: 465 | C5: 284.7 | D5: 53.3 | H5: 32.9 | L5: 100 | M5: =C5+D5+E5+F5+G5+H5+I5+J5+L5+K5 -> 470.9 | N5: =L5-O5 -> 94.1 | O5: =M5-B5-F5 -> 5.9
A6: 45174 | B6: 793.38 | C6: 393.78 | D6: 158.5 | L6: 240 | M6: =C6+D6+E6+F6+G6+H6+I6+J6+L6+K6 -> 792.28 | N6: =L6-O6 -> 241.1 | O6: =M6-B6-F6 -> -1.1
A7: 45175 | B7: 1266.9 | C7: 731.62 | D7: 129 | H7: 74.7 | K7: 25.08 | L7: 305 | M7: =C7+D7+E7+F7+G7+H7+I7+J7+L7+K7 -> 1265.4 | N7: =L7-O7 -> 306.5 | O7: =M7-B7-F7 -> -1.5
A8: 45176 | B8: 1010.9 | C8: 639.4 | D8: 47.3 | H8: 91.7 | L8: 240 | M8: =C8+D8+E8+F8+G8+H8+I8+J8+L8+K8 -> 1018.4 | N8: =L8-O8 -> 232.5 | O8: =M8-B8-F8 -> 7.5
A9: 45177 | B9: 1031.65 | C9: 617.65 | D9: 131.5 | H9: 18.9 | L9: 260 | M9: =C9+D9+E9+F9+G9+H9+I9+J9+L9+K9 -> 1028.05 | N9: =L9-O9 -> 263.6 | O9: =M9-B9-F9 -> -3.6
A10: 45178 | B10: 2128.88 | C10: 1173.36 | D10: 279.4 | H10: 65.8 | L10: 615 | M10: =C10+D10+E10+F10+G10+H10+I10+J10+L10+K10 -> 2133.56 | N10: =L10-O10 -> 610.32 | O10: =M10-B10-F10 -> 4.68
A11: 45179 | B11: 1663.46 | C11: 1206.76 | D11: 119.4 | L11: 345 | M11: =C11+D11+E11+F11+G11+H11+I11+J11+L11+K11 -> 1671.16 | N11: =L11-O11 -> 337.3 | O11: =M11-B11-F11 -> 7.7
A12: 45180 | B12: 652.64 | C12: 474.64 | D12: 26.8 | L12: 150 | M12: =C12+D12+E12+F12+G12+H12+I12+J12+L12+K12 -> 651.44 | N12: =L12-O12 -> 151.2 | O12: =M12-B12-F12 -> -1.2
A13: 45181 | B13: 2465.71 | C13: 407.68 | D13: 66 | K13: =241+52.54+103.25+789+615.34 -> 1801.13 | L13: 190 | M13: =C13+D13+E13+F13+G13+H13+I13+J13+L13+K13 -> 2464.81 | N13: =L13-O13 -> 190.9 | O13: =M13-B13-F13 -> -0.9
A14: 45182 | B14: 1326.72 | C14: 886.12 | D14: 97.8 | L14: 345 | M14: =C14+D14+E14+F14+G14+H14+I14+J14+L14+K14 -> 1328.92 | N14: =L14-O14 -> 342.8 | O14: =M14-B14-F14 -> 2.2
A15: 45183 | B15: 1264.26 | C15: 663.58 | D15: 80.36 | H15: 70.7 | L15: 450 | M15: =C15+D15+E15+F15+G15+H15+I15+J15+L15+K15 -> 1264.64 | N15: =L15-O15 -> 449.62 | O15: =M15-B15-F15 -> 0.38
A16: 45184 | B16: 894.5 | C16: 548.62 | D16: 56.38 | H16: 32.9 | K16: 29.5 | L16: 230 | M16: =C16+D16+E16+F16+G16+H16+I16+J16+L16+K16 -> 897.4 | N16: =L16-O16 -> 227.1 | O16: =M16-B16-F16 -> 2.9
A17: 45185 | B17: 1617.05 | C17: 900.72 | D17: 201.1 | H17: 77.7 | K17: 51.63 | L17: 380 | M17: =C17+D17+E17+F17+G17+H17+I17+J17+L17+K17 -> 1611.15 | N17: =L17-O17 -> 385.9 | O17: =M17-B17-F17 -> -5.9
A18: 45186 | B18: 837.32 | C18: 562.58 | D18: 39.74 | H18: 18.9 | L18: 225 | M18: =C18+D18+E18+F18+G18+H18+I18+J18+L18+K18 -> 846.22 | N18: =L18-O18 -> 216.1 | O18: =M18-B18-F18 -> 8.9
A19: 45187 | B19: 521.91 | C19: 351.51 | D19: 17.2 | L19: 155 | M19: =C19+D19+E19+F19+G19+H19+I19+J19+L19+K19 -> 523.71 | N19: =L19-O19 -> 153.2 | O19: =M19-B19-F19 -> 1.8
A20: 45188 | B20: 657.57 | C20: 401.66 | D20: 25 | G20: 36.9 | H20: 38.91 | L20: 155 | M20: =C20+D20+E20+F20+G20+H20+I20+J20+L20+K20 -> 657.47 | N20: =L20-O20 -> 155.1 | O20: =M20-B20-F20 -> -0.1
A21: 45189 | B21: 395.46 | C21: 266.76 | D21: 11.4 | L21: 120 | M21: =C21+D21+E21+F21+G21+H21+I21+J21+L21+K21 -> 398.16 | N21: =L21-O21 -> 117.3 | O21: =M21-B21-F21 -> 2.7
A22: 45190 | B22: 484.76 | C22: 332.36 | D22: 17.7 | H22: 67.8 | L22: 65 | M22: =C22+D22+E22+F22+G22+H22+I22+J22+L22+K22 -> 482.86 | N22: =L22-O22 -> 66.9 | O22: =M22-B22-F22 -> -1.9
A23: 45191 | B23: 1214.81 | C23: 489.76 | D23: 37.1 | H23: 18.9 | K23: =147.5+73.75+25.08+177.66 -> 423.99 | L23: 245 | M23: =C23+D23+E23+F23+G23+H23+I23+J23+L23+K23 -> 1214.75 | N23: =L23-O23 -> 245.06 | O23: =M23-B23-F23 -> -0.06
A24: 45192 | B24: 1714.11 | C24: 1053.75 | D24: 161.06 | H24: 44.9 | L24: 440 | M24: =C24+D24+E24+F24+G24+H24+I24+J24+L24+K24 -> 1699.71 | N24: =L24-O24 -> 454.4 | O24: =M24-B24-F24 -> -14.4
A25: 45193 | B25: 1972.02 | C25: 1486.76 | D25: 128.52 | L25: 355 | M25: =C25+D25+E25+F25+G25+H25+I25+J25+L25+K25 -> 1970.28 | N25: =L25-O25 -> 356.74 | O25: =M25-B25-F25 -> -1.74
A26: 45194 | B26: 553.92 | C26: 382.82 | D26: 57.6 | L26: 110 | M26: =C26+D26+E26+F26+G26+H26+I26+J26+L26+K26 -> 550.42 | N26: =L26-O26 -> 113.5 | O26: =M26-B26-F26 -> -3.5
A27: 45195 | B27: 1277.7 | C27: 181.8 | D27: 28.4 | H27: 71.7 | K27: 858.7 | L27: 140 | M27: =C27+D27+E27+F27+G27+H27+I27+J27+L27+K27 -> 1280.6 | N27: =L27-O27 -> 137.1 | O27: =M27-B27-F27 -> 2.9
A28: 45196 | B28: 842.46 | C28: 493.4 | D28: 85.02 | H28: 37.8 | L28: 230 | M28: =C28+D28+E28+F28+G28+H28+I28+J28+L28+K28 -> 846.22 | N28: =L28-O28 -> 226.24 | O28: =M28-B28-F28 -> 3.76
A29: 45197 | B29: 751.76 | C29: 439.7 | D29: 96.56 | H29: 32.9 | L29: 180 | M29: =C29+D29+E29+F29+G29+H29+I29+J29+L29+K29 -> 749.16 | N29: =L29-O29 -> 182.6 | O29: =M29-B29-F29 -> -2.6
A30: 45198 | B30: 1076.47 | C30: 735.48 | D30: 82.1 | H30: 72.8 | K30: 27.29 | L30: 160 | M30: =C30+D30+E30+F30+G30+H30+I30+J30+L30+K30 -> 1077.67 | N30: =L30-O30 -> 158.8 | O30: =M30-B30-F30 -> 1.2
A31: 45199 | B31: 2972.72 | C31: 1658.92 | D31: 230.6 | G31: 18.9 | H31: 88.7 | L31: 965 | M31: =C31+D31+E31+F31+G31+H31+I31+J31+L31+K31 -> 2962.12 | N31: =L31-O31 -> 975.6 | O31: =M31-B31-F31 -> -10.6
N32: =L32-O32 -> 0 | O32: =M32-B32-F32 -> 0
A33: TOTAL | M33: =SUM(M2:M32) -> 35717 | N33: =M33-O33 -> 35683.22 | O33: =SUM(O2:O32) -> 33.78

Sheet Out 23
B1: FECHO DO DIA | C1: SALT PAY | D1: SANTANDER | E1: GASTOS C/RECIBO | F1: GASTOS S/RECIBO | G1: GLOVO | H1: UBER EATS | I1: VOLUP | J1: BOLT | K1: Transf. Bancária | L1: NUMERARIO | M1: TOTAL | N1: DEPOSITO | O1: EXTRA | P1: FUNDO CAIXA | R1: Num cert
A2: 45200 | B2: 2200.94 | C2: 1388.26 | D2: 237.18 | H2: 56.7 | L2: 520 | M2: =C2+D2+E2+F2+G2+H2+I2+J2+L2+K2 -> 2202.14 | N2: =L2-O2 -> 518.8 | O2: =M2-B2-F2 -> 1.2
A3: 45201 | B3: 601.64 | C3: 312.7 | D3: 110.54 | H3: 33 | L3: 145 | M3: =C3+D3+E3+F3+G3+H3+I3+J3+L3+K3 -> 601.24 | N3: =L3-O3 -> 145.4 | O3: =M3-B3-F3 -> -0.4
A4: 45202 | B4: 501 | C4: 296.8 | D4: 38.6 | H4: 21 | L4: 150 | M4: =C4+D4+E4+F4+G4+H4+I4+J4+L4+K4 -> 506.4 | N4: =L4-O4 -> 144.6 | O4: =M4-B4-F4 -> 5.4
A5: 45203 | B5: 1517.95 | C5: 572.48 | D5: 54.6 | H5: 108.5 | K5: =578.29+132.98 -> 711.27 | L5: 70 | M5: =C5+D5+E5+F5+G5+H5+I5+J5+L5+K5 -> 1516.85 | N5: =L5-O5 -> 71.1 | O5: =M5-B5-F5 -> -1.1
A6: 45204 | B6: 2293.47 | C6: 1552.28 | D6: 176.64 | H6: 90.6 | K6: =85.47+72.28 -> 157.75 | L6: 320 | M6: =C6+D6+E6+F6+G6+H6+I6+J6+L6+K6 -> 2297.27 | N6: =L6-O6 -> 316.2 | O6: =M6-B6-F6 -> 3.8
A7: 45205 | B7: 1443.32 | C7: 997.62 | D7: 146.6 | L7: 305 | M7: =C7+D7+E7+F7+G7+H7+I7+J7+L7+K7 -> 1449.22 | N7: =L7-O7 -> 299.1 | O7: =M7-B7-F7 -> 5.9
A8: 45206 | B8: 2578.48 | C8: 1541.98 | D8: 251.9 | H8: 156.4 | L8: 630 | M8: =C8+D8+E8+F8+G8+H8+I8+J8+L8+K8 -> 2580.28 | N8: =L8-O8 -> 628.2 | O8: =M8-B8-F8 -> 1.8
A9: 45207 | B9: 1834.42 | C9: 1234.38 | D9: 165.94 | H9: 63.8 | L9: 370 | M9: =C9+D9+E9+F9+G9+H9+I9+J9+L9+K9 -> 1834.12 | N9: =L9-O9 -> 370.3 | O9: =M9-B9-F9 -> -0.3
A10: 45208 | B10: 992.1 | C10: 662.6 | D10: 66.2 | H10: 18.9 | L10: 250 | M10: =C10+D10+E10+F10+G10+H10+I10+J10+L10+K10 -> 997.7 | N10: =L10-O10 -> 244.4 | O10: =M10-B10-F10 -> 5.6
A11: 45209 | B11: 1419.48 | C11: 549.42 | D11: 88.7 | H11: 54.8 | K11: =507.78+54.58 -> 562.36 | L11: 165 | M11: =C11+D11+E11+F11+G11+H11+I11+J11+L11+K11 -> 1420.28 | N11: =L11-O11 -> 164.2 | O11: =M11-B11-F11 -> 0.8
A12: 45210 | B12: 963.44 | C12: 528.33 | D12: 24.8 | K12: =180.75 -> 180.75 | L12: 230 | M12: =C12+D12+E12+F12+G12+H12+I12+J12+L12+K12 -> 963.88 | N12: =L12-O12 -> 229.56 | O12: =M12-B12-F12 -> 0.44
A13: 45211 | B13: 656.9 | C13: 426.1 | D13: 45 | L13: 185 | M13: =C13+D13+E13+F13+G13+H13+I13+J13+L13+K13 -> 656.1 | N13: =L13-O13 -> 185.8 | O13: =M13-B13-F13 -> -0.8
A14: 45212 | B14: 588.75 | C14: 257.1 | D14: 0 | H14: 74.7 | K14: 71.95 | L14: 180 | M14: =C14+D14+E14+F14+G14+H14+I14+J14+L14+K14 -> 583.75 | N14: =L14-O14 -> 185 | O14: =M14-B14-F14 -> -5
A15: 45213 | B15: 1964.78 | C15: 1133.78 | D15: 158.6 | H15: 75.8 | L15: 595 | M15: =C15+D15+E15+F15+G15+H15+I15+J15+L15+K15 -> 1963.18 | N15: =L15-O15 -> 596.6 | O15: =M15-B15-F15 -> -1.6
A16: 45214 | B16: 568.42 | C16: 313.96 | D16: 68.96 | H16: 89.6 | L16: 95 | M16: =C16+D16+E16+F16+G16+H16+I16+J16+L16+K16 -> 567.52 | N16: =L16-O16 -> 95.9 | O16: =M16-B16-F16 -> -0.9
A17: 45215 | B17: 227.4 | C17: 139.7 | D17: 29.2 | L17: 60 | M17: =C17+D17+E17+F17+G17+H17+I17+J17+L17+K17 -> 228.9 | N17: =L17-O17 -> 58.5 | O17: =M17-B17-F17 -> 1.5
A18: 45216 | B18: 118.3 | C18: 43.9 | D18: 1 | H18: 32.9 | L18: 40 | M18: =C18+D18+E18+F18+G18+H18+I18+J18+L18+K18 -> 117.8 | N18: =L18-O18 -> 40.5 | O18: =M18-B18-F18 -> -0.5
A19: 45217 | B19: 94.82 | C19: 32.8 | D19: 0 | L19: 65 | M19: =C19+D19+E19+F19+G19+H19+I19+J19+L19+K19 -> 97.8 | N19: =L19-O19 -> 62.02 | O19: =M19-B19-F19 -> 2.98
A20: 45218 | B20: 191.4 | C20: 142.2 | D20: 5.8 | L20: 45 | M20: =C20+D20+E20+F20+G20+H20+I20+J20+L20+K20 -> 193 | N20: =L20-O20 -> 43.4 | O20: =M20-B20-F20 -> 1.6
A21: 45219 | B21: 190.38 | C21: 139.38 | D21: 0 | L21: 50 | M21: =C21+D21+E21+F21+G21+H21+I21+J21+L21+K21 -> 189.38 | N21: =L21-O21 -> 51 | O21: =M21-B21-F21 -> -1
A22: 45220 | B22: 1289 | C22: 829.49 | D22: 72.4 | H22: 109.5 | L22: 280 | M22: =C22+D22+E22+F22+G22+H22+I22+J22+L22+K22 -> 1291.39 | N22: =L22-O22 -> 277.61 | O22: =M22-B22-F22 -> 2.39
A23: 45221 | B23: 1148.88 | C23: 761.2 | D23: 94.9 | H23: 37.8 | L23: 260 | M23: =C23+D23+E23+F23+G23+H23+I23+J23+L23+K23 -> 1153.9 | N23: =L23-O23 -> 254.98 | O23: =M23-B23-F23 -> 5.02
A24: 45222 | B24: 55.49 | C24: 55.49 | D24: 0 | L24: 0 | M24: =C24+D24+E24+F24+G24+H24+I24+J24+L24+K24 -> 55.49 | N24: =L24-O24 -> 0 | O24: =M24-B24-F24 -> 0
A25: 45223 | B25: 0 | M25: =C25+D25+E25+F25+G25+H25+I25+J25+L25+K25 -> 0 | N25: =L25-O25 -> 0 | O25: =M25-B25-F25 -> 0
A26: 45224 | B26: 0 | M26: =C26+D26+E26+F26+G26+H26+I26+J26+L26+K26 -> 0 | N26: =L26-O26 -> 0 | O26: =M26-B26-F26 -> 0
A27: 45225 | B27: 383.56 | C27: 190.72 | D27: 0 | K27: =81+33.44 -> 114.44 | L27: 80 | M27: =C27+D27+E27+F27+G27+H27+I27+J27+L27+K27 -> 385.16 | N27: =L27-O27 -> 78.4 | O27: =M27-B27-F27 -> 1.6
A28: 45226 | B28: 426.99 | C28: 206.96 | D28: 7.8 | H28: 52.9 | L28: 160 | M28: =C28+D28+E28+F28+G28+H28+I28+J28+L28+K28 -> 427.66 | N28: =L28-O28 -> 159.33 | O28: =M28-B28-F28 -> 0.67
A29: 45227 | B29: 538.22 | C29: 426.82 | D29: 34.3 | H29: 51.8 | L29: 30 | M29: =C29+D29+E29+F29+G29+H29+I29+J29+L29+K29 -> 542.92 | N29: =L29-O29 -> 25.3 | O29: =M29-B29-F29 -> 4.7
A30: 45228 | B30: 523.79 | C30: 362.33 | D30: 24.68 | H30: 37.8 | L30: 100 | M30: =C30+D30+E30+F30+G30+H30+I30+J30+L30+K30 -> 524.81 | N30: =L30-O30 -> 98.98 | O30: =M30-B30-F30 -> 1.02
A31: 45229 | B31: 202.4 | C31: 144.5 | D31: 17.8 | L31: 40 | M31: =C31+D31+E31+F31+G31+H31+I31+J31+L31+K31 -> 202.3 | N31: =L31-O31 -> 40.1 | O31: =M31-B31-F31 -> -0.1
A32: 45230 | B32: 346.05 | C32: 262.05 | D32: 14.4 | L32: 70 | M32: =C32+D32+E32+F32+G32+H32+I32+J32+L32+K32 -> 346.45 | N32: =L32-O32 -> 69.6 | O32: =M32-B32-F32 -> 0.4
A33: TOTAL | M33: =SUM(M2:M32) -> 25896.89 | N33: =M33-O33 -> 25861.77 | O33: =SUM(O2:O32) -> 35.12

Sheet Set 24 Mat
B2: Loja | C2: FECHO TOTAL | D2: FECHO MATOSINHOS | E2: SALT PAY | F2: SANTANDER | G2: GASTOS C/RECIBO | H2: GASTOS S/RECIBO | I2: GLOVO | J2: UBER EATS | K2: VOLUP | L2: BOLT | M2: Transf. Bancária | N2: TIME OUT MARKET | O2: NUMERARIO | P2: TOTAL | Q2: DEPOSITO | R2: EXTRA | S2: FUNDO CAIXA
A3: 45536 | B3: Matosinhos;TimeOut;Bolhão | C3: =D3+N3 -> 4214.61 | D3: 3774.01 | E3: 1563.52 | F3: 150.4 | J3: 136.5 | M3: =732+816.39 -> 1548.39 | N3: 440.6 | O3: 380 | P3: =E3+F3+G3+H3+I3+J3+K3+L3+O3+M3+N3 -> 4219.41 | Q3: =O3-R3 -> 375.2 | R3: =P3-C3-H3 -> 4.8
A4: 45537 | B4: Matosinhos | C4: =D4+N4 -> 1254.34 | D4: 943.8 | E4: 509.8 | F4: 142.9 | J4: 51.8 | N4: 310.54 | O4: 240 | P4: =E4+F4+G4+H4+I4+J4+K4+L4+O4+M4+N4 -> 1255.04 | Q4: =O4-R4 -> 239.3 | R4: =P4-C4-H4 -> 0.7
A5: 45538 | B5: Matosinhos | C5: =D5+N5 -> 1276.96 | D5: 891.76 | E5: 555.78 | F5: 86.4 | J5: 32.9 | N5: 385.2 | O5: 215 | P5: =E5+F5+G5+H5+I5+J5+K5+L5+O5+M5+N5 -> 1275.28 | Q5: =O5-R5 -> 216.68 | R5: =P5-C5-H5 -> -1.68
A6: 45539 | B6: Matosinhos | C6: =D6+N6 -> 1603.7 | D6: 1104.5 | E6: 760.22 | F6: 98.3 | N6: 499.2 | O6: 245 | P6: =E6+F6+G6+H6+I6+J6+K6+L6+O6+M6+N6 -> 1602.72 | Q6: =O6-R6 -> 245.98 | R6: =P6-C6-H6 -> -0.98
A7: 45540 | B7: Matosinhos | C7: =D7+N7 -> 1407.62 | D7: 1150.22 | E7: 481.52 | F7: 100.09 | J7: 159.4 | M7: =128.63+91.81+27.7 -> 248.14 | N7: 257.4 | O7: 160 | P7: =E7+F7+G7+H7+I7+J7+K7+L7+O7+M7+N7 -> 1406.55 | Q7: =O7-R7 -> 161.07 | R7: =P7-C7-H7 -> -1.07
A8: 45541 | B8: Matosinhos | C8: =D8+N8 -> 1353.6 | D8: 859.21 | E8: 466.85 | F8: 73.46 | J8: 70.7 | N8: 494.39 | O8: 250 | P8: =E8+F8+G8+H8+I8+J8+K8+L8+O8+M8+N8 -> 1355.4 | Q8: =O8-R8 -> 248.2 | R8: =P8-C8-H8 -> 1.8
A9: 45542 | C9: =D9+N9 -> 2660.24 | D9: 1772.44 | E9: 1189.17 | F9: 233.74 | J9: 51.8 | N9: 887.8 | O9: 280 | P9: =E9+F9+G9+H9+I9+J9+K9+L9+O9+M9+N9 -> 2642.51 | Q9: =O9-R9 -> 297.73 | R9: =P9-C9-H9 -> -17.73
A10: 45543 | C10: =D10+N10 -> 2254.8 | D10: 1778 | E10: 1233.5 | F10: 184.3 | J10: 70.7 | N10: 476.8 | O10: 270 | P10: =E10+F10+G10+H10+I10+J10+K10+L10+O10+M10+N10 -> 2235.3 | Q10: =O10-R10 -> 289.5 | R10: =P10-C10-H10 -> -19.5
A11: 45544 | C11: =D11+N11 -> 1151.54 | D11: 843.54 | E11: 578.34 | F11: 69.5 | N11: 308 | O11: 195 | P11: =E11+F11+G11+H11+I11+J11+K11+L11+O11+M11+N11 -> 1150.84 | Q11: =O11-R11 -> 195.7 | R11: =P11-C11-H11 -> -0.7
A12: 45545 | C12: =D12+N12 -> 984.73 | D12: 739.53 | E12: 550.23 | F12: 39.2 | J12: 32.9 | N12: 245.2 | O12: 120 | P12: =E12+F12+G12+H12+I12+J12+K12+L12+O12+M12+N12 -> 987.53 | Q12: =O12-R12 -> 117.2 | R12: =P12-C12-H12 -> 2.8
A13: 45546 | C13: =D13+N13 -> 1625.2 | D13: 1269.8 | E13: 572.34 | F13: 79.1 | J13: 51.8 | M13: 441.76 | N13: 355.4 | O13: 130 | P13: =E13+F13+G13+H13+I13+J13+K13+L13+O13+M13+N13 -> 1630.4 | Q13: =O13-R13 -> 124.8 | R13: =P13-C13-H13 -> 5.2
A14: 45547 | C14: =D14+N14 -> 2002.72 | D14: 1745.32 | E14: 464.38 | F14: 132.9 | J14: 32.9 | M14: 1006.14 | N14: 257.4 | O14: 100 | P14: =E14+F14+G14+H14+I14+J14+K14+L14+O14+M14+N14 -> 1993.72 | Q14: =O14-R14 -> 109 | R14: =P14-C14-H14 -> -9
A15: 45548 | C15: =D15+N15 -> 2126.06 | D15: 1665.06 | E15: 1068.36 | F15: 132.7 | J15: 67.8 | M15: 55.68 | N15: 461 | O15: 310 | P15: =E15+F15+G15+H15+I15+J15+K15+L15+O15+M15+N15 -> 2095.54 | Q15: =O15-R15 -> 340.52 | R15: =P15-C15-H15 -> -30.52
A16: 45549 | C16: =D16+N16 -> 3399.53 | D16: 2886.73 | E16: 1473.17 | F16: 334.37 | I16: 18.9 | J16: 122.5 | M16: 473.14 | N16: 512.8 | O16: 450 | P16: =E16+F16+G16+H16+I16+J16+K16+L16+O16+M16+N16 -> 3384.88 | Q16: =O16-R16 -> 464.65 | R16: =P16-C16-H16 -> -14.65
